Workbook

Sheet Start here
A1: Debt Payoff Planner (Snowball / Avalanche)
A2: Free template · templates.snoutsmith.com
B4: WHAT IT DOES
B5: List up to 10 debts, pick snowball (smallest balance first) or avalanche (highest rate first), add an extra monthly amount, and see the payoff order, the month each debt is paid off and your debt-free date – simulated month by month.
B7: HOW TO USE
B8: 1. Enter each debt on Plan: balance, yearly interest rate, minimum payment.
B9: 2. Choose the method in B4, your extra monthly payment in B5 and the start month in B6.
B10: 3. Plan shows the order, the month each debt is gone and the debt-free date. Schedule shows every month's balances.
B12: GOOD TO KNOW
B13: • The simulation pays every minimum, puts the extra (plus minimums freed by paid-off debts) on the debt in focus, and adds monthly interest.
B14: • Estimates assume fixed rates and no new charges. A planning tool, not financial advice.
B16: Tinted cells are yours to type in. Grey numbers are formulas – leave them. Works in Google Sheets (File → Import or open the .xlsx) and Excel, free plans, no add-ons or scripts.

Sheet Plan
A1: Debt payoff plan
A2: Simulated month by month – estimates, not financial advice
A4: Method | B4: Snowball
A5: Extra per month | B5: 200
A6: Start month | B6: 46327
A8: Debt | B8: Balance | C8: Rate / yr | D8: Min payment | E8: Order | F8: Paid off in month | G8: Paid off
A9: Credit card A | B9: 3200 | C9: 0.229 | D9: 95 | E9: =IF(N(B9)=0,"",IF($B$4="Avalanche",COUNTIFS($B$9:$B$18,">0",$C$9:$C$18,">"&C9)+COUNTIFS($B$9:$B$18,">0",$C$9:$C$18,C9,$B$9:$B$18,"<"&B9)+COUNTIFS($A$9:A9,"<>",$B$9:B9,B9,$C$9:C9,C9),COUNTIFS($B$9:$B$18,">0",$B$9:$B$18,"<"&B9)+COUNTIFS($B$9:B9,B9))) | F9: =IF(N(B9)=0,"",IF(INDEX(Schedule!B$5:B$244,240)>0,"over 20 years",COUNTIF(Schedule!B$5:B$244,">0")+1)) | G9: =IF(ISNUMBER(F9),DATE(YEAR($B$6),MONTH($B$6)+F9-1,1),"")
A10: Store card | B10: 850 | C10: 0.269 | D10: 35 | E10: =IF(N(B10)=0,"",IF($B$4="Avalanche",COUNTIFS($B$9:$B$18,">0",$C$9:$C$18,">"&C10)+COUNTIFS($B$9:$B$18,">0",$C$9:$C$18,C10,$B$9:$B$18,"<"&B10)+COUNTIFS($A$9:A10,"<>",$B$9:B10,B10,$C$9:C10,C10),COUNTIFS($B$9:$B$18,">0",$B$9:$B$18,"<"&B10)+COUNTIFS($B$9:B10,B10))) | F10: =IF(N(B10)=0,"",IF(INDEX(Schedule!C$5:C$244,240)>0,"over 20 years",COUNTIF(Schedule!C$5:C$244,">0")+1)) | G10: =IF(ISNUMBER(F10),DATE(YEAR($B$6),MONTH($B$6)+F10-1,1),"")
A11: Car loan | B11: 9400 | C11: 0.069 | D11: 260 | E11: =IF(N(B11)=0,"",IF($B$4="Avalanche",COUNTIFS($B$9:$B$18,">0",$C$9:$C$18,">"&C11)+COUNTIFS($B$9:$B$18,">0",$C$9:$C$18,C11,$B$9:$B$18,"<"&B11)+COUNTIFS($A$9:A11,"<>",$B$9:B11,B11,$C$9:C11,C11),COUNTIFS($B$9:$B$18,">0",$B$9:$B$18,"<"&B11)+COUNTIFS($B$9:B11,B11))) | F11: =IF(N(B11)=0,"",IF(INDEX(Schedule!D$5:D$244,240)>0,"over 20 years",COUNTIF(Schedule!D$5:D$244,">0")+1)) | G11: =IF(ISNUMBER(F11),DATE(YEAR($B$6),MONTH($B$6)+F11-1,1),"")
A12: Student loan | B12: 14800 | C12: 0.049 | D12: 170 | E12: =IF(N(B12)=0,"",IF($B$4="Avalanche",COUNTIFS($B$9:$B$18,">0",$C$9:$C$18,">"&C12)+COUNTIFS($B$9:$B$18,">0",$C$9:$C$18,C12,$B$9:$B$18,"<"&B12)+COUNTIFS($A$9:A12,"<>",$B$9:B12,B12,$C$9:C12,C12),COUNTIFS($B$9:$B$18,">0",$B$9:$B$18,"<"&B12)+COUNTIFS($B$9:B12,B12))) | F12: =IF(N(B12)=0,"",IF(INDEX(Schedule!E$5:E$244,240)>0,"over 20 years",COUNTIF(Schedule!E$5:E$244,">0")+1)) | G12: =IF(ISNUMBER(F12),DATE(YEAR($B$6),MONTH($B$6)+F12-1,1),"")
A13: Personal loan | B13: 4100 | C13: 0.119 | D13: 140 | E13: =IF(N(B13)=0,"",IF($B$4="Avalanche",COUNTIFS($B$9:$B$18,">0",$C$9:$C$18,">"&C13)+COUNTIFS($B$9:$B$18,">0",$C$9:$C$18,C13,$B$9:$B$18,"<"&B13)+COUNTIFS($A$9:A13,"<>",$B$9:B13,B13,$C$9:C13,C13),COUNTIFS($B$9:$B$18,">0",$B$9:$B$18,"<"&B13)+COUNTIFS($B$9:B13,B13))) | F13: =IF(N(B13)=0,"",IF(INDEX(Schedule!F$5:F$244,240)>0,"over 20 years",COUNTIF(Schedule!F$5:F$244,">0")+1)) | G13: =IF(ISNUMBER(F13),DATE(YEAR($B$6),MONTH($B$6)+F13-1,1),"")
A14: Credit card B | B14: 1900 | C14: 0.199 | D14: 60 | E14: =IF(N(B14)=0,"",IF($B$4="Avalanche",COUNTIFS($B$9:$B$18,">0",$C$9:$C$18,">"&C14)+COUNTIFS($B$9:$B$18,">0",$C$9:$C$18,C14,$B$9:$B$18,"<"&B14)+COUNTIFS($A$9:A14,"<>",$B$9:B14,B14,$C$9:C14,C14),COUNTIFS($B$9:$B$18,">0",$B$9:$B$18,"<"&B14)+COUNTIFS($B$9:B14,B14))) | F14: =IF(N(B14)=0,"",IF(INDEX(Schedule!G$5:G$244,240)>0,"over 20 years",COUNTIF(Schedule!G$5:G$244,">0")+1)) | G14: =IF(ISNUMBER(F14),DATE(YEAR($B$6),MONTH($B$6)+F14-1,1),"")
E15: =IF(N(B15)=0,"",IF($B$4="Avalanche",COUNTIFS($B$9:$B$18,">0",$C$9:$C$18,">"&C15)+COUNTIFS($B$9:$B$18,">0",$C$9:$C$18,C15,$B$9:$B$18,"<"&B15)+COUNTIFS($A$9:A15,"<>",$B$9:B15,B15,$C$9:C15,C15),COUNTIFS($B$9:$B$18,">0",$B$9:$B$18,"<"&B15)+COUNTIFS($B$9:B15,B15))) | F15: =IF(N(B15)=0,"",IF(INDEX(Schedule!H$5:H$244,240)>0,"over 20 years",COUNTIF(Schedule!H$5:H$244,">0")+1)) | G15: =IF(ISNUMBER(F15),DATE(YEAR($B$6),MONTH($B$6)+F15-1,1),"")
E16: =IF(N(B16)=0,"",IF($B$4="Avalanche",COUNTIFS($B$9:$B$18,">0",$C$9:$C$18,">"&C16)+COUNTIFS($B$9:$B$18,">0",$C$9:$C$18,C16,$B$9:$B$18,"<"&B16)+COUNTIFS($A$9:A16,"<>",$B$9:B16,B16,$C$9:C16,C16),COUNTIFS($B$9:$B$18,">0",$B$9:$B$18,"<"&B16)+COUNTIFS($B$9:B16,B16))) | F16: =IF(N(B16)=0,"",IF(INDEX(Schedule!I$5:I$244,240)>0,"over 20 years",COUNTIF(Schedule!I$5:I$244,">0")+1)) | G16: =IF(ISNUMBER(F16),DATE(YEAR($B$6),MONTH($B$6)+F16-1,1),"")
E17: =IF(N(B17)=0,"",IF($B$4="Avalanche",COUNTIFS($B$9:$B$18,">0",$C$9:$C$18,">"&C17)+COUNTIFS($B$9:$B$18,">0",$C$9:$C$18,C17,$B$9:$B$18,"<"&B17)+COUNTIFS($A$9:A17,"<>",$B$9:B17,B17,$C$9:C17,C17),COUNTIFS($B$9:$B$18,">0",$B$9:$B$18,"<"&B17)+COUNTIFS($B$9:B17,B17))) | F17: =IF(N(B17)=0,"",IF(INDEX(Schedule!J$5:J$244,240)>0,"over 20 years",COUNTIF(Schedule!J$5:J$244,">0")+1)) | G17: =IF(ISNUMBER(F17),DATE(YEAR($B$6),MONTH($B$6)+F17-1,1),"")
E18: =IF(N(B18)=0,"",IF($B$4="Avalanche",COUNTIFS($B$9:$B$18,">0",$C$9:$C$18,">"&C18)+COUNTIFS($B$9:$B$18,">0",$C$9:$C$18,C18,$B$9:$B$18,"<"&B18)+COUNTIFS($A$9:A18,"<>",$B$9:B18,B18,$C$9:C18,C18),COUNTIFS($B$9:$B$18,">0",$B$9:$B$18,"<"&B18)+COUNTIFS($B$9:B18,B18))) | F18: =IF(N(B18)=0,"",IF(INDEX(Schedule!K$5:K$244,240)>0,"over 20 years",COUNTIF(Schedule!K$5:K$244,">0")+1)) | G18: =IF(ISNUMBER(F18),DATE(YEAR($B$6),MONTH($B$6)+F18-1,1),"")
A19: Total | B19: =SUM(B9:B18) | D19: =SUM(D9:D18)
A21: DEBT-FREE
A22: Month number | B22: =IF(COUNT(F9:F18)<COUNT(B9:B18),"over 20 years",MAX(F9:F18))
A23: Date | B23: =IF(ISNUMBER(B22),DATE(YEAR(B6),MONTH(B6)+B22-1,1),"")
A24: Total paid (approx.) | B24: =SUM(Schedule!M5:M244)
A25: Interest (approx.) | B25: =B24-B19

Sheet Schedule
A1: Schedule
A2: Balance of each debt at the end of every month
A4: Month | B4: Debt 1 | C4: Debt 2 | D4: Debt 3 | E4: Debt 4 | F4: Debt 5 | G4: Debt 6 | H4: Debt 7 | I4: Debt 8 | J4: Debt 9 | K4: Debt 10 | L4: Focus | M4: Paid
A5: 1 | B5: =IF(N(Plan!$B$9)<=0,0,MAX(0,Plan!$B$9*(1+Plan!$C$9/12)-(Plan!$D$9+IF(Plan!$E$9=$L5,Plan!$B$5+IF(AND(N(Plan!$B$9)>0,N(Plan!$B$9)<=0),Plan!$D$9,0)+IF(AND(N(Plan!$B$10)>0,N(Plan!$B$10)<=0),Plan!$D$10,0)+IF(AND(N(Plan!$B$11)>0,N(Plan!$B$11)<=0),Plan!$D$11,0)+IF(AND(N(Plan!$B$12)>0,N(Plan!$B$12)<=0),Plan!$D$12,0)+IF(AND(N(Plan!$B$13)>0,N(Plan!$B$13)<=0),Plan!$D$13,0)+IF(AND(N(Plan!$B$14)>0,N(Plan!$B$14)<=0),Plan!$D$14,0)+IF(AND(N(Plan!$B$15)>0,N(Plan!$B$15)<=0),Plan!$D$15,0)+IF(AND(N(Plan!$B$16)>0,N(Plan!$B$16)<=0),Plan!$D$16,0)+IF(AND(N(Plan!$B$17)>0,N(Plan!$B$17)<=0),Plan!$D$17,0)+IF(AND(N(Plan!$B$18)>0,N(Plan!$B$18)<=0),Plan!$D$18,0),0)))) | C5: =IF(N(Plan!$B$10)<=0,0,MAX(0,Plan!$B$10*(1+Plan!$C$10/12)-(Plan!$D$10+IF(Plan!$E$10=$L5,Plan!$B$5+IF(AND(N(Plan!$B$9)>0,N(Plan!$B$9)<=0),Plan!$D$9,0)+IF(AND(N(Plan!$B$10)>0,N(Plan!$B$10)<=0),Plan!$D$10,0)+IF(AND(N(Plan!$B$11)>0,N(Plan!$B$11)<=0),Plan!$D$11,0)+IF(AND(N(Plan!$B$12)>0,N(Plan!$B$12)<=0),Plan!$D$12,0)+IF(AND(N(Plan!$B$13)>0,N(Plan!$B$13)<=0),Plan!$D$13,0)+IF(AND(N(Plan!$B$14)>0,N(Plan!$B$14)<=0),Plan!$D$14,0)+IF(AND(N(Plan!$B$15)>0,N(Plan!$B$15)<=0),Plan!$D$15,0)+IF(AND(N(Plan!$B$16)>0,N(Plan!$B$16)<=0),Plan!$D$16,0)+IF(AND(N(Plan!$B$17)>0,N(Plan!$B$17)<=0),Plan!$D$17,0)+IF(AND(N(Plan!$B$18)>0,N(Plan!$B$18)<=0),Plan!$D$18,0),0)))) | D5: =IF(N(Plan!$B$11)<=0,0,MAX(0,Plan!$B$11*(1+Plan!$C$11/12)-(Plan!$D$11+IF(Plan!$E$11=$L5,Plan!$B$5+IF(AND(N(Plan!$B$9)>0,N(Plan!$B$9)<=0),Plan!$D$9,0)+IF(AND(N(Plan!$B$10)>0,N(Plan!$B$10)<=0),Plan!$D$10,0)+IF(AND(N(Plan!$B$11)>0,N(Plan!$B$11)<=0),Plan!$D$11,0)+IF(AND(N(Plan!$B$12)>0,N(Plan!$B$12)<=0),Plan!$D$12,0)+IF(AND(N(Plan!$B$13)>0,N(Plan!$B$13)<=0),Plan!$D$13,0)+IF(AND(N(Plan!$B$14)>0,N(Plan!$B$14)<=0),Plan!$D$14,0)+IF(AND(N(Plan!$B$15)>0,N(Plan!$B$15)<=0),Plan!$D$15,0)+IF(AND(N(Plan!$B$16)>0,N(Plan!$B$16)<=0),Plan!$D$16,0)+IF(AND(N(Plan!$B$17)>0,N(Plan!$B$17)<=0),Plan!$D$17,0)+IF(AND(N(Plan!$B$18)>0,N(Plan!$B$18)<=0),Plan!$D$18,0),0)))) | E5: =IF(N(Plan!$B$12)<=0,0,MAX(0,Plan!$B$12*(1+Plan!$C$12/12)-(Plan!$D$12+IF(Plan!$E$12=$L5,Plan!$B$5+IF(AND(N(Plan!$B$9)>0,N(Plan!$B$9)<=0),Plan!$D$9,0)+IF(AND(N(Plan!$B$10)>0,N(Plan!$B$10)<=0),Plan!$D$10,0)+IF(AND(N(Plan!$B$11)>0,N(Plan!$B$11)<=0),Plan!$D$11,0)+IF(AND(N(Plan!$B$12)>0,N(Plan!$B$12)<=0),Plan!$D$12,0)+IF(AND(N(Plan!$B$13)>0,N(Plan!$B$13)<=0),Plan!$D$13,0)+IF(AND(N(Plan!$B$14)>0,N(Plan!$B$14)<=0),Plan!$D$14,0)+IF(AND(N(Plan!$B$15)>0,N(Plan!$B$15)<=0),Plan!$D$15,0)+IF(AND(N(Plan!$B$16)>0,N(Plan!$B$16)<=0),Plan!$D$16,0)+IF(AND(N(Plan!$B$17)>0,N(Plan!$B$17)<=0),Plan!$D$17,0)+IF(AND(N(Plan!$B$18)>0,N(Plan!$B$18)<=0),Plan!$D$18,0),0)))) | F5: =IF(N(Plan!$B$13)<=0,0,MAX(0,Plan!$B$13*(1+Plan!$C$13/12)-(Plan!$D$13+IF(Plan!$E$13=$L5,Plan!$B$5+IF(AND(N(Plan!$B$9)>0,N(Plan!$B$9)<=0),Plan!$D$9,0)+IF(AND(N(Plan!$B$10)>0,N(Plan!$B$10)<=0),Plan!$D$10,0)+IF(AND(N(Plan!$B$11)>0,N(Plan!$B$11)<=0),Plan!$D$11,0)+IF(AND(N(Plan!$B$12)>0,N(Plan!$B$12)<=0),Plan!$D$12,0)+IF(AND(N(Plan!$B$13)>0,N(Plan!$B$13)<=0),Plan!$D$13,0)+IF(AND(N(Plan!$B$14)>0,N(Plan!$B$14)<=0),Plan!$D$14,0)+IF(AND(N(Plan!$B$15)>0,N(Plan!$B$15)<=0),Plan!$D$15,0)+IF(AND(N(Plan!$B$16)>0,N(Plan!$B$16)<=0),Plan!$D$16,0)+IF(AND(N(Plan!$B$17)>0,N(Plan!$B$17)<=0),Plan!$D$17,0)+IF(AND(N(Plan!$B$18)>0,N(Plan!$B$18)<=0),Plan!$D$18,0),0)))) | G5: =IF(N(Plan!$B$14)<=0,0,MAX(0,Plan!$B$14*(1+Plan!$C$14/12)-(Plan!$D$14+IF(Plan!$E$14=$L5,Plan!$B$5+IF(AND(N(Plan!$B$9)>0,N(Plan!$B$9)<=0),Plan!$D$9,0)+IF(AND(N(Plan!$B$10)>0,N(Plan!$B$10)<=0),Plan!$D$10,0)+IF(AND(N(Plan!$B$11)>0,N(Plan!$B$11)<=0),Plan!$D$11,0)+IF(AND(N(Plan!$B$12)>0,N(Plan!$B$12)<=0),Plan!$D$12,0)+IF(AND(N(Plan!$B$13)>0,N(Plan!$B$13)<=0),Plan!$D$13,0)+IF(AND(N(Plan!$B$14)>0,N(Plan!$B$14)<=0),Plan!$D$14,0)+IF(AND(N(Plan!$B$15)>0,N(Plan!$B$15)<=0),Plan!$D$15,0)+IF(AND(N(Plan!$B$16)>0,N(Plan!$B$16)<=0),Plan!$D$16,0)+IF(AND(N(Plan!$B$17)>0,N(Plan!$B$17)<=0),Plan!$D$17,0)+IF(AND(N(Plan!$B$18)>0,N(Plan!$B$18)<=0),Plan!$D$18,0),0)))) | H5: =IF(N(Plan!$B$15)<=0,0,MAX(0,Plan!$B$15*(1+Plan!$C$15/12)-(Plan!$D$15+IF(Plan!$E$15=$L5,Plan!$B$5+IF(AND(N(Plan!$B$9)>0,N(Plan!$B$9)<=0),Plan!$D$9,0)+IF(AND(N(Plan!$B$10)>0,N(Plan!$B$10)<=0),Plan!$D$10,0)+IF(AND(N(Plan!$B$11)>0,N(Plan!$B$11)<=0),Plan!$D$11,0)+IF(AND(N(Plan!$B$12)>0,N(Plan!$B$12)<=0),Plan!$D$12,0)+IF(AND(N(Plan!$B$13)>0,N(Plan!$B$13)<=0),Plan!$D$13,0)+IF(AND(N(Plan!$B$14)>0,N(Plan!$B$14)<=0),Plan!$D$14,0)+IF(AND(N(Plan!$B$15)>0,N(Plan!$B$15)<=0),Plan!$D$15,0)+IF(AND(N(Plan!$B$16)>0,N(Plan!$B$16)<=0),Plan!$D$16,0)+IF(AND(N(Plan!$B$17)>0,N(Plan!$B$17)<=0),Plan!$D$17,0)+IF(AND(N(Plan!$B$18)>0,N(Plan!$B$18)<=0),Plan!$D$18,0),0)))) | I5: =IF(N(Plan!$B$16)<=0,0,MAX(0,Plan!$B$16*(1+Plan!$C$16/12)-(Plan!$D$16+IF(Plan!$E$16=$L5,Plan!$B$5+IF(AND(N(Plan!$B$9)>0,N(Plan!$B$9)<=0),Plan!$D$9,0)+IF(AND(N(Plan!$B$10)>0,N(Plan!$B$10)<=0),Plan!$D$10,0)+IF(AND(N(Plan!$B$11)>0,N(Plan!$B$11)<=0),Plan!$D$11,0)+IF(AND(N(Plan!$B$12)>0,N(Plan!$B$12)<=0),Plan!$D$12,0)+IF(AND(N(Plan!$B$13)>0,N(Plan!$B$13)<=0),Plan!$D$13,0)+IF(AND(N(Plan!$B$14)>0,N(Plan!$B$14)<=0),Plan!$D$14,0)+IF(AND(N(Plan!$B$15)>0,N(Plan!$B$15)<=0),Plan!$D$15,0)+IF(AND(N(Plan!$B$16)>0,N(Plan!$B$16)<=0),Plan!$D$16,0)+IF(AND(N(Plan!$B$17)>0,N(Plan!$B$17)<=0),Plan!$D$17,0)+IF(AND(N(Plan!$B$18)>0,N(Plan!$B$18)<=0),Plan!$D$18,0),0)))) | J5: =IF(N(Plan!$B$17)<=0,0,MAX(0,Plan!$B$17*(1+Plan!$C$17/12)-(Plan!$D$17+IF(Plan!$E$17=$L5,Plan!$B$5+IF(AND(N(Plan!$B$9)>0,N(Plan!$B$9)<=0),Plan!$D$9,0)+IF(AND(N(Plan!$B$10)>0,N(Plan!$B$10)<=0),Plan!$D$10,0)+IF(AND(N(Plan!$B$11)>0,N(Plan!$B$11)<=0),Plan!$D$11,0)+IF(AND(N(Plan!$B$12)>0,N(Plan!$B$12)<=0),Plan!$D$12,0)+IF(AND(N(Plan!$B$13)>0,N(Plan!$B$13)<=0),Plan!$D$13,0)+IF(AND(N(Plan!$B$14)>0,N(Plan!$B$14)<=0),Plan!$D$14,0)+IF(AND(N(Plan!$B$15)>0,N(Plan!$B$15)<=0),Plan!$D$15,0)+IF(AND(N(Plan!$B$16)>0,N(Plan!$B$16)<=0),Plan!$D$16,0)+IF(AND(N(Plan!$B$17)>0,N(Plan!$B$17)<=0),Plan!$D$17,0)+IF(AND(N(Plan!$B$18)>0,N(Plan!$B$18)<=0),Plan!$D$18,0),0)))) | K5: =IF(N(Plan!$B$18)<=0,0,MAX(0,Plan!$B$18*(1+Plan!$C$18/12)-(Plan!$D$18+IF(Plan!$E$18=$L5,Plan!$B$5+IF(AND(N(Plan!$B$9)>0,N(Plan!$B$9)<=0),Plan!$D$9,0)+IF(AND(N(Plan!$B$10)>0,N(Plan!$B$10)<=0),Plan!$D$10,0)+IF(AND(N(Plan!$B$11)>0,N(Plan!$B$11)<=0),Plan!$D$11,0)+IF(AND(N(Plan!$B$12)>0,N(Plan!$B$12)<=0),Plan!$D$12,0)+IF(AND(N(Plan!$B$13)>0,N(Plan!$B$13)<=0),Plan!$D$13,0)+IF(AND(N(Plan!$B$14)>0,N(Plan!$B$14)<=0),Plan!$D$14,0)+IF(AND(N(Plan!$B$15)>0,N(Plan!$B$15)<=0),Plan!$D$15,0)+IF(AND(N(Plan!$B$16)>0,N(Plan!$B$16)<=0),Plan!$D$16,0)+IF(AND(N(Plan!$B$17)>0,N(Plan!$B$17)<=0),Plan!$D$17,0)+IF(AND(N(Plan!$B$18)>0,N(Plan!$B$18)<=0),Plan!$D$18,0),0)))) | L5: =MIN(IF(N(Plan!$B$9)>0,Plan!$E$9,999),IF(N(Plan!$B$10)>0,Plan!$E$10,999),IF(N(Plan!$B$11)>0,Plan!$E$11,999),IF(N(Plan!$B$12)>0,Plan!$E$12,999),IF(N(Plan!$B$13)>0,Plan!$E$13,999),IF(N(Plan!$B$14)>0,Plan!$E$14,999),IF(N(Plan!$B$15)>0,Plan!$E$15,999),IF(N(Plan!$B$16)>0,Plan!$E$16,999),IF(N(Plan!$B$17)>0,Plan!$E$17,999),IF(N(Plan!$B$18)>0,Plan!$E$18,999)) | M5: =IF(N(Plan!$B$9)<=0,0,MIN(Plan!$B$9*(1+Plan!$C$9/12),Plan!$D$9+IF(Plan!$E$9=$L5,Plan!$B$5+IF(AND(N(Plan!$B$9)>0,N(Plan!$B$9)<=0),Plan!$D$9,0)+IF(AND(N(Plan!$B$10)>0,N(Plan!$B$10)<=0),Plan!$D$10,0)+IF(AND(N(Plan!$B$11)>0,N(Plan!$B$11)<=0),Plan!$D$11,0)+IF(AND(N(Plan!$B$12)>0,N(Plan!$B$12)<=0),Plan!$D$12,0)+IF(AND(N(Plan!$B$13)>0,N(Plan!$B$13)<=0),Plan!$D$13,0)+IF(AND(N(Plan!$B$14)>0,N(Plan!$B$14)<=0),Plan!$D$14,0)+IF(AND(N(Plan!$B$15)>0,N(Plan!$B$15)<=0),Plan!$D$15,0)+IF(AND(N(Plan!$B$16)>0,N(Plan!$B$16)<=0),Plan!$D$16,0)+IF(AND(N(Plan!$B$17)>0,N(Plan!$B$17)<=0),Plan!$D$17,0)+IF(AND(N(Plan!$B$18)>0,N(Plan!$B$18)<=0),Plan!$D$18,0),0)))+IF(N(Plan!$B$10)<=0,0,MIN(Plan!$B$10*(1+Plan!$C$10/12),Plan!$D$10+IF(Plan!$E$10=$L5,Plan!$B$5+IF(AND(N(Plan!$B$9)>0,N(Plan!$B$9)<=0),Plan!$D$9,0)+IF(AND(N(Plan!$B$10)>0,N(Plan!$B$10)<=0),Plan!$D$10,0)+IF(AND(N(Plan!$B$11)>0,N(Plan!$B$11)<=0),Plan!$D$11,0)+IF(AND(N(Plan!$B$12)>0,N(Plan!$B$12)<=0),Plan!$D$12,0)+IF(AND(N(Plan!$B$13)>0,N(Plan!$B$13)<=0),Plan!$D$13,0)+IF(AND(N(Plan!$B$14)>0,N(Plan!$B$14)<=0),Plan!$D$14,0)+IF(AND(N(Plan!$B$15)>0,N(Plan!$B$15)<=0),Plan!$D$15,0)+IF(AND(N(Plan!$B$16)>0,N(Plan!$B$16)<=0),Plan!$D$16,0)+IF(AND(N(Plan!$B$17)>0,N(Plan!$B$17)<=0),Plan!$D$17,0)+IF(AND(N(Plan!$B$18)>0,N(Plan!$B$18)<=0),Plan!$D$18,0),0)))+IF(N(Plan!$B$11)<=0,0,MIN(Plan!$B$11*(1+Plan!$C$11/12),Plan!$D$11+IF(Plan!$E$11=$L5,Plan!$B$5+IF(AND(N(Plan!$B$9)>0,N(Plan!$B$9)<=0),Plan!$D$9,0)+IF(AND(N(Plan!$B$10)>0,N(Plan!$B$10)<=0),Plan!$D$10,0)+IF(AND(N(Plan!$B$11)>0,N(Plan!$B$11)<=0),Plan!$D$11,0)+IF(AND(N(Plan!$B$12)>0,N(Plan!$B$12)<=0),Plan!$D$12,0)+IF(AND(N(Plan!$B$13)>0,N(Plan!$B$13)<=0),Plan!$D$13,0)+IF(AND(N(Plan!$B$14)>0,N(Plan!$B$14)<=0),Plan!$D$14,0)+IF(AND(N(Plan!$B$15)>0,N(Plan!$B$15)<=0),Plan!$D$15,0)+IF(AND(N(Plan!$B$16)>0,N(Plan!$B$16)<=0),Plan!$D$16,0)+IF(AND(N(Plan!$B$17)>0,N(Plan!$B$17)<=0),Plan!$D$17,0)+IF(AND(N(Plan!$B$18)>0,N(Plan!$B$18)<=0),Plan!$D$18,0),0)))+IF(N(Plan!$B$12)<=0,0,MIN(Plan!$B$12*(1+Plan!$C$12/12),Plan!$D$12+IF(Plan!$E$12=$L5,Plan!$B$5+IF(AND(N(Plan!$B$9)>0,N(Plan!$B$9)<=0),Plan!$D$9,0)+IF(AND(N(Plan!$B$10)>0,N(Plan!$B$10)<=0),Plan!$D$10,0)+IF(AND(N(Plan!$B$11)>0,N(Plan!$B$11)<=0),Plan!$D$11,0)+IF(AND(N(Plan!$B$12)>0,N(Plan!$B$12)<=0),Plan!$D$12,0)+IF(AND(N(Plan!$B$13)>0,N(Plan!$B$13)<=0),Plan!$D$13,0)+IF(AND(N(Plan!$B$14)>0,N(Plan!$B$14)<=0),Plan!$D$14,0)+IF(AND(N(Plan!$B$15)>0,N(Plan!$B$15)<=0),Plan!$D$15,0)+IF(AND(N(Plan!$B$16)>0,N(Plan!$B$16)<=0),Plan!$D$16,0)+IF(AND(N(Plan!$B$17)>0,N(Plan!$B$17)<=0),Plan!$D$17,0)+IF(AND(N(Plan!$B$18)>0,N(Plan!$B$18)<=0),Plan!$D$18,0),0)))+IF(N(Plan!$B$13)<=0,0,MIN(Plan!$B$13*(1+Plan!$C$13/12),Plan!$D$13+IF(Plan!$E$13=$L5,Plan!$B$5+IF(AND(N(Plan!$B$9)>0,N(Plan!$B$9)<=0),Plan!$D$9,0)+IF(AND(N(Plan!$B$10)>0,N(Plan!$B$10)<=0),Plan!$D$10,0)+IF(AND(N(Plan!$B$11)>0,N(Plan!$B$11)<=0),Plan!$D$11,0)+IF(AND(N(Plan!$B$12)>0,N(Plan!$B$12)<=0),Plan!$D$12,0)+IF(AND(N(Plan!$B$13)>0,N(Plan!$B$13)<=0),Plan!$D$13,0)+IF(AND(N(Plan!$B$14)>0,N(Plan!$B$14)<=0),Plan!$D$14,0)+IF(AND(N(Plan!$B$15)>0,N(Plan!$B$15)<=0),Plan!$D$15,0)+IF(AND(N(Plan!$B$16)>0,N(Plan!$B$16)<=0),Plan!$D$16,0)+IF(AND(N(Plan!$B$17)>0,N(Plan!$B$17)<=0),Plan!$D$17,0)+IF(AND(N(Plan!$B$18)>0,N(Plan!$B$18)<=0),Plan!$D$18,0),0)))+IF(N(Plan!$B$14)<=0,0,MIN(Plan!$B$14*(1+Plan!$C$14/12),Plan!$D$14+IF(Plan!$E$14=$L5,Plan!$B$5+IF(AND(N(Plan!$B$9)>0,N(Plan!$B$9)<=0),Plan!$D$9,0)+IF(AND(N(Plan!$B$10)>0,N(Plan!$B$10)<=0),Plan!$D$10,0)+IF(AND(N(Plan!$B$11)>0,N(Plan!$B$11)<=0),Plan!$D$11,0)+IF(AND(N(Plan!$B$12)>0,N(Plan!$B$12)<=0),Plan!$D$12,0)+IF(AND(N(Plan!$B$13)>0,N(Plan!$B$13)<=0),Plan!$D$13,0)+IF(AND(N(Plan!$B$14)>0,N(Plan!$B$14)<=0),Plan!$D$14,0)+IF(AND(N(Plan!$B$15)>0,N(Plan!$B$15)<=0),Plan!$D$15,0)+IF(AND(N(Plan!$B$16)>0,N(Plan!$B$16)<=0),Plan!$D$16,0)+IF(AND(N(Plan!$B$17)>0,N(Plan!$B$17)<=0),Plan!$D$17,0)+IF(AND(N(Plan!$B$18)>0,N(Plan!$B$18)<=0),Plan!$D$18,0),0)))+IF(N(Plan!$B$15)<=0,0,MIN(Plan!$B$15*(1+Plan!$C$15/12),Plan!$D$15+IF(Plan!$E$15=$L5,Plan!$B$5+IF(AND(N(Plan!$B$9)>0,N(Plan!$B$9)<=0),Plan!$D$9,0)+IF(AND(N(Plan!$B$10)>0,N(Plan!$B$10)<=0),Plan!$D$10,0)+IF(AND(N(Plan!$B$11)>0,N(Plan!$B$11)<=0),Plan!$D$11,0)+IF(AND(N(Plan!$B$12)>0,N(Plan!$B$12)<=0),Plan!$D$12,0)+IF(AND(N(Plan!$B$13)>0,N(Plan!$B$13)<=0),Plan!$D$13,0)+IF(AND(N(Plan!$B$14)>0,N(Plan!$B$14)<=0),Plan!$D$14,0)+IF(AND(N(Plan!$B$15)>0,N(Plan!$B$15)<=0),Plan!$D$15,0)+IF(AND(N(Plan!$B$16)>0,N(Plan!$B$16)<=0),Plan!$D$16,0)+IF(AND(N(Plan!$B$17)>0,N(Plan!$B$17)<=0),Plan!$D$17,0)+IF(AND(N(Plan!$B$18)>0,N(Plan!$B$18)<=0),Plan!$D$18,0),0)))+IF(N(Plan!$B$16)<=0,0,MIN(Plan!$B$16*(1+Plan!$C$16/12),Plan!$D$16+IF(Plan!$E$16=$L5,Plan!$B$5+IF(AND(N(Plan!$B$9)>0,N(Plan!$B$9)<=0),Plan!$D$9,0)+IF(AND(N(Plan!$B$10)>0,N(Plan!$B$10)<=0),Plan!$D$10,0)+IF(AND(N(Plan!$B$11)>0,N(Plan!$B$11)<=0),Plan!$D$11,0)+IF(AND(N(Plan!$B$12)>0,N(Plan!$B$12)<=0),Plan!$D$12,0)+IF(AND(N(Plan!$B$13)>0,N(Plan!$B$13)<=0),Plan!$D$13,0)+IF(AND(N(Plan!$B$14)>0,N(Plan!$B$14)<=0),Plan!$D$14,0)+IF(AND(N(Plan!$B$15)>0,N(Plan!$B$15)<=0),Plan!$D$15,0)+IF(AND(N(Plan!$B$16)>0,N(Plan!$B$16)<=0),Plan!$D$16,0)+IF(AND(N(Plan!$B$17)>0,N(Plan!$B$17)<=0),Plan!$D$17,0)+IF(AND(N(Plan!$B$18)>0,N(Plan!$B$18)<=0),Plan!$D$18,0),0)))+IF(N(Plan!$B$17)<=0,0,MIN(Plan!$B$17*(1+Plan!$C$17/12),Plan!$D$17+IF(Plan!$E$17=$L5,Plan!$B$5+IF(AND(N(Plan!$B$9)>0,N(Plan!$B$9)<=0),Plan!$D$9,0)+IF(AND(N(Plan!$B$10)>0,N(Plan!$B$10)<=0),Plan!$D$10,0)+IF(AND(N(Plan!$B$11)>0,N(Plan!$B$11)<=0),Plan!$D$11,0)+IF(AND(N(Plan!$B$12)>0,N(Plan!$B$12)<=0),Plan!$D$12,0)+IF(AND(N(Plan!$B$13)>0,N(Plan!$B$13)<=0),Plan!$D$13,0)+IF(AND(N(Plan!$B$14)>0,N(Plan!$B$14)<=0),Plan!$D$14,0)+IF(AND(N(Plan!$B$15)>0,N(Plan!$B$15)<=0),Plan!$D$15,0)+IF(AND(N(Plan!$B$16)>0,N(Plan!$B$16)<=0),Plan!$D$16,0)+IF(AND(N(Plan!$B$17)>0,N(Plan!$B$17)<=0),Plan!$D$17,0)+IF(AND(N(Plan!$B$18)>0,N(Plan!$B$18)<=0),Plan!$D$18,0),0)))+IF(N(Plan!$B$18)<=0,0,MIN(Plan!$B$18*(1+Plan!$C$18/12),Plan!$D$18+IF(Plan!$E$18=$L5,Plan!$B$5+IF(AND(N(Plan!$B$9)>0,N(Plan!$B$9)<=0),Plan!$D$9,0)+IF(AND(N(Plan!$B$10)>0,N(Plan!$B$10)<=0),Plan!$D$10,0)+IF(AND(N(Plan!$B$11)>0,N(Plan!$B$11)<=0),Plan!$D$11,0)+IF(AND(N(Plan!$B$12)>0,N(Plan!$B$12)<=0),Plan!$D$12,0)+IF(AND(N(Plan!$B$13)>0,N(Plan!$B$13)<=0),Plan!$D$13,0)+IF(AND(N(Plan!$B$14)>0,N(Plan!$B$14)<=0),Plan!$D$14,0)+IF(AND(N(Plan!$B$15)>0,N(Plan!$B$15)<=0),Plan!$D$15,0)+IF(AND(N(Plan!$B$16)>0,N(Plan!$B$16)<=0),Plan!$D$16,0)+IF(AND(N(Plan!$B$17)>0,N(Plan!$B$17)<=0),Plan!$D$17,0)+IF(AND(N(Plan!$B$18)>0,N(Plan!$B$18)<=0),Plan!$D$18,0),0)))
A6: 2 | B6: =IF(N(B5)<=0,0,MAX(0,B5*(1+Plan!$C$9/12)-(Plan!$D$9+IF(Plan!$E$9=$L6,Plan!$B$5+IF(AND(N(Plan!$B$9)>0,N(B5)<=0),Plan!$D$9,0)+IF(AND(N(Plan!$B$10)>0,N(C5)<=0),Plan!$D$10,0)+IF(AND(N(Plan!$B$11)>0,N(D5)<=0),Plan!$D$11,0)+IF(AND(N(Plan!$B$12)>0,N(E5)<=0),Plan!$D$12,0)+IF(AND(N(Plan!$B$13)>0,N(F5)<=0),Plan!$D$13,0)+IF(AND(N(Plan!$B$14)>0,N(G5)<=0),Plan!$D$14,0)+IF(AND(N(Plan!$B$15)>0,N(H5)<=0),Plan!$D$15,0)+IF(AND(N(Plan!$B$16)>0,N(I5)<=0),Plan!$D$16,0)+IF(AND(N(Plan!$B$17)>0,N(J5)<=0),Plan!$D$17,0)+IF(AND(N(Plan!$B$18)>0,N(K5)<=0),Plan!$D$18,0),0)))) | C6: =IF(N(C5)<=0,0,MAX(0,C5*(1+Plan!$C$10/12)-(Plan!$D$10+IF(Plan!$E$10=$L6,Plan!$B$5+IF(AND(N(Plan!$B$9)>0,N(B5)<=0),Plan!$D$9,0)+IF(AND(N(Plan!$B$10)>0,N(C5)<=0),Plan!$D$10,0)+IF(AND(N(Plan!$B$11)>0,N(D5)<=0),Plan!$D$11,0)+IF(AND(N(Plan!$B$12)>0,N(E5)<=0),Plan!$D$12,0)+IF(AND(N(Plan!$B$13)>0,N(F5)<=0),Plan!$D$13,0)+IF(AND(N(Plan!$B$14)>0,N(G5)<=0),Plan!$D$14,0)+IF(AND(N(Plan!$B$15)>0,N(H5)<=0),Plan!$D$15,0)+IF(AND(N(Plan!$B$16)>0,N(I5)<=0),Plan!$D$16,0)+IF(AND(N(Plan!$B$17)>0,N(J5)<=0),Plan!$D$17,0)+IF(AND(N(Plan!$B$18)>0,N(K5)<=0),Plan!$D$18,0),0)))) | D6: =IF(N(D5)<=0,0,MAX(0,D5*(1+Plan!$C$11/12)-(Plan!$D$11+IF(Plan!$E$11=$L6,Plan!$B$5+IF(AND(N(Plan!$B$9)>0,N(B5)<=0),Plan!$D$9,0)+IF(AND(N(Plan!$B$10)>0,N(C5)<=0),Plan!$D$10,0)+IF(AND(N(Plan!$B$11)>0,N(D5)<=0),Plan!$D$11,0)+IF(AND(N(Plan!$B$12)>0,N(E5)<=0),Plan!$D$12,0)+IF(AND(N(Plan!$B$13)>0,N(F5)<=0),Plan!$D$13,0)+IF(AND(N(Plan!$B$14)>0,N(G5)<=0),Plan!$D$14,0)+IF(AND(N(Plan!$B$15)>0,N(H5)<=0),Plan!$D$15,0)+IF(AND(N(Plan!$B$16)>0,N(I5)<=0),Plan!$D$16,0)+IF(AND(N(Plan!$B$17)>0,N(J5)<=0),Plan!$D$17,0)+IF(AND(N(Plan!$B$18)>0,N(K5)<=0),Plan!$D$18,0),0)))) | E6: =IF(N(E5)<=0,0,MAX(0,E5*(1+Plan!$C$12/12)-(Plan!$D$12+IF(Plan!$E$12=$L6,Plan!$B$5+IF(AND(N(Plan!$B$9)>0,N(B5)<=0),Plan!$D$9,0)+IF(AND(N(Plan!$B$10)>0,N(C5)<=0),Plan!$D$10,0)+IF(AND(N(Plan!$B$11)>0,N(D5)<=0),Plan!$D$11,0)+IF(AND(N(Plan!$B$12)>0,N(E5)<=0),Plan!$D$12,0)+IF(AND(N(Plan!$B$13)>0,N(F5)<=0),Plan!$D$13,0)+IF(AND(N(Plan!$B$14)>0,N(G5)<=0),Plan!$D$14,0)+IF(AND(N(Plan!$B$15)>0,N(H5)<=0),Plan!$D$15,0)+IF(AND(N(Plan!$B$16)>0,N(I5)<=0),Plan!$D$16,0)+IF(AND(N(Plan!$B$17)>0,N(J5)<=0),Plan!$D$17,0)+IF(AND(N(Plan!$B$18)>0,N(K5)<=0),Plan!$D$18,0),0)))) | F6: =IF(N(F5)<=0,0,MAX(0,F5*(1+Plan!$C$13/12)-(Plan!$D$13+IF(Plan!$E$13=$L6,Plan!$B$5+IF(AND(N(Plan!$B$9)>0,N(B5)<=0),Plan!$D$9,0)+IF(AND(N(Plan!$B$10)>0,N(C5)<=0),Plan!$D$10,0)+IF(AND(N(Plan!$B$11)>0,N(D5)<=0),Plan!$D$11,0)+IF(AND(N(Plan!$B$12)>0,N(E5)<=0),Plan!$D$12,0)+IF(AND(N(Plan!$B$13)>0,N(F5)<=0),Plan!$D$13,0)+IF(AND(N(Plan!$B$14)>0,N(G5)<=0),Plan!$D$14,0)+IF(AND(N(Plan!$B$15)>0,N(H5)<=0),Plan!$D$15,0)+IF(AND(N(Plan!$B$16)>0,N(I5)<=0),Plan!$D$16,0)+IF(AND(N(Plan!$B$17)>0,N(J5)<=0),Plan!$D$17,0)+IF(AND(N(Plan!$B$18)>0,N(K5)<=0),Plan!$D$18,0),0)))) | G6: =IF(N(G5)<=0,0,MAX(0,G5*(1+Plan!$C$14/12)-(Plan!$D$14+IF(Plan!$E$14=$L6,Plan!$B$5+IF(AND(N(Plan!$B$9)>0,N(B5)<=0),Plan!$D$9,0)+IF(AND(N(Plan!$B$10)>0,N(C5)<=0),Plan!$D$10,0)+IF(AND(N(Plan!$B$11)>0,N(D5)<=0),Plan!$D$11,0)+IF(AND(N(Plan!$B$12)>0,N(E5)<=0),Plan!$D$12,0)+IF(AND(N(Plan!$B$13)>0,N(F5)<=0),Plan!$D$13,0)+IF(AND(N(Plan!$B$14)>0,N(G5)<=0),Plan!$D$14,0)+IF(AND(N(Plan!$B$15)>0,N(H5)<=0),Plan!$D$15,0)+IF(AND(N(Plan!$B$16)>0,N(I5)<=0),Plan!$D$16,0)+IF(AND(N(Plan!$B$17)>0,N(J5)<=0),Plan!$D$17,0)+IF(AND(N(Plan!$B$18)>0,N(K5)<=0),Plan!$D$18,0),0)))) | H6: =IF(N(H5)<=0,0,MAX(0,H5*(1+Plan!$C$15/12)-(Plan!$D$15+IF(Plan!$E$15=$L6,Plan!$B$5+IF(AND(N(Plan!$B$9)>0,N(B5)<=0),Plan!$D$9,0)+IF(AND(N(Plan!$B$10)>0,N(C5)<=0),Plan!$D$10,0)+IF(AND(N(Plan!$B$11)>0,N(D5)<=0),Plan!$D$11,0)+IF(AND(N(Plan!$B$12)>0,N(E5)<=0),Plan!$D$12,0)+IF(AND(N(Plan!$B$13)>0,N(F5)<=0),Plan!$D$13,0)+IF(AND(N(Plan!$B$14)>0,N(G5)<=0),Plan!$D$14,0)+IF(AND(N(Plan!$B$15)>0,N(H5)<=0),Plan!$D$15,0)+IF(AND(N(Plan!$B$16)>0,N(I5)<=0),Plan!$D$16,0)+IF(AND(N(Plan!$B$17)>0,N(J5)<=0),Plan!$D$17,0)+IF(AND(N(Plan!$B$18)>0,N(K5)<=0),Plan!$D$18,0),0)))) | I6: =IF(N(I5)<=0,0,MAX(0,I5*(1+Plan!$C$16/12)-(Plan!$D$16+IF(Plan!$E$16=$L6,Plan!$B$5+IF(AND(N(Plan!$B$9)>0,N(B5)<=0),Plan!$D$9,0)+IF(AND(N(Plan!$B$10)>0,N(C5)<=0),Plan!$D$10,0)+IF(AND(N(Plan!$B$11)>0,N(D5)<=0),Plan!$D$11,0)+IF(AND(N(Plan!$B$12)>0,N(E5)<=0),Plan!$D$12,0)+IF(AND(N(Plan!$B$13)>0,N(F5)<=0),Plan!$D$13,0)+IF(AND(N(Plan!$B$14)>0,N(G5)<=0),Plan!$D$14,0)+IF(AND(N(Plan!$B$15)>0,N(H5)<=0),Plan!$D$15,0)+IF(AND(N(Plan!$B$16)>0,N(I5)<=0),Plan!$D$16,0)+IF(AND(N(Plan!$B$17)>0,N(J5)<=0),Plan!$D$17,0)+IF(AND(N(Plan!$B$18)>0,N(K5)<=0),Plan!$D$18,0),0)))) | J6: =IF(N(J5)<=0,0,MAX(0,J5*(1+Plan!$C$17/12)-(Plan!$D$17+IF(Plan!$E$17=$L6,Plan!$B$5+IF(AND(N(Plan!$B$9)>0,N(B5)<=0),Plan!$D$9,0)+IF(AND(N(Plan!$B$10)>0,N(C5)<=0),Plan!$D$10,0)+IF(AND(N(Plan!$B$11)>0,N(D5)<=0),Plan!$D$11,0)+IF(AND(N(Plan!$B$12)>0,N(E5)<=0),Plan!$D$12,0)+IF(AND(N(Plan!$B$13)>0,N(F5)<=0),Plan!$D$13,0)+IF(AND(N(Plan!$B$14)>0,N(G5)<=0),Plan!$D$14,0)+IF(AND(N(Plan!$B$15)>0,N(H5)<=0),Plan!$D$15,0)+IF(AND(N(Plan!$B$16)>0,N(I5)<=0),Plan!$D$16,0)+IF(AND(N(Plan!$B$17)>0,N(J5)<=0),Plan!$D$17,0)+IF(AND(N(Plan!$B$18)>0,N(K5)<=0),Plan!$D$18,0),0)))) | K6: =IF(N(K5)<=0,0,MAX(0,K5*(1+Plan!$C$18/12)-(Plan!$D$18+IF(Plan!$E$18=$L6,Plan!$B$5+IF(AND(N(Plan!$B$9)>0,N(B5)<=0),Plan!$D$9,0)+IF(AND(N(Plan!$B$10)>0,N(C5)<=0),Plan!$D$10,0)+IF(AND(N(Plan!$B$11)>0,N(D5)<=0),Plan!$D$11,0)+IF(AND(N(Plan!$B$12)>0,N(E5)<=0),Plan!$D$12,0)+IF(AND(N(Plan!$B$13)>0,N(F5)<=0),Plan!$D$13,0)+IF(AND(N(Plan!$B$14)>0,N(G5)<=0),Plan!$D$14,0)+IF(AND(N(Plan!$B$15)>0,N(H5)<=0),Plan!$D$15,0)+IF(AND(N(Plan!$B$16)>0,N(I5)<=0),Plan!$D$16,0)+IF(AND(N(Plan!$B$17)>0,N(J5)<=0),Plan!$D$17,0)+IF(AND(N(Plan!$B$18)>0,N(K5)<=0),Plan!$D$18,0),0)))) | L6: =MIN(IF(N(B5)>0,Plan!$E$9,999),IF(N(C5)>0,Plan!$E$10,999),IF(N(D5)>0,Plan!$E$11,999),IF(N(E5)>0,Plan!$E$12,999),IF(N(F5)>0,Plan!$E$13,999),IF(N(G5)>0,Plan!$E$14,999),IF(N(H5)>0,Plan!$E$15,999),IF(N(I5)>0,Plan!$E$16,999),IF(N(J5)>0,Plan!$E$17,999),IF(N(K5)>0,Plan!$E$18,999)) | M6: =IF(N(B5)<=0,0,MIN(B5*(1+Plan!$C$9/12),Plan!$D$9+IF(Plan!$E$9=$L6,Plan!$B$5+IF(AND(N(Plan!$B$9)>0,N(B5)<=0),Plan!$D$9,0)+IF(AND(N(Plan!$B$10)>0,N(C5)<=0),Plan!$D$10,0)+IF(AND(N(Plan!$B$11)>0,N(D5)<=0),Plan!$D$11,0)+IF(AND(N(Plan!$B$12)>0,N(E5)<=0),Plan!$D$12,0)+IF(AND(N(Plan!$B$13)>0,N(F5)<=0),Plan!$D$13,0)+IF(AND(N(Plan!$B$14)>0,N(G5)<=0),Plan!$D$14,0)+IF(AND(N(Plan!$B$15)>0,N(H5)<=0),Plan!$D$15,0)+IF(AND(N(Plan!$B$16)>0,N(I5)<=0),Plan!$D$16,0)+IF(AND(N(Plan!$B$17)>0,N(J5)<=0),Plan!$D$17,0)+IF(AND(N(Plan!$B$18)>0,N(K5)<=0),Plan!$D$18,0),0)))+IF(N(C5)<=0,0,MIN(C5*(1+Plan!$C$10/12),Plan!$D$10+IF(Plan!$E$10=$L6,Plan!$B$5+IF(AND(N(Plan!$B$9)>0,N(B5)<=0),Plan!$D$9,0)+IF(AND(N(Plan!$B$10)>0,N(C5)<=0),Plan!$D$10,0)+IF(AND(N(Plan!$B$11)>0,N(D5)<=0),Plan!$D$11,0)+IF(AND(N(Plan!$B$12)>0,N(E5)<=0),Plan!$D$12,0)+IF(AND(N(Plan!$B$13)>0,N(F5)<=0),Plan!$D$13,0)+IF(AND(N(Plan!$B$14)>0,N(G5)<=0),Plan!$D$14,0)+IF(AND(N(Plan!$B$15)>0,N(H5)<=0),Plan!$D$15,0)+IF(AND(N(Plan!$B$16)>0,N(I5)<=0),Plan!$D$16,0)+IF(AND(N(Plan!$B$17)>0,N(J5)<=0),Plan!$D$17,0)+IF(AND(N(Plan!$B$18)>0,N(K5)<=0),Plan!$D$18,0),0)))+IF(N(D5)<=0,0,MIN(D5*(1+Plan!$C$11/12),Plan!$D$11+IF(Plan!$E$11=$L6,Plan!$B$5+IF(AND(N(Plan!$B$9)>0,N(B5)<=0),Plan!$D$9,0)+IF(AND(N(Plan!$B$10)>0,N(C5)<=0),Plan!$D$10,0)+IF(AND(N(Plan!$B$11)>0,N(D5)<=0),Plan!$D$11,0)+IF(AND(N(Plan!$B$12)>0,N(E5)<=0),Plan!$D$12,0)+IF(AND(N(Plan!$B$13)>0,N(F5)<=0),Plan!$D$13,0)+IF(AND(N(Plan!$B$14)>0,N(G5)<=0),Plan!$D$14,0)+IF(AND(N(Plan!$B$15)>0,N(H5)<=0),Plan!$D$15,0)+IF(AND(N(Plan!$B$16)>0,N(I5)<=0),Plan!$D$16,0)+IF(AND(N(Plan!$B$17)>0,N(J5)<=0),Plan!$D$17,0)+IF(AND(N(Plan!$B$18)>0,N(K5)<=0),Plan!$D$18,0),0)))+IF(N(E5)<=0,0,MIN(E5*(1+Plan!$C$12/12),Plan!$D$12+IF(Plan!$E$12=$L6,Plan!$B$5+IF(AND(N(Plan!$B$9)>0,N(B5)<=0),Plan!$D$9,0)+IF(AND(N(Plan!$B$10)>0,N(C5)<=0),Plan!$D$10,0)+IF(AND(N(Plan!$B$11)>0,N(D5)<=0),Plan!$D$11,0)+IF(AND(N(Plan!$B$12)>0,N(E5)<=0),Plan!$D$12,0)+IF(AND(N(Plan!$B$13)>0,N(F5)<=0),Plan!$D$13,0)+IF(AND(N(Plan!$B$14)>0,N(G5)<=0),Plan!$D$14,0)+IF(AND(N(Plan!$B$15)>0,N(H5)<=0),Plan!$D$15,0)+IF(AND(N(Plan!$B$16)>0,N(I5)<=0),Plan!$D$16,0)+IF(AND(N(Plan!$B$17)>0,N(J5)<=0),Plan!$D$17,0)+IF(AND(N(Plan!$B$18)>0,N(K5)<=0),Plan!$D$18,0),0)))+IF(N(F5)<=0,0,MIN(F5*(1+Plan!$C$13/12),Plan!$D$13+IF(Plan!$E$13=$L6,Plan!$B$5+IF(AND(N(Plan!$B$9)>0,N(B5)<=0),Plan!$D$9,0)+IF(AND(N(Plan!$B$10)>0,N(C5)<=0),Plan!$D$10,0)+IF(AND(N(Plan!$B$11)>0,N(D5)<=0),Plan!$D$11,0)+IF(AND(N(Plan!$B$12)>0,N(E5)<=0),Plan!$D$12,0)+IF(AND(N(Plan!$B$13)>0,N(F5)<=0),Plan!$D$13,0)+IF(AND(N(Plan!$B$14)>0,N(G5)<=0),Plan!$D$14,0)+IF(AND(N(Plan!$B$15)>0,N(H5)<=0),Plan!$D$15,0)+IF(AND(N(Plan!$B$16)>0,N(I5)<=0),Plan!$D$16,0)+IF(AND(N(Plan!$B$17)>0,N(J5)<=0),Plan!$D$17,0)+IF(AND(N(Plan!$B$18)>0,N(K5)<=0),Plan!$D$18,0),0)))+IF(N(G5)<=0,0,MIN(G5*(1+Plan!$C$14/12),Plan!$D$14+IF(Plan!$E$14=$L6,Plan!$B$5+IF(AND(N(Plan!$B$9)>0,N(B5)<=0),Plan!$D$9,0)+IF(AND(N(Plan!$B$10)>0,N(C5)<=0),Plan!$D$10,0)+IF(AND(N(Plan!$B$11)>0,N(D5)<=0),Plan!$D$11,0)+IF(AND(N(Plan!$B$12)>0,N(E5)<=0),Plan!$D$12,0)+IF(AND(N(Plan!$B$13)>0,N(F5)<=0),Plan!$D$13,0)+IF(AND(N(Plan!$B$14)>0,N(G5)<=0),Plan!$D$14,0)+IF(AND(N(Plan!$B$15)>0,N(H5)<=0),Plan!$D$15,0)+IF(AND(N(Plan!$B$16)>0,N(I5)<=0),Plan!$D$16,0)+IF(AND(N(Plan!$B$17)>0,N(J5)<=0),Plan!$D$17,0)+IF(AND(N(Plan!$B$18)>0,N(K5)<=0),Plan!$D$18,0),0)))+IF(N(H5)<=0,0,MIN(H5*(1+Plan!$C$15/12),Plan!$D$15+IF(Plan!$E$15=$L6,Plan!$B$5+IF(AND(N(Plan!$B$9)>0,N(B5)<=0),Plan!$D$9,0)+IF(AND(N(Plan!$B$10)>0,N(C5)<=0),Plan!$D$10,0)+IF(AND(N(Plan!$B$11)>0,N(D5)<=0),Plan!$D$11,0)+IF(AND(N(Plan!$B$12)>0,N(E5)<=0),Plan!$D$12,0)+IF(AND(N(Plan!$B$13)>0,N(F5)<=0),Plan!$D$13,0)+IF(AND(N(Plan!$B$14)>0,N(G5)<=0),Plan!$D$14,0)+IF(AND(N(Plan!$B$15)>0,N(H5)<=0),Plan!$D$15,0)+IF(AND(N(Plan!$B$16)>0,N(I5)<=0),Plan!$D$16,0)+IF(AND(N(Plan!$B$17)>0,N(J5)<=0),Plan!$D$17,0)+IF(AND(N(Plan!$B$18)>0,N(K5)<=0),Plan!$D$18,0),0)))+IF(N(I5)<=0,0,MIN(I5*(1+Plan!$C$16/12),Plan!$D$16+IF(Plan!$E$16=$L6,Plan!$B$5+IF(AND(N(Plan!$B$9)>0,N(B5)<=0),Plan!$D$9,0)+IF(AND(N(Plan!$B$10)>0,N(C5)<=0),Plan!$D$10,0)+IF(AND(N(Plan!$B$11)>0,N(D5)<=0),Plan!$D$11,0)+IF(AND(N(Plan!$B$12)>0,N(E5)<=0),Plan!$D$12,0)+IF(AND(N(Plan!$B$13)>0,N(F5)<=0),Plan!$D$13,0)+IF(AND(N(Plan!$B$14)>0,N(G5)<=0),Plan!$D$14,0)+IF(AND(N(Plan!$B$15)>0,N(H5)<=0),Plan!$D$15,0)+IF(AND(N(Plan!$B$16)>0,N(I5)<=0),Plan!$D$16,0)+IF(AND(N(Plan!$B$17)>0,N(J5)<=0),Plan!$D$17,0)+IF(AND(N(Plan!$B$18)>0,N(K5)<=0),Plan!$D$18,0),0)))+IF(N(J5)<=0,0,MIN(J5*(1+Plan!$C$17/12),Plan!$D$17+IF(Plan!$E$17=$L6,Plan!$B$5+IF(AND(N(Plan!$B$9)>0,N(B5)<=0),Plan!$D$9,0)+IF(AND(N(Plan!$B$10)>0,N(C5)<=0),Plan!$D$10,0)+IF(AND(N(Plan!$B$11)>0,N(D5)<=0),Plan!$D$11,0)+IF(AND(N(Plan!$B$12)>0,N(E5)<=0),Plan!$D$12,0)+IF(AND(N(Plan!$B$13)>0,N(F5)<=0),Plan!$D$13,0)+IF(AND(N(Plan!$B$14)>0,N(G5)<=0),Plan!$D$14,0)+IF(AND(N(Plan!$B$15)>0,N(H5)<=0),Plan!$D$15,0)+IF(AND(N(Plan!$B$16)>0,N(I5)<=0),Plan!$D$16,0)+IF(AND(N(Plan!$B$17)>0,N(J5)<=0),Plan!$D$17,0)+IF(AND(N(Plan!$B$18)>0,N(K5)<=0),Plan!$D$18,0),0)))+IF(N(K5)<=0,0,MIN(K5*(1+Plan!$C$18/12),Plan!$D$18+IF(Plan!$E$18=$L6,Plan!$B$5+IF(AND(N(Plan!$B$9)>0,N(B5)<=0),Plan!$D$9,0)+IF(AND(N(Plan!$B$10)>0,N(C5)<=0),Plan!$D$10,0)+IF(AND(N(Plan!$B$11)>0,N(D5)<=0),Plan!$D$11,0)+IF(AND(N(Plan!$B$12)>0,N(E5)<=0),Plan!$D$12,0)+IF(AND(N(Plan!$B$13)>0,N(F5)<=0),Plan!$D$13,0)+IF(AND(N(Plan!$B$14)>0,N(G5)<=0),Plan!$D$14,0)+IF(AND(N(Plan!$B$15)>0,N(H5)<=0),Plan!$D$15,0)+IF(AND(N(Plan!$B$16)>0,N(I5)<=0),Plan!$D$16,0)+IF(AND(N(Plan!$B$17)>0,N(J5)<=0),Plan!$D$17,0)+IF(AND(N(Plan!$B$18)>0,N(K5)<=0),Plan!$D$18,0),0)))
A7: 3 | B7: =IF(N(B6)<=0,0,MAX(0,B6*(1+Plan!$C$9/12)-(Plan!$D$9+IF(Plan!$E$9=$L7,Plan!$B$5+IF(AND(N(Plan!$B$9)>0,N(B6)<=0),Plan!$D$9,0)+IF(AND(N(Plan!$B$10)>0,N(C6)<=0),Plan!$D$10,0)+IF(AND(N(Plan!$B$11)>0,N(D6)<=0),Plan!$D$11,0)+IF(AND(N(Plan!$B$12)>0,N(E6)<=0),Plan!$D$12,0)+IF(AND(N(Plan!$B$13)>0,N(F6)<=0),Plan!$D$13,0)+IF(AND(N(Plan!$B$14)>0,N(G6)<=0),Plan!$D$14,0)+IF(AND(N(Plan!$B$15)>0,N(H6)<=0),Plan!$D$15,0)+IF(AND(N(Plan!$B$16)>0,N(I6)<=0),Plan!$D$16,0)+IF(AND(N(Plan!$B$17)>0,N(J6)<=0),Plan!$D$17,0)+IF(AND(N(Plan!$B$18)>0,N(K6)<=0),Plan!$D$18,0),0)))) | C7: =IF(N(C6)<=0,0,MAX(0,C6*(1+Plan!$C$10/12)-(Plan!$D$10+IF(Plan!$E$10=$L7,Plan!$B$5+IF(AND(N(Plan!$B$9)>0,N(B6)<=0),Plan!$D$9,0)+IF(AND(N(Plan!$B$10)>0,N(C6)<=0),Plan!$D$10,0)+IF(AND(N(Plan!$B$11)>0,N(D6)<=0),Plan!$D$11,0)+IF(AND(N(Plan!$B$12)>0,N(E6)<=0),Plan!$D$12,0)+IF(AND(N(Plan!$B$13)>0,N(F6)<=0),Plan!$D$13,0)+IF(AND(N(Plan!$B$14)>0,N(G6)<=0),Plan!$D$14,0)+IF(AND(N(Plan!$B$15)>0,N(H6)<=0),Plan!$D$15,0)+IF(AND(N(Plan!$B$16)>0,N(I6)<=0),Plan!$D$16,0)+IF(AND(N(Plan!$B$17)>0,N(J6)<=0),Plan!$D$17,0)+IF(AND(N(Plan!$B$18)>0,N(K6)<=0),Plan!$D$18,0),0)))) | D7: =IF(N(D6)<=0,0,MAX(0,D6*(1+Plan!$C$11/12)-(Plan!$D$11+IF(Plan!$E$11=$L7,Plan!$B$5+IF(AND(N(Plan!$B$9)>0,N(B6)<=0),Plan!$D$9,0)+IF(AND(N(Plan!$B$10)>0,N(C6)<=0),Plan!$D$10,0)+IF(AND(N(Plan!$B$11)>0,N(D6)<=0),Plan!$D$11,0)+IF(AND(N(Plan!$B$12)>0,N(E6)<=0),Plan!$D$12,0)+IF(AND(N(Plan!$B$13)>0,N(F6)<=0),Plan!$D$13,0)+IF(AND(N(Plan!$B$14)>0,N(G6)<=0),Plan!$D$14,0)+IF(AND(N(Plan!$B$15)>0,N(H6)<=0),Plan!$D$15,0)+IF(AND(N(Plan!$B$16)>0,N(I6)<=0),Plan!$D$16,0)+IF(AND(N(Plan!$B$17)>0,N(J6)<=0),Plan!$D$17,0)+IF(AND(N(Plan!$B$18)>0,N(K6)<=0),Plan!$D$18,0),0)))) | E7: =IF(N(E6)<=0,0,MAX(0,E6*(1+Plan!$C$12/12)-(Plan!$D$12+IF(Plan!$E$12=$L7,Plan!$B$5+IF(AND(N(Plan!$B$9)>0,N(B6)<=0),Plan!$D$9,0)+IF(AND(N(Plan!$B$10)>0,N(C6)<=0),Plan!$D$10,0)+IF(AND(N(Plan!$B$11)>0,N(D6)<=0),Plan!$D$11,0)+IF(AND(N(Plan!$B$12)>0,N(E6)<=0),Plan!$D$12,0)+IF(AND(N(Plan!$B$13)>0,N(F6)<=0),Plan!$D$13,0)+IF(AND(N(Plan!$B$14)>0,N(G6)<=0),Plan!$D$14,0)+IF(AND(N(Plan!$B$15)>0,N(H6)<=0),Plan!$D$15,0)+IF(AND(N(Plan!$B$16)>0,N(I6)<=0),Plan!$D$16,0)+IF(AND(N(Plan!$B$17)>0,N(J6)<=0),Plan!$D$17,0)+IF(AND(N(Plan!$B$18)>0,N(K6)<=0),Plan!$D$18,0),0)))) | F7: =IF(N(F6)<=0,0,MAX(0,F6*(1+Plan!$C$13/12)-(Plan!$D$13+IF(Plan!$E$13=$L7,Plan!$B$5+IF(AND(N(Plan!$B$9)>0,N(B6)<=0),Plan!$D$9,0)+IF(AND(N(Plan!$B$10)>0,N(C6)<=0),Plan!$D$10,0)+IF(AND(N(Plan!$B$11)>0,N(D6)<=0),Plan!$D$11,0)+IF(AND(N(Plan!$B$12)>0,N(E6)<=0),Plan!$D$12,0)+IF(AND(N(Plan!$B$13)>0,N(F6)<=0),Plan!$D$13,0)+IF(AND(N(Plan!$B$14)>0,N(G6)<=0),Plan!$D$14,0)+IF(AND(N(Plan!$B$15)>0,N(H6)<=0),Plan!$D$15,0)+IF(AND(N(Plan!$B$16)>0,N(I6)<=0),Plan!$D$16,0)+IF(AND(N(Plan!$B$17)>0,N(J6)<=0),Plan!$D$17,0)+IF(AND(N(Plan!$B$18)>0,N(K6)<=0),Plan!$D$18,0),0)))) | G7: =IF(N(G6)<=0,0,MAX(0,G6*(1+Plan!$C$14/12)-(Plan!$D$14+IF(Plan!$E$14=$L7,Plan!$B$5+IF(AND(N(Plan!$B$9)>0,N(B6)<=0),Plan!$D$9,0)+IF(AND(N(Plan!$B$10)>0,N(C6)<=0),Plan!$D$10,0)+IF(AND(N(Plan!$B$11)>0,N(D6)<=0),Plan!$D$11,0)+IF(AND(N(Plan!$B$12)>0,N(E6)<=0),Plan!$D$12,0)+IF(AND(N(Plan!$B$13)>0,N(F6)<=0),Plan!$D$13,0)+IF(AND(N(Plan!$B$14)>0,N(G6)<=0),Plan!$D$14,0)+IF(AND(N(Plan!$B$15)>0,N(H6)<=0),Plan!$D$15,0)+IF(AND(N(Plan!$B$16)>0,N(I6)<=0),Plan!$D$16,0)+IF(AND(N(Plan!$B$17)>0,N(J6)<=0),Plan!$D$17,0)+IF(AND(N(Plan!$B$18)>0,N(K6)<=0),Plan!$D$18,0),0)))) | H7: =IF(N(H6)<=0,0,MAX(0,H6*(1+Plan!$C$15/12)-(Plan!$D$15+IF(Plan!$E$15=$L7,Plan!$B$5+IF(AND(N(Plan!$B$9)>0,N(B6)<=0),Plan!$D$9,0)+IF(AND(N(Plan!$B$10)>0,N(C6)<=0),Plan!$D$10,0)+IF(AND(N(Plan!$B$11)>0,N(D6)<=0),Plan!$D$11,0)+IF(AND(N(Plan!$B$12)>0,N(E6)<=0),Plan!$D$12,0)+IF(AND(N(Plan!$B$13)>0,N(F6)<=0),Plan!$D$13,0)+IF(AND(N(Plan!$B$14)>0,N(G6)<=0),Plan!$D$14,0)+IF(AND(N(Plan!$B$15)>0,N(H6)<=0),Plan!$D$15,0)+IF(AND(N(Plan!$B$16)>0,N(I6)<=0),Plan!$D$16,0)+IF(AND(N(Plan!$B$17)>0,N(J6)<=0),Plan!$D$17,0)+IF(AND(N(Plan!$B$18)>0,N(K6)<=0),Plan!$D$18,0),0)))) | I7: =IF(N(I6)<=0,0,MAX(0,I6*(1+Plan!$C$16/12)-(Plan!$D$16+IF(Plan!$E$16=$L7,Plan!$B$5+IF(AND(N(Plan!$B$9)>0,N(B6)<=0),Plan!$D$9,0)+IF(AND(N(Plan!$B$10)>0,N(C6)<=0),Plan!$D$10,0)+IF(AND(N(Plan!$B$11)>0,N(D6)<=0),Plan!$D$11,0)+IF(AND(N(Plan!$B$12)>0,N(E6)<=0),Plan!$D$12,0)+IF(AND(N(Plan!$B$13)>0,N(F6)<=0),Plan!$D$13,0)+IF(AND(N(Plan!$B$14)>0,N(G6)<=0),Plan!$D$14,0)+IF(AND(N(Plan!$B$15)>0,N(H6)<=0),Plan!$D$15,0)+IF(AND(N(Plan!$B$16)>0,N(I6)<=0),Plan!$D$16,0)+IF(AND(N(Plan!$B$17)>0,N(J6)<=0),Plan!$D$17,0)+IF(AND(N(Plan!$B$18)>0,N(K6)<=0),Plan!$D$18,0),0)))) | J7: =IF(N(J6)<=0,0,MAX(0,J6*(1+Plan!$C$17/12)-(Plan!$D$17+IF(Plan!$E$17=$L7,Plan!$B$5+IF(AND(N(Plan!$B$9)>0,N(B6)<=0),Plan!$D$9,0)+IF(AND(N(Plan!$B$10)>0,N(C6)<=0),Plan!$D$10,0)+IF(AND(N(Plan!$B$11)>0,N(D6)<=0),Plan!$D$11,0)+IF(AND(N(Plan!$B$12)>0,N(E6)<=0),Plan!$D$12,0)+IF(AND(N(Plan!$B$13)>0,N(F6)<=0),Plan!$D$13,0)+IF(AND(N(Plan!$B$14)>0,N(G6)<=0),Plan!$D$14,0)+IF(AND(N(Plan!$B$15)>0,N(H6)<=0),Plan!$D$15,0)+IF(AND(N(Plan!$B$16)>0,N(I6)<=0),Plan!$D$16,0)+IF(AND(N(Plan!$B$17)>0,N(J6)<=0),Plan!$D$17,0)+IF(AND(N(Plan!$B$18)>0,N(K6)<=0),Plan!$D$18,0),0)))) | K7: =IF(N(K6)<=0,0,MAX(0,K6*(1+Plan!$C$18/12)-(Plan!$D$18+IF(Plan!$E$18=$L7,Plan!$B$5+IF(AND(N(Plan!$B$9)>0,N(B6)<=0),Plan!$D$9,0)+IF(AND(N(Plan!$B$10)>0,N(C6)<=0),Plan!$D$10,0)+IF(AND(N(Plan!$B$11)>0,N(D6)<=0),Plan!$D$11,0)+IF(AND(N(Plan!$B$12)>0,N(E6)<=0),Plan!$D$12,0)+IF(AND(N(Plan!$B$13)>0,N(F6)<=0),Plan!$D$13,0)+IF(AND(N(Plan!$B$14)>0,N(G6)<=0),Plan!$D$14,0)+IF(AND(N(Plan!$B$15)>0,N(H6)<=0),Plan!$D$15,0)+IF(AND(N(Plan!$B$16)>0,N(I6)<=0),Plan!$D$16,0)+IF(AND(N(Plan!$B$17)>0,N(J6)<=0),Plan!$D$17,0)+IF(AND(N(Plan!$B$18)>0,N(K6)<=0),Plan!$D$18,0),0)))) | L7: =MIN(IF(N(B6)>0,Plan!$E$9,999),IF(N(C6)>0,Plan!$E$10,999),IF(N(D6)>0,Plan!$E$11,999),IF(N(E6)>0,Plan!$E$12,999),IF(N(F6)>0,Plan!$E$13,999),IF(N(G6)>0,Plan!$E$14,999),IF(N(H6)>0,Plan!$E$15,999),IF(N(I6)>0,Plan!$E$16,999),IF(N(J6)>0,Plan!$E$17,999),IF(N(K6)>0,Plan!$E$18,999)) | M7: =IF(N(B6)<=0,0,MIN(B6*(1+Plan!$C$9/12),Plan!$D$9+IF(Plan!$E$9=$L7,Plan!$B$5+IF(AND(N(Plan!$B$9)>0,N(B6)<=0),Plan!$D$9,0)+IF(AND(N(Plan!$B$10)>0,N(C6)<=0),Plan!$D$10,0)+IF(AND(N(Plan!$B$11)>0,N(D6)<=0),Plan!$D$11,0)+IF(AND(N(Plan!$B$12)>0,N(E6)<=0),Plan!$D$12,0)+IF(AND(N(Plan!$B$13)>0,N(F6)<=0),Plan!$D$13,0)+IF(AND(N(Plan!$B$14)>0,N(G6)<=0),Plan!$D$14,0)+IF(AND(N(Plan!$B$15)>0,N(H6)<=0),Plan!$D$15,0)+IF(AND(N(Plan!$B$16)>0,N(I6)<=0),Plan!$D$16,0)+IF(AND(N(Plan!$B$17)>0,N(J6)<=0),Plan!$D$17,0)+IF(AND(N(Plan!$B$18)>0,N(K6)<=0),Plan!$D$18,0),0)))+IF(N(C6)<=0,0,MIN(C6*(1+Plan!$C$10/12),Plan!$D$10+IF(Plan!$E$10=$L7,Plan!$B$5+IF(AND(N(Plan!$B$9)>0,N(B6)<=0),Plan!$D$9,0)+IF(AND(N(Plan!$B$10)>0,N(C6)<=0),Plan!$D$10,0)+IF(AND(N(Plan!$B$11)>0,N(D6)<=0),Plan!$D$11,0)+IF(AND(N(Plan!$B$12)>0,N(E6)<=0),Plan!$D$12,0)+IF(AND(N(Plan!$B$13)>0,N(F6)<=0),Plan!$D$13,0)+IF(AND(N(Plan!$B$14)>0,N(G6)<=0),Plan!$D$14,0)+IF(AND(N(Plan!$B$15)>0,N(H6)<=0),Plan!$D$15,0)+IF(AND(N(Plan!$B$16)>0,N(I6)<=0),Plan!$D$16,0)+IF(AND(N(Plan!$B$17)>0,N(J6)<=0),Plan!$D$17,0)+IF(AND(N(Plan!$B$18)>0,N(K6)<=0),Plan!$D$18,0),0)))+IF(N(D6)<=0,0,MIN(D6*(1+Plan!$C$11/12),Plan!$D$11+IF(Plan!$E$11=$L7,Plan!$B$5+IF(AND(N(Plan!$B$9)>0,N(B6)<=0),Plan!$D$9,0)+IF(AND(N(Plan!$B$10)>0,N(C6)<=0),Plan!$D$10,0)+IF(AND(N(Plan!$B$11)>0,N(D6)<=0),Plan!$D$11,0)+IF(AND(N(Plan!$B$12)>0,N(E6)<=0),Plan!$D$12,0)+IF(AND(N(Plan!$B$13)>0,N(F6)<=0),Plan!$D$13,0)+IF(AND(N(Plan!$B$14)>0,N(G6)<=0),Plan!$D$14,0)+IF(AND(N(Plan!$B$15)>0,N(H6)<=0),Plan!$D$15,0)+IF(AND(N(Plan!$B$16)>0,N(I6)<=0),Plan!$D$16,0)+IF(AND(N(Plan!$B$17)>0,N(J6)<=0),Plan!$D$17,0)+IF(AND(N(Plan!$B$18)>0,N(K6)<=0),Plan!$D$18,0),0)))+IF(N(E6)<=0,0,MIN(E6*(1+Plan!$C$12/12),Plan!$D$12+IF(Plan!$E$12=$L7,Plan!$B$5+IF(AND(N(Plan!$B$9)>0,N(B6)<=0),Plan!$D$9,0)+IF(AND(N(Plan!$B$10)>0,N(C6)<=0),Plan!$D$10,0)+IF(AND(N(Plan!$B$11)>0,N(D6)<=0),Plan!$D$11,0)+IF(AND(N(Plan!$B$12)>0,N(E6)<=0),Plan!$D$12,0)+IF(AND(N(Plan!$B$13)>0,N(F6)<=0),Plan!$D$13,0)+IF(AND(N(Plan!$B$14)>0,N(G6)<=0),Plan!$D$14,0)+IF(AND(N(Plan!$B$15)>0,N(H6)<=0),Plan!$D$15,0)+IF(AND(N(Plan!$B$16)>0,N(I6)<=0),Plan!$D$16,0)+IF(AND(N(Plan!$B$17)>0,N(J6)<=0),Plan!$D$17,0)+IF(AND(N(Plan!$B$18)>0,N(K6)<=0),Plan!$D$18,0),0)))+IF(N(F6)<=0,0,MIN(F6*(1+Plan!$C$13/12),Plan!$D$13+IF(Plan!$E$13=$L7,Plan!$B$5+IF(AND(N(Plan!$B$9)>0,N(B6)<=0),Plan!$D$9,0)+IF(AND(N(Plan!$B$10)>0,N(C6)<=0),Plan!$D$10,0)+IF(AND(N(Plan!$B$11)>0,N(D6)<=0),Plan!$D$11,0)+IF(AND(N(Plan!$B$12)>0,N(E6)<=0),Plan!$D$12,0)+IF(AND(N(Plan!$B$13)>0,N(F6)<=0),Plan!$D$13,0)+IF(AND(N(Plan!$B$14)>0,N(G6)<=0),Plan!$D$14,0)+IF(AND(N(Plan!$B$15)>0,N(H6)<=0),Plan!$D$15,0)+IF(AND(N(Plan!$B$16)>0,N(I6)<=0),Plan!$D$16,0)+IF(AND(N(Plan!$B$17)>0,N(J6)<=0),Plan!$D$17,0)+IF(AND(N(Plan!$B$18)>0,N(K6)<=0),Plan!$D$18,0),0)))+IF(N(G6)<=0,0,MIN(G6*(1+Plan!$C$14/12),Plan!$D$14+IF(Plan!$E$14=$L7,Plan!$B$5+IF(AND(N(Plan!$B$9)>0,N(B6)<=0),Plan!$D$9,0)+IF(AND(N(Plan!$B$10)>0,N(C6)<=0),Plan!$D$10,0)+IF(AND(N(Plan!$B$11)>0,N(D6)<=0),Plan!$D$11,0)+IF(AND(N(Plan!$B$12)>0,N(E6)<=0),Plan!$D$12,0)+IF(AND(N(Plan!$B$13)>0,N(F6)<=0),Plan!$D$13,0)+IF(AND(N(Plan!$B$14)>0,N(G6)<=0),Plan!$D$14,0)+IF(AND(N(Plan!$B$15)>0,N(H6)<=0),Plan!$D$15,0)+IF(AND(N(Plan!$B$16)>0,N(I6)<=0),Plan!$D$16,0)+IF(AND(N(Plan!$B$17)>0,N(J6)<=0),Plan!$D$17,0)+IF(AND(N(Plan!$B$18)>0,N(K6)<=0),Plan!$D$18,0),0)))+IF(N(H6)<=0,0,MIN(H6*(1+Plan!$C$15/12),Plan!$D$15+IF(Plan!$E$15=$L7,Plan!$B$5+IF(AND(N(Plan!$B$9)>0,N(B6)<=0),Plan!$D$9,0)+IF(AND(N(Plan!$B$10)>0,N(C6)<=0),Plan!$D$10,0)+IF(AND(N(Plan!$B$11)>0,N(D6)<=0),Plan!$D$11,0)+IF(AND(N(Plan!$B$12)>0,N(E6)<=0),Plan!$D$12,0)+IF(AND(N(Plan!$B$13)>0,N(F6)<=0),Plan!$D$13,0)+IF(AND(N(Plan!$B$14)>0,N(G6)<=0),Plan!$D$14,0)+IF(AND(N(Plan!$B$15)>0,N(H6)<=0),Plan!$D$15,0)+IF(AND(N(Plan!$B$16)>0,N(I6)<=0),Plan!$D$16,0)+IF(AND(N(Plan!$B$17)>0,N(J6)<=0),Plan!$D$17,0)+IF(AND(N(Plan!$B$18)>0,N(K6)<=0),Plan!$D$18,0),0)))+IF(N(I6)<=0,0,MIN(I6*(1+Plan!$C$16/12),Plan!$D$16+IF(Plan!$E$16=$L7,Plan!$B$5+IF(AND(N(Plan!$B$9)>0,N(B6)<=0),Plan!$D$9,0)+IF(AND(N(Plan!$B$10)>0,N(C6)<=0),Plan!$D$10,0)+IF(AND(N(Plan!$B$11)>0,N(D6)<=0),Plan!$D$11,0)+IF(AND(N(Plan!$B$12)>0,N(E6)<=0),Plan!$D$12,0)+IF(AND(N(Plan!$B$13)>0,N(F6)<=0),Plan!$D$13,0)+IF(AND(N(Plan!$B$14)>0,N(G6)<=0),Plan!$D$14,0)+IF(AND(N(Plan!$B$15)>0,N(H6)<=0),Plan!$D$15,0)+IF(AND(N(Plan!$B$16)>0,N(I6)<=0),Plan!$D$16,0)+IF(AND(N(Plan!$B$17)>0,N(J6)<=0),Plan!$D$17,0)+IF(AND(N(Plan!$B$18)>0,N(K6)<=0),Plan!$D$18,0),0)))+IF(N(J6)<=0,0,MIN(J6*(1+Plan!$C$17/12),Plan!$D$17+IF(Plan!$E$17=$L7,Plan!$B$5+IF(AND(N(Plan!$B$9)>0,N(B6)<=0),Plan!$D$9,0)+IF(AND(N(Plan!$B$10)>0,N(C6)<=0),Plan!$D$10,0)+IF(AND(N(Plan!$B$11)>0,N(D6)<=0),Plan!$D$11,0)+IF(AND(N(Plan!$B$12)>0,N(E6)<=0),Plan!$D$12,0)+IF(AND(N(Plan!$B$13)>0,N(F6)<=0),Plan!$D$13,0)+IF(AND(N(Plan!$B$14)>0,N(G6)<=0),Plan!$D$14,0)+IF(AND(N(Plan!$B$15)>0,N(H6)<=0),Plan!$D$15,0)+IF(AND(N(Plan!$B$16)>0,N(I6)<=0),Plan!$D$16,0)+IF(AND(N(Plan!$B$17)>0,N(J6)<=0),Plan!$D$17,0)+IF(AND(N(Plan!$B$18)>0,N(K6)<=0),Plan!$D$18,0),0)))+IF(N(K6)<=0,0,MIN(K6*(1+Plan!$C$18/12),Plan!$D$18+IF(Plan!$E$18=$L7,Plan!$B$5+IF(AND(N(Plan!$B$9)>0,N(B6)<=0),Plan!$D$9,0)+IF(AND(N(Plan!$B$10)>0,N(C6)<=0),Plan!$D$10,0)+IF(AND(N(Plan!$B$11)>0,N(D6)<=0),Plan!$D$11,0)+IF(AND(N(Plan!$B$12)>0,N(E6)<=0),Plan!$D$12,0)+IF(AND(N(Plan!$B$13)>0,N(F6)<=0),Plan!$D$13,0)+IF(AND(N(Plan!$B$14)>0,N(G6)<=0),Plan!$D$14,0)+IF(AND(N(Plan!$B$15)>0,N(H6)<=0),Plan!$D$15,0)+IF(AND(N(Plan!$B$16)>0,N(I6)<=0),Plan!$D$16,0)+IF(AND(N(Plan!$B$17)>0,N(J6)<=0),Plan!$D$17,0)+IF(AND(N(Plan!$B$18)>0,N(K6)<=0),Plan!$D$18,0),0)))
A8: 4 | B8: =IF(N(B7)<=0,0,MAX(0,B7*(1+Plan!$C$9/12)-(Plan!$D$9+IF(Plan!$E$9=$L8,Plan!$B$5+IF(AND(N(Plan!$B$9)>0,N(B7)<=0),Plan!$D$9,0)+IF(AND(N(Plan!$B$10)>0,N(C7)<=0),Plan!$D$10,0)+IF(AND(N(Plan!$B$11)>0,N(D7)<=0),Plan!$D$11,0)+IF(AND(N(Plan!$B$12)>0,N(E7)<=0),Plan!$D$12,0)+IF(AND(N(Plan!$B$13)>0,N(F7)<=0),Plan!$D$13,0)+IF(AND(N(Plan!$B$14)>0,N(G7)<=0),Plan!$D$14,0)+IF(AND(N(Plan!$B$15)>0,N(H7)<=0),Plan!$D$15,0)+IF(AND(N(Plan!$B$16)>0,N(I7)<=0),Plan!$D$16,0)+IF(AND(N(Plan!$B$17)>0,N(J7)<=0),Plan!$D$17,0)+IF(AND(N(Plan!$B$18)>0,N(K7)<=0),Plan!$D$18,0),0)))) | C8: =IF(N(C7)<=0,0,MAX(0,C7*(1+Plan!$C$10/12)-(Plan!$D$10+IF(Plan!$E$10=$L8,Plan!$B$5+IF(AND(N(Plan!$B$9)>0,N(B7)<=0),Plan!$D$9,0)+IF(AND(N(Plan!$B$10)>0,N(C7)<=0),Plan!$D$10,0)+IF(AND(N(Plan!$B$11)>0,N(D7)<=0),Plan!$D$11,0)+IF(AND(N(Plan!$B$12)>0,N(E7)<=0),Plan!$D$12,0)+IF(AND(N(Plan!$B$13)>0,N(F7)<=0),Plan!$D$13,0)+IF(AND(N(Plan!$B$14)>0,N(G7)<=0),Plan!$D$14,0)+IF(AND(N(Plan!$B$15)>0,N(H7)<=0),Plan!$D$15,0)+IF(AND(N(Plan!$B$16)>0,N(I7)<=0),Plan!$D$16,0)+IF(AND(N(Plan!$B$17)>0,N(J7)<=0),Plan!$D$17,0)+IF(AND(N(Plan!$B$18)>0,N(K7)<=0),Plan!$D$18,0),0)))) | D8: =IF(N(D7)<=0,0,MAX(0,D7*(1+Plan!$C$11/12)-(Plan!$D$11+IF(Plan!$E$11=$L8,Plan!$B$5+IF(AND(N(Plan!$B$9)>0,N(B7)<=0),Plan!$D$9,0)+IF(AND(N(Plan!$B$10)>0,N(C7)<=0),Plan!$D$10,0)+IF(AND(N(Plan!$B$11)>0,N(D7)<=0),Plan!$D$11,0)+IF(AND(N(Plan!$B$12)>0,N(E7)<=0),Plan!$D$12,0)+IF(AND(N(Plan!$B$13)>0,N(F7)<=0),Plan!$D$13,0)+IF(AND(N(Plan!$B$14)>0,N(G7)<=0),Plan!$D$14,0)+IF(AND(N(Plan!$B$15)>0,N(H7)<=0),Plan!$D$15,0)+IF(AND(N(Plan!$B$16)>0,N(I7)<=0),Plan!$D$16,0)+IF(AND(N(Plan!$B$17)>0,N(J7)<=0),Plan!$D$17,0)+IF(AND(N(Plan!$B$18)>0,N(K7)<=0),Plan!$D$18,0),0)))) | E8: =IF(N(E7)<=0,0,MAX(0,E7*(1+Plan!$C$12/12)-(Plan!$D$12+IF(Plan!$E$12=$L8,Plan!$B$5+IF(AND(N(Plan!$B$9)>0,N(B7)<=0),Plan!$D$9,0)+IF(AND(N(Plan!$B$10)>0,N(C7)<=0),Plan!$D$10,0)+IF(AND(N(Plan!$B$11)>0,N(D7)<=0),Plan!$D$11,0)+IF(AND(N(Plan!$B$12)>0,N(E7)<=0),Plan!$D$12,0)+IF(AND(N(Plan!$B$13)>0,N(F7)<=0),Plan!$D$13,0)+IF(AND(N(Plan!$B$14)>0,N(G7)<=0),Plan!$D$14,0)+IF(AND(N(Plan!$B$15)>0,N(H7)<=0),Plan!$D$15,0)+IF(AND(N(Plan!$B$16)>0,N(I7)<=0),Plan!$D$16,0)+IF(AND(N(Plan!$B$17)>0,N(J7)<=0),Plan!$D$17,0)+IF(AND(N(Plan!$B$18)>0,N(K7)<=0),Plan!$D$18,0),0)))) | F8: =IF(N(F7)<=0,0,MAX(0,F7*(1+Plan!$C$13/12)-(Plan!$D$13+IF(Plan!$E$13=$L8,Plan!$B$5+IF(AND(N(Plan!$B$9)>0,N(B7)<=0),Plan!$D$9,0)+IF(AND(N(Plan!$B$10)>0,N(C7)<=0),Plan!$D$10,0)+IF(AND(N(Plan!$B$11)>0,N(D7)<=0),Plan!$D$11,0)+IF(AND(N(Plan!$B$12)>0,N(E7)<=0),Plan!$D$12,0)+IF(AND(N(Plan!$B$13)>0,N(F7)<=0),Plan!$D$13,0)+IF(AND(N(Plan!$B$14)>0,N(G7)<=0),Plan!$D$14,0)+IF(AND(N(Plan!$B$15)>0,N(H7)<=0),Plan!$D$15,0)+IF(AND(N(Plan!$B$16)>0,N(I7)<=0),Plan!$D$16,0)+IF(AND(N(Plan!$B$17)>0,N(J7)<=0),Plan!$D$17,0)+IF(AND(N(Plan!$B$18)>0,N(K7)<=0),Plan!$D$18,0),0)))) | G8: =IF(N(G7)<=0,0,MAX(0,G7*(1+Plan!$C$14/12)-(Plan!$D$14+IF(Plan!$E$14=$L8,Plan!$B$5+IF(AND(N(Plan!$B$9)>0,N(B7)<=0),Plan!$D$9,0)+IF(AND(N(Plan!$B$10)>0,N(C7)<=0),Plan!$D$10,0)+IF(AND(N(Plan!$B$11)>0,N(D7)<=0),Plan!$D$11,0)+IF(AND(N(Plan!$B$12)>0,N(E7)<=0),Plan!$D$12,0)+IF(AND(N(Plan!$B$13)>0,N(F7)<=0),Plan!$D$13,0)+IF(AND(N(Plan!$B$14)>0,N(G7)<=0),Plan!$D$14,0)+IF(AND(N(Plan!$B$15)>0,N(H7)<=0),Plan!$D$15,0)+IF(AND(N(Plan!$B$16)>0,N(I7)<=0),Plan!$D$16,0)+IF(AND(N(Plan!$B$17)>0,N(J7)<=0),Plan!$D$17,0)+IF(AND(N(Plan!$B$18)>0,N(K7)<=0),Plan!$D$18,0),0)))) | H8: =IF(N(H7)<=0,0,MAX(0,H7*(1+Plan!$C$15/12)-(Plan!$D$15+IF(Plan!$E$15=$L8,Plan!$B$5+IF(AND(N(Plan!$B$9)>0,N(B7)<=0),Plan!$D$9,0)+IF(AND(N(Plan!$B$10)>0,N(C7)<=0),Plan!$D$10,0)+IF(AND(N(Plan!$B$11)>0,N(D7)<=0),Plan!$D$11,0)+IF(AND(N(Plan!$B$12)>0,N(E7)<=0),Plan!$D$12,0)+IF(AND(N(Plan!$B$13)>0,N(F7)<=0),Plan!$D$13,0)+IF(AND(N(Plan!$B$14)>0,N(G7)<=0),Plan!$D$14,0)+IF(AND(N(Plan!$B$15)>0,N(H7)<=0),Plan!$D$15,0)+IF(AND(N(Plan!$B$16)>0,N(I7)<=0),Plan!$D$16,0)+IF(AND(N(Plan!$B$17)>0,N(J7)<=0),Plan!$D$17,0)+IF(AND(N(Plan!$B$18)>0,N(K7)<=0),Plan!$D$18,0),0)))) | I8: =IF(N(I7)<=0,0,MAX(0,I7*(1+Plan!$C$16/12)-(Plan!$D$16+IF(Plan!$E$16=$L8,Plan!$B$5+IF(AND(N(Plan!$B$9)>0,N(B7)<=0),Plan!$D$9,0)+IF(AND(N(Plan!$B$10)>0,N(C7)<=0),Plan!$D$10,0)+IF(AND(N(Plan!$B$11)>0,N(D7)<=0),Plan!$D$11,0)+IF(AND(N(Plan!$B$12)>0,N(E7)<=0),Plan!$D$12,0)+IF(AND(N(Plan!$B$13)>0,N(F7)<=0),Plan!$D$13,0)+IF(AND(N(Plan!$B$14)>0,N(G7)<=0),Plan!$D$14,0)+IF(AND(N(Plan!$B$15)>0,N(H7)<=0),Plan!$D$15,0)+IF(AND(N(Plan!$B$16)>0,N(I7)<=0),Plan!$D$16,0)+IF(AND(N(Plan!$B$17)>0,N(J7)<=0),Plan!$D$17,0)+IF(AND(N(Plan!$B$18)>0,N(K7)<=0),Plan!$D$18,0),0)))) | J8: =IF(N(J7)<=0,0,MAX(0,J7*(1+Plan!$C$17/12)-(Plan!$D$17+IF(Plan!$E$17=$L8,Plan!$B$5+IF(AND(N(Plan!$B$9)>0,N(B7)<=0),Plan!$D$9,0)+IF(AND(N(Plan!$B$10)>0,N(C7)<=0),Plan!$D$10,0)+IF(AND(N(Plan!$B$11)>0,N(D7)<=0),Plan!$D$11,0)+IF(AND(N(Plan!$B$12)>0,N(E7)<=0),Plan!$D$12,0)+IF(AND(N(Plan!$B$13)>0,N(F7)<=0),Plan!$D$13,0)+IF(AND(N(Plan!$B$14)>0,N(G7)<=0),Plan!$D$14,0)+IF(AND(N(Plan!$B$15)>0,N(H7)<=0),Plan!$D$15,0)+IF(AND(N(Plan!$B$16)>0,N(I7)<=0),Plan!$D$16,0)+IF(AND(N(Plan!$B$17)>0,N(J7)<=0),Plan!$D$17,0)+IF(AND(N(Plan!$B$18)>0,N(K7)<=0),Plan!$D$18,0),0)))) | K8: =IF(N(K7)<=0,0,MAX(0,K7*(1+Plan!$C$18/12)-(Plan!$D$18+IF(Plan!$E$18=$L8,Plan!$B$5+IF(AND(N(Plan!$B$9)>0,N(B7)<=0),Plan!$D$9,0)+IF(AND(N(Plan!$B$10)>0,N(C7)<=0),Plan!$D$10,0)+IF(AND(N(Plan!$B$11)>0,N(D7)<=0),Plan!$D$11,0)+IF(AND(N(Plan!$B$12)>0,N(E7)<=0),Plan!$D$12,0)+IF(AND(N(Plan!$B$13)>0,N(F7)<=0),Plan!$D$13,0)+IF(AND(N(Plan!$B$14)>0,N(G7)<=0),Plan!$D$14,0)+IF(AND(N(Plan!$B$15)>0,N(H7)<=0),Plan!$D$15,0)+IF(AND(N(Plan!$B$16)>0,N(I7)<=0),Plan!$D$16,0)+IF(AND(N(Plan!$B$17)>0,N(J7)<=0),Plan!$D$17,0)+IF(AND(N(Plan!$B$18)>0,N(K7)<=0),Plan!$D$18,0),0)))) | L8: =MIN(IF(N(B7)>0,Plan!$E$9,999),IF(N(C7)>0,Plan!$E$10,999),IF(N(D7)>0,Plan!$E$11,999),IF(N(E7)>0,Plan!$E$12,999),IF(N(F7)>0,Plan!$E$13,999),IF(N(G7)>0,Plan!$E$14,999),IF(N(H7)>0,Plan!$E$15,999),IF(N(I7)>0,Plan!$E$16,999),IF(N(J7)>0,Plan!$E$17,999),IF(N(K7)>0,Plan!$E$18,999)) | M8: =IF(N(B7)<=0,0,MIN(B7*(1+Plan!$C$9/12),Plan!$D$9+IF(Plan!$E$9=$L8,Plan!$B$5+IF(AND(N(Plan!$B$9)>0,N(B7)<=0),Plan!$D$9,0)+IF(AND(N(Plan!$B$10)>0,N(C7)<=0),Plan!$D$10,0)+IF(AND(N(Plan!$B$11)>0,N(D7)<=0),Plan!$D$11,0)+IF(AND(N(Plan!$B$12)>0,N(E7)<=0),Plan!$D$12,0)+IF(AND(N(Plan!$B$13)>0,N(F7)<=0),Plan!$D$13,0)+IF(AND(N(Plan!$B$14)>0,N(G7)<=0),Plan!$D$14,0)+IF(AND(N(Plan!$B$15)>0,N(H7)<=0),Plan!$D$15,0)+IF(AND(N(Plan!$B$16)>0,N(I7)<=0),Plan!$D$16,0)+IF(AND(N(Plan!$B$17)>0,N(J7)<=0),Plan!$D$17,0)+IF(AND(N(Plan!$B$18)>0,N(K7)<=0),Plan!$D$18,0),0)))+IF(N(C7)<=0,0,MIN(C7*(1+Plan!$C$10/12),Plan!$D$10+IF(Plan!$E$10=$L8,Plan!$B$5+IF(AND(N(Plan!$B$9)>0,N(B7)<=0),Plan!$D$9,0)+IF(AND(N(Plan!$B$10)>0,N(C7)<=0),Plan!$D$10,0)+IF(AND(N(Plan!$B$11)>0,N(D7)<=0),Plan!$D$11,0)+IF(AND(N(Plan!$B$12)>0,N(E7)<=0),Plan!$D$12,0)+IF(AND(N(Plan!$B$13)>0,N(F7)<=0),Plan!$D$13,0)+IF(AND(N(Plan!$B$14)>0,N(G7)<=0),Plan!$D$14,0)+IF(AND(N(Plan!$B$15)>0,N(H7)<=0),Plan!$D$15,0)+IF(AND(N(Plan!$B$16)>0,N(I7)<=0),Plan!$D$16,0)+IF(AND(N(Plan!$B$17)>0,N(J7)<=0),Plan!$D$17,0)+IF(AND(N(Plan!$B$18)>0,N(K7)<=0),Plan!$D$18,0),0)))+IF(N(D7)<=0,0,MIN(D7*(1+Plan!$C$11/12),Plan!$D$11+IF(Plan!$E$11=$L8,Plan!$B$5+IF(AND(N(Plan!$B$9)>0,N(B7)<=0),Plan!$D$9,0)+IF(AND(N(Plan!$B$10)>0,N(C7)<=0),Plan!$D$10,0)+IF(AND(N(Plan!$B$11)>0,N(D7)<=0),Plan!$D$11,0)+IF(AND(N(Plan!$B$12)>0,N(E7)<=0),Plan!$D$12,0)+IF(AND(N(Plan!$B$13)>0,N(F7)<=0),Plan!$D$13,0)+IF(AND(N(Plan!$B$14)>0,N(G7)<=0),Plan!$D$14,0)+IF(AND(N(Plan!$B$15)>0,N(H7)<=0),Plan!$D$15,0)+IF(AND(N(Plan!$B$16)>0,N(I7)<=0),Plan!$D$16,0)+IF(AND(N(Plan!$B$17)>0,N(J7)<=0),Plan!$D$17,0)+IF(AND(N(Plan!$B$18)>0,N(K7)<=0),Plan!$D$18,0),0)))+IF(N(E7)<=0,0,MIN(E7*(1+Plan!$C$12/12),Plan!$D$12+IF(Plan!$E$12=$L8,Plan!$B$5+IF(AND(N(Plan!$B$9)>0,N(B7)<=0),Plan!$D$9,0)+IF(AND(N(Plan!$B$10)>0,N(C7)<=0),Plan!$D$10,0)+IF(AND(N(Plan!$B$11)>0,N(D7)<=0),Plan!$D$11,0)+IF(AND(N(Plan!$B$12)>0,N(E7)<=0),Plan!$D$12,0)+IF(AND(N(Plan!$B$13)>0,N(F7)<=0),Plan!$D$13,0)+IF(AND(N(Plan!$B$14)>0,N(G7)<=0),Plan!$D$14,0)+IF(AND(N(Plan!$B$15)>0,N(H7)<=0),Plan!$D$15,0)+IF(AND(N(Plan!$B$16)>0,N(I7)<=0),Plan!$D$16,0)+IF(AND(N(Plan!$B$17)>0,N(J7)<=0),Plan!$D$17,0)+IF(AND(N(Plan!$B$18)>0,N(K7)<=0),Plan!$D$18,0),0)))+IF(N(F7)<=0,0,MIN(F7*(1+Plan!$C$13/12),Plan!$D$13+IF(Plan!$E$13=$L8,Plan!$B$5+IF(AND(N(Plan!$B$9)>0,N(B7)<=0),Plan!$D$9,0)+IF(AND(N(Plan!$B$10)>0,N(C7)<=0),Plan!$D$10,0)+IF(AND(N(Plan!$B$11)>0,N(D7)<=0),Plan!$D$11,0)+IF(AND(N(Plan!$B$12)>0,N(E7)<=0),Plan!$D$12,0)+IF(AND(N(Plan!$B$13)>0,N(F7)<=0),Plan!$D$13,0)+IF(AND(N(Plan!$B$14)>0,N(G7)<=0),Plan!$D$14,0)+IF(AND(N(Plan!$B$15)>0,N(H7)<=0),Plan!$D$15,0)+IF(AND(N(Plan!$B$16)>0,N(I7)<=0),Plan!$D$16,0)+IF(AND(N(Plan!$B$17)>0,N(J7)<=0),Plan!$D$17,0)+IF(AND(N(Plan!$B$18)>0,N(K7)<=0),Plan!$D$18,0),0)))+IF(N(G7)<=0,0,MIN(G7*(1+Plan!$C$14/12),Plan!$D$14+IF(Plan!$E$14=$L8,Plan!$B$5+IF(AND(N(Plan!$B$9)>0,N(B7)<=0),Plan!$D$9,0)+IF(AND(N(Plan!$B$10)>0,N(C7)<=0),Plan!$D$10,0)+IF(AND(N(Plan!$B$11)>0,N(D7)<=0),Plan!$D$11,0)+IF(AND(N(Plan!$B$12)>0,N(E7)<=0),Plan!$D$12,0)+IF(AND(N(Plan!$B$13)>0,N(F7)<=0),Plan!$D$13,0)+IF(AND(N(Plan!$B$14)>0,N(G7)<=0),Plan!$D$14,0)+IF(AND(N(Plan!$B$15)>0,N(H7)<=0),Plan!$D$15,0)+IF(AND(N(Plan!$B$16)>0,N(I7)<=0),Plan!$D$16,0)+IF(AND(N(Plan!$B$17)>0,N(J7)<=0),Plan!$D$17,0)+IF(AND(N(Plan!$B$18)>0,N(K7)<=0),Plan!$D$18,0),0)))+IF(N(H7)<=0,0,MIN(H7*(1+Plan!$C$15/12),Plan!$D$15+IF(Plan!$E$15=$L8,Plan!$B$5+IF(AND(N(Plan!$B$9)>0,N(B7)<=0),Plan!$D$9,0)+IF(AND(N(Plan!$B$10)>0,N(C7)<=0),Plan!$D$10,0)+IF(AND(N(Plan!$B$11)>0,N(D7)<=0),Plan!$D$11,0)+IF(AND(N(Plan!$B$12)>0,N(E7)<=0),Plan!$D$12,0)+IF(AND(N(Plan!$B$13)>0,N(F7)<=0),Plan!$D$13,0)+IF(AND(N(Plan!$B$14)>0,N(G7)<=0),Plan!$D$14,0)+IF(AND(N(Plan!$B$15)>0,N(H7)<=0),Plan!$D$15,0)+IF(AND(N(Plan!$B$16)>0,N(I7)<=0),Plan!$D$16,0)+IF(AND(N(Plan!$B$17)>0,N(J7)<=0),Plan!$D$17,0)+IF(AND(N(Plan!$B$18)>0,N(K7)<=0),Plan!$D$18,0),0)))+IF(N(I7)<=0,0,MIN(I7*(1+Plan!$C$16/12),Plan!$D$16+IF(Plan!$E$16=$L8,Plan!$B$5+IF(AND(N(Plan!$B$9)>0,N(B7)<=0),Plan!$D$9,0)+IF(AND(N(Plan!$B$10)>0,N(C7)<=0),Plan!$D$10,0)+IF(AND(N(Plan!$B$11)>0,N(D7)<=0),Plan!$D$11,0)+IF(AND(N(Plan!$B$12)>0,N(E7)<=0),Plan!$D$12,0)+IF(AND(N(Plan!$B$13)>0,N(F7)<=0),Plan!$D$13,0)+IF(AND(N(Plan!$B$14)>0,N(G7)<=0),Plan!$D$14,0)+IF(AND(N(Plan!$B$15)>0,N(H7)<=0),Plan!$D$15,0)+IF(AND(N(Plan!$B$16)>0,N(I7)<=0),Plan!$D$16,0)+IF(AND(N(Plan!$B$17)>0,N(J7)<=0),Plan!$D$17,0)+IF(AND(N(Plan!$B$18)>0,N(K7)<=0),Plan!$D$18,0),0)))+IF(N(J7)<=0,0,MIN(J7*(1+Plan!$C$17/12),Plan!$D$17+IF(Plan!$E$17=$L8,Plan!$B$5+IF(AND(N(Plan!$B$9)>0,N(B7)<=0),Plan!$D$9,0)+IF(AND(N(Plan!$B$10)>0,N(C7)<=0),Plan!$D$10,0)+IF(AND(N(Plan!$B$11)>0,N(D7)<=0),Plan!$D$11,0)+IF(AND(N(Plan!$B$12)>0,N(E7)<=0),Plan!$D$12,0)+IF(AND(N(Plan!$B$13)>0,N(F7)<=0),Plan!$D$13,0)+IF(AND(N(Plan!$B$14)>0,N(G7)<=0),Plan!$D$14,0)+IF(AND(N(Plan!$B$15)>0,N(H7)<=0),Plan!$D$15,0)+IF(AND(N(Plan!$B$16)>0,N(I7)<=0),Plan!$D$16,0)+IF(AND(N(Plan!$B$17)>0,N(J7)<=0),Plan!$D$17,0)+IF(AND(N(Plan!$B$18)>0,N(K7)<=0),Plan!$D$18,0),0)))+IF(N(K7)<=0,0,MIN(K7*(1+Plan!$C$18/12),Plan!$D$18+IF(Plan!$E$18=$L8,Plan!$B$5+IF(AND(N(Plan!$B$9)>0,N(B7)<=0),Plan!$D$9,0)+IF(AND(N(Plan!$B$10)>0,N(C7)<=0),Plan!$D$10,0)+IF(AND(N(Plan!$B$11)>0,N(D7)<=0),Plan!$D$11,0)+IF(AND(N(Plan!$B$12)>0,N(E7)<=0),Plan!$D$12,0)+IF(AND(N(Plan!$B$13)>0,N(F7)<=0),Plan!$D$13,0)+IF(AND(N(Plan!$B$14)>0,N(G7)<=0),Plan!$D$14,0)+IF(AND(N(Plan!$B$15)>0,N(H7)<=0),Plan!$D$15,0)+IF(AND(N(Plan!$B$16)>0,N(I7)<=0),Plan!$D$16,0)+IF(AND(N(Plan!$B$17)>0,N(J7)<=0),Plan!$D$17,0)+IF(AND(N(Plan!$B$18)>0,N(K7)<=0),Plan!$D$18,0),0)))
A9: 5 | B9: =IF(N(B8)<=0,0,MAX(0,B8*(1+Plan!$C$9/12)-(Plan!$D$9+IF(Plan!$E$9=$L9,Plan!$B$5+IF(AND(N(Plan!$B$9)>0,N(B8)<=0),Plan!$D$9,0)+IF(AND(N(Plan!$B$10)>0,N(C8)<=0),Plan!$D$10,0)+IF(AND(N(Plan!$B$11)>0,N(D8)<=0),Plan!$D$11,0)+IF(AND(N(Plan!$B$12)>0,N(E8)<=0),Plan!$D$12,0)+IF(AND(N(Plan!$B$13)>0,N(F8)<=0),Plan!$D$13,0)+IF(AND(N(Plan!$B$14)>0,N(G8)<=0),Plan!$D$14,0)+IF(AND(N(Plan!$B$15)>0,N(H8)<=0),Plan!$D$15,0)+IF(AND(N(Plan!$B$16)>0,N(I8)<=0),Plan!$D$16,0)+IF(AND(N(Plan!$B$17)>0,N(J8)<=0),Plan!$D$17,0)+IF(AND(N(Plan!$B$18)>0,N(K8)<=0),Plan!$D$18,0),0)))) | C9: =IF(N(C8)<=0,0,MAX(0,C8*(1+Plan!$C$10/12)-(Plan!$D$10+IF(Plan!$E$10=$L9,Plan!$B$5+IF(AND(N(Plan!$B$9)>0,N(B8)<=0),Plan!$D$9,0)+IF(AND(N(Plan!$B$10)>0,N(C8)<=0),Plan!$D$10,0)+IF(AND(N(Plan!$B$11)>0,N(D8)<=0),Plan!$D$11,0)+IF(AND(N(Plan!$B$12)>0,N(E8)<=0),Plan!$D$12,0)+IF(AND(N(Plan!$B$13)>0,N(F8)<=0),Plan!$D$13,0)+IF(AND(N(Plan!$B$14)>0,N(G8)<=0),Plan!$D$14,0)+IF(AND(N(Plan!$B$15)>0,N(H8)<=0),Plan!$D$15,0)+IF(AND(N(Plan!$B$16)>0,N(I8)<=0),Plan!$D$16,0)+IF(AND(N(Plan!$B$17)>0,N(J8)<=0),Plan!$D$17,0)+IF(AND(N(Plan!$B$18)>0,N(K8)<=0),Plan!$D$18,0),0)))) | D9: =IF(N(D8)<=0,0,MAX(0,D8*(1+Plan!$C$11/12)-(Plan!$D$11+IF(Plan!$E$11=$L9,Plan!$B$5+IF(AND(N(Plan!$B$9)>0,N(B8)<=0),Plan!$D$9,0)+IF(AND(N(Plan!$B$10)>0,N(C8)<=0),Plan!$D$10,0)+IF(AND(N(Plan!$B$11)>0,N(D8)<=0),Plan!$D$11,0)+IF(AND(N(Plan!$B$12)>0,N(E8)<=0),Plan!$D$12,0)+IF(AND(N(Plan!$B$13)>0,N(F8)<=0),Plan!$D$13,0)+IF(AND(N(Plan!$B$14)>0,N(G8)<=0),Plan!$D$14,0)+IF(AND(N(Plan!$B$15)>0,N(H8)<=0),Plan!$D$15,0)+IF(AND(N(Plan!$B$16)>0,N(I8)<=0),Plan!$D$16,0)+IF(AND(N(Plan!$B$17)>0,N(J8)<=0),Plan!$D$17,0)+IF(AND(N(Plan!$B$18)>0,N(K8)<=0),Plan!$D$18,0),0)))) | E9: =IF(N(E8)<=0,0,MAX(0,E8*(1+Plan!$C$12/12)-(Plan!$D$12+IF(Plan!$E$12=$L9,Plan!$B$5+IF(AND(N(Plan!$B$9)>0,N(B8)<=0),Plan!$D$9,0)+IF(AND(N(Plan!$B$10)>0,N(C8)<=0),Plan!$D$10,0)+IF(AND(N(Plan!$B$11)>0,N(D8)<=0),Plan!$D$11,0)+IF(AND(N(Plan!$B$12)>0,N(E8)<=0),Plan!$D$12,0)+IF(AND(N(Plan!$B$13)>0,N(F8)<=0),Plan!$D$13,0)+IF(AND(N(Plan!$B$14)>0,N(G8)<=0),Plan!$D$14,0)+IF(AND(N(Plan!$B$15)>0,N(H8)<=0),Plan!$D$15,0)+IF(AND(N(Plan!$B$16)>0,N(I8)<=0),Plan!$D$16,0)+IF(AND(N(Plan!$B$17)>0,N(J8)<=0),Plan!$D$17,0)+IF(AND(N(Plan!$B$18)>0,N(K8)<=0),Plan!$D$18,0),0)))) | F9: =IF(N(F8)<=0,0,MAX(0,F8*(1+Plan!$C$13/12)-(Plan!$D$13+IF(Plan!$E$13=$L9,Plan!$B$5+IF(AND(N(Plan!$B$9)>0,N(B8)<=0),Plan!$D$9,0)+IF(AND(N(Plan!$B$10)>0,N(C8)<=0),Plan!$D$10,0)+IF(AND(N(Plan!$B$11)>0,N(D8)<=0),Plan!$D$11,0)+IF(AND(N(Plan!$B$12)>0,N(E8)<=0),Plan!$D$12,0)+IF(AND(N(Plan!$B$13)>0,N(F8)<=0),Plan!$D$13,0)+IF(AND(N(Plan!$B$14)>0,N(G8)<=0),Plan!$D$14,0)+IF(AND(N(Plan!$B$15)>0,N(H8)<=0),Plan!$D$15,0)+IF(AND(N(Plan!$B$16)>0,N(I8)<=0),Plan!$D$16,0)+IF(AND(N(Plan!$B$17)>0,N(J8)<=0),Plan!$D$17,0)+IF(AND(N(Plan!$B$18)>0,N(K8)<=0),Plan!$D$18,0),0)))) | G9: =IF(N(G8)<=0,0,MAX(0,G8*(1+Plan!$C$14/12)-(Plan!$D$14+IF(Plan!$E$14=$L9,Plan!$B$5+IF(AND(N(Plan!$B$9)>0,N(B8)<=0),Plan!$D$9,0)+IF(AND(N(Plan!$B$10)>0,N(C8)<=0),Plan!$D$10,0)+IF(AND(N(Plan!$B$11)>0,N(D8)<=0),Plan!$D$11,0)+IF(AND(N(Plan!$B$12)>0,N(E8)<=0),Plan!$D$12,0)+IF(AND(N(Plan!$B$13)>0,N(F8)<=0),Plan!$D$13,0)+IF(AND(N(Plan!$B$14)>0,N(G8)<=0),Plan!$D$14,0)+IF(AND(N(Plan!$B$15)>0,N(H8)<=0),Plan!$D$15,0)+IF(AND(N(Plan!$B$16)>0,N(I8)<=0),Plan!$D$16,0)+IF(AND(N(Plan!$B$17)>0,N(J8)<=0),Plan!$D$17,0)+IF(AND(N(Plan!$B$18)>0,N(K8)<=0),Plan!$D$18,0),0)))) | H9: =IF(N(H8)<=0,0,MAX(0,H8*(1+Plan!$C$15/12)-(Plan!$D$15+IF(Plan!$E$15=$L9,Plan!$B$5+IF(AND(N(Plan!$B$9)>0,N(B8)<=0),Plan!$D$9,0)+IF(AND(N(Plan!$B$10)>0,N(C8)<=0),Plan!$D$10,0)+IF(AND(N(Plan!$B$11)>0,N(D8)<=0),Plan!$D$11,0)+IF(AND(N(Plan!$B$12)>0,N(E8)<=0),Plan!$D$12,0)+IF(AND(N(Plan!$B$13)>0,N(F8)<=0),Plan!$D$13,0)+IF(AND(N(Plan!$B$14)>0,N(G8)<=0),Plan!$D$14,0)+IF(AND(N(Plan!$B$15)>0,N(H8)<=0),Plan!$D$15,0)+IF(AND(N(Plan!$B$16)>0,N(I8)<=0),Plan!$D$16,0)+IF(AND(N(Plan!$B$17)>0,N(J8)<=0),Plan!$D$17,0)+IF(AND(N(Plan!$B$18)>0,N(K8)<=0),Plan!$D$18,0),0)))) | I9: =IF(N(I8)<=0,0,MAX(0,I8*(1+Plan!$C$16/12)-(Plan!$D$16+IF(Plan!$E$16=$L9,Plan!$B$5+IF(AND(N(Plan!$B$9)>0,N(B8)<=0),Plan!$D$9,0)+IF(AND(N(Plan!$B$10)>0,N(C8)<=0),Plan!$D$10,0)+IF(AND(N(Plan!$B$11)>0,N(D8)<=0),Plan!$D$11,0)+IF(AND(N(Plan!$B$12)>0,N(E8)<=0),Plan!$D$12,0)+IF(AND(N(Plan!$B$13)>0,N(F8)<=0),Plan!$D$13,0)+IF(AND(N(Plan!$B$14)>0,N(G8)<=0),Plan!$D$14,0)+IF(AND(N(Plan!$B$15)>0,N(H8)<=0),Plan!$D$15,0)+IF(AND(N(Plan!$B$16)>0,N(I8)<=0),Plan!$D$16,0)+IF(AND(N(Plan!$B$17)>0,N(J8)<=0),Plan!$D$17,0)+IF(AND(N(Plan!$B$18)>0,N(K8)<=0),Plan!$D$18,0),0)))) | J9: =IF(N(J8)<=0,0,MAX(0,J8*(1+Plan!$C$17/12)-(Plan!$D$17+IF(Plan!$E$17=$L9,Plan!$B$5+IF(AND(N(Plan!$B$9)>0,N(B8)<=0),Plan!$D$9,0)+IF(AND(N(Plan!$B$10)>0,N(C8)<=0),Plan!$D$10,0)+IF(AND(N(Plan!$B$11)>0,N(D8)<=0),Plan!$D$11,0)+IF(AND(N(Plan!$B$12)>0,N(E8)<=0),Plan!$D$12,0)+IF(AND(N(Plan!$B$13)>0,N(F8)<=0),Plan!$D$13,0)+IF(AND(N(Plan!$B$14)>0,N(G8)<=0),Plan!$D$14,0)+IF(AND(N(Plan!$B$15)>0,N(H8)<=0),Plan!$D$15,0)+IF(AND(N(Plan!$B$16)>0,N(I8)<=0),Plan!$D$16,0)+IF(AND(N(Plan!$B$17)>0,N(J8)<=0),Plan!$D$17,0)+IF(AND(N(Plan!$B$18)>0,N(K8)<=0),Plan!$D$18,0),0)))) | K9: =IF(N(K8)<=0,0,MAX(0,K8*(1+Plan!$C$18/12)-(Plan!$D$18+IF(Plan!$E$18=$L9,Plan!$B$5+IF(AND(N(Plan!$B$9)>0,N(B8)<=0),Plan!$D$9,0)+IF(AND(N(Plan!$B$10)>0,N(C8)<=0),Plan!$D$10,0)+IF(AND(N(Plan!$B$11)>0,N(D8)<=0),Plan!$D$11,0)+IF(AND(N(Plan!$B$12)>0,N(E8)<=0),Plan!$D$12,0)+IF(AND(N(Plan!$B$13)>0,N(F8)<=0),Plan!$D$13,0)+IF(AND(N(Plan!$B$14)>0,N(G8)<=0),Plan!$D$14,0)+IF(AND(N(Plan!$B$15)>0,N(H8)<=0),Plan!$D$15,0)+IF(AND(N(Plan!$B$16)>0,N(I8)<=0),Plan!$D$16,0)+IF(AND(N(Plan!$B$17)>0,N(J8)<=0),Plan!$D$17,0)+IF(AND(N(Plan!$B$18)>0,N(K8)<=0),Plan!$D$18,0),0)))) | L9: =MIN(IF(N(B8)>0,Plan!$E$9,999),IF(N(C8)>0,Plan!$E$10,999),IF(N(D8)>0,Plan!$E$11,999),IF(N(E8)>0,Plan!$E$12,999),IF(N(F8)>0,Plan!$E$13,999),IF(N(G8)>0,Plan!$E$14,999),IF(N(H8)>0,Plan!$E$15,999),IF(N(I8)>0,Plan!$E$16,999),IF(N(J8)>0,Plan!$E$17,999),IF(N(K8)>0,Plan!$E$18,999)) | M9: =IF(N(B8)<=0,0,MIN(B8*(1+Plan!$C$9/12),Plan!$D$9+IF(Plan!$E$9=$L9,Plan!$B$5+IF(AND(N(Plan!$B$9)>0,N(B8)<=0),Plan!$D$9,0)+IF(AND(N(Plan!$B$10)>0,N(C8)<=0),Plan!$D$10,0)+IF(AND(N(Plan!$B$11)>0,N(D8)<=0),Plan!$D$11,0)+IF(AND(N(Plan!$B$12)>0,N(E8)<=0),Plan!$D$12,0)+IF(AND(N(Plan!$B$13)>0,N(F8)<=0),Plan!$D$13,0)+IF(AND(N(Plan!$B$14)>0,N(G8)<=0),Plan!$D$14,0)+IF(AND(N(Plan!$B$15)>0,N(H8)<=0),Plan!$D$15,0)+IF(AND(N(Plan!$B$16)>0,N(I8)<=0),Plan!$D$16,0)+IF(AND(N(Plan!$B$17)>0,N(J8)<=0),Plan!$D$17,0)+IF(AND(N(Plan!$B$18)>0,N(K8)<=0),Plan!$D$18,0),0)))+IF(N(C8)<=0,0,MIN(C8*(1+Plan!$C$10/12),Plan!$D$10+IF(Plan!$E$10=$L9,Plan!$B$5+IF(AND(N(Plan!$B$9)>0,N(B8)<=0),Plan!$D$9,0)+IF(AND(N(Plan!$B$10)>0,N(C8)<=0),Plan!$D$10,0)+IF(AND(N(Plan!$B$11)>0,N(D8)<=0),Plan!$D$11,0)+IF(AND(N(Plan!$B$12)>0,N(E8)<=0),Plan!$D$12,0)+IF(AND(N(Plan!$B$13)>0,N(F8)<=0),Plan!$D$13,0)+IF(AND(N(Plan!$B$14)>0,N(G8)<=0),Plan!$D$14,0)+IF(AND(N(Plan!$B$15)>0,N(H8)<=0),Plan!$D$15,0)+IF(AND(N(Plan!$B$16)>0,N(I8)<=0),Plan!$D$16,0)+IF(AND(N(Plan!$B$17)>0,N(J8)<=0),Plan!$D$17,0)+IF(AND(N(Plan!$B$18)>0,N(K8)<=0),Plan!$D$18,0),0)))+IF(N(D8)<=0,0,MIN(D8*(1+Plan!$C$11/12),Plan!$D$11+IF(Plan!$E$11=$L9,Plan!$B$5+IF(AND(N(Plan!$B$9)>0,N(B8)<=0),Plan!$D$9,0)+IF(AND(N(Plan!$B$10)>0,N(C8)<=0),Plan!$D$10,0)+IF(AND(N(Plan!$B$11)>0,N(D8)<=0),Plan!$D$11,0)+IF(AND(N(Plan!$B$12)>0,N(E8)<=0),Plan!$D$12,0)+IF(AND(N(Plan!$B$13)>0,N(F8)<=0),Plan!$D$13,0)+IF(AND(N(Plan!$B$14)>0,N(G8)<=0),Plan!$D$14,0)+IF(AND(N(Plan!$B$15)>0,N(H8)<=0),Plan!$D$15,0)+IF(AND(N(Plan!$B$16)>0,N(I8)<=0),Plan!$D$16,0)+IF(AND(N(Plan!$B$17)>0,N(J8)<=0),Plan!$D$17,0)+IF(AND(N(Plan!$B$18)>0,N(K8)<=0),Plan!$D$18,0),0)))+IF(N(E8)<=0,0,MIN(E8*(1+Plan!$C$12/12),Plan!$D$12+IF(Plan!$E$12=$L9,Plan!$B$5+IF(AND(N(Plan!$B$9)>0,N(B8)<=0),Plan!$D$9,0)+IF(AND(N(Plan!$B$10)>0,N(C8)<=0),Plan!$D$10,0)+IF(AND(N(Plan!$B$11)>0,N(D8)<=0),Plan!$D$11,0)+IF(AND(N(Plan!$B$12)>0,N(E8)<=0),Plan!$D$12,0)+IF(AND(N(Plan!$B$13)>0,N(F8)<=0),Plan!$D$13,0)+IF(AND(N(Plan!$B$14)>0,N(G8)<=0),Plan!$D$14,0)+IF(AND(N(Plan!$B$15)>0,N(H8)<=0),Plan!$D$15,0)+IF(AND(N(Plan!$B$16)>0,N(I8)<=0),Plan!$D$16,0)+IF(AND(N(Plan!$B$17)>0,N(J8)<=0),Plan!$D$17,0)+IF(AND(N(Plan!$B$18)>0,N(K8)<=0),Plan!$D$18,0),0)))+IF(N(F8)<=0,0,MIN(F8*(1+Plan!$C$13/12),Plan!$D$13+IF(Plan!$E$13=$L9,Plan!$B$5+IF(AND(N(Plan!$B$9)>0,N(B8)<=0),Plan!$D$9,0)+IF(AND(N(Plan!$B$10)>0,N(C8)<=0),Plan!$D$10,0)+IF(AND(N(Plan!$B$11)>0,N(D8)<=0),Plan!$D$11,0)+IF(AND(N(Plan!$B$12)>0,N(E8)<=0),Plan!$D$12,0)+IF(AND(N(Plan!$B$13)>0,N(F8)<=0),Plan!$D$13,0)+IF(AND(N(Plan!$B$14)>0,N(G8)<=0),Plan!$D$14,0)+IF(AND(N(Plan!$B$15)>0,N(H8)<=0),Plan!$D$15,0)+IF(AND(N(Plan!$B$16)>0,N(I8)<=0),Plan!$D$16,0)+IF(AND(N(Plan!$B$17)>0,N(J8)<=0),Plan!$D$17,0)+IF(AND(N(Plan!$B$18)>0,N(K8)<=0),Plan!$D$18,0),0)))+IF(N(G8)<=0,0,MIN(G8*(1+Plan!$C$14/12),Plan!$D$14+IF(Plan!$E$14=$L9,Plan!$B$5+IF(AND(N(Plan!$B$9)>0,N(B8)<=0),Plan!$D$9,0)+IF(AND(N(Plan!$B$10)>0,N(C8)<=0),Plan!$D$10,0)+IF(AND(N(Plan!$B$11)>0,N(D8)<=0),Plan!$D$11,0)+IF(AND(N(Plan!$B$12)>0,N(E8)<=0),Plan!$D$12,0)+IF(AND(N(Plan!$B$13)>0,N(F8)<=0),Plan!$D$13,0)+IF(AND(N(Plan!$B$14)>0,N(G8)<=0),Plan!$D$14,0)+IF(AND(N(Plan!$B$15)>0,N(H8)<=0),Plan!$D$15,0)+IF(AND(N(Plan!$B$16)>0,N(I8)<=0),Plan!$D$16,0)+IF(AND(N(Plan!$B$17)>0,N(J8)<=0),Plan!$D$17,0)+IF(AND(N(Plan!$B$18)>0,N(K8)<=0),Plan!$D$18,0),0)))+IF(N(H8)<=0,0,MIN(H8*(1+Plan!$C$15/12),Plan!$D$15+IF(Plan!$E$15=$L9,Plan!$B$5+IF(AND(N(Plan!$B$9)>0,N(B8)<=0),Plan!$D$9,0)+IF(AND(N(Plan!$B$10)>0,N(C8)<=0),Plan!$D$10,0)+IF(AND(N(Plan!$B$11)>0,N(D8)<=0),Plan!$D$11,0)+IF(AND(N(Plan!$B$12)>0,N(E8)<=0),Plan!$D$12,0)+IF(AND(N(Plan!$B$13)>0,N(F8)<=0),Plan!$D$13,0)+IF(AND(N(Plan!$B$14)>0,N(G8)<=0),Plan!$D$14,0)+IF(AND(N(Plan!$B$15)>0,N(H8)<=0),Plan!$D$15,0)+IF(AND(N(Plan!$B$16)>0,N(I8)<=0),Plan!$D$16,0)+IF(AND(N(Plan!$B$17)>0,N(J8)<=0),Plan!$D$17,0)+IF(AND(N(Plan!$B$18)>0,N(K8)<=0),Plan!$D$18,0),0)))+IF(N(I8)<=0,0,MIN(I8*(1+Plan!$C$16/12),Plan!$D$16+IF(Plan!$E$16=$L9,Plan!$B$5+IF(AND(N(Plan!$B$9)>0,N(B8)<=0),Plan!$D$9,0)+IF(AND(N(Plan!$B$10)>0,N(C8)<=0),Plan!$D$10,0)+IF(AND(N(Plan!$B$11)>0,N(D8)<=0),Plan!$D$11,0)+IF(AND(N(Plan!$B$12)>0,N(E8)<=0),Plan!$D$12,0)+IF(AND(N(Plan!$B$13)>0,N(F8)<=0),Plan!$D$13,0)+IF(AND(N(Plan!$B$14)>0,N(G8)<=0),Plan!$D$14,0)+IF(AND(N(Plan!$B$15)>0,N(H8)<=0),Plan!$D$15,0)+IF(AND(N(Plan!$B$16)>0,N(I8)<=0),Plan!$D$16,0)+IF(AND(N(Plan!$B$17)>0,N(J8)<=0),Plan!$D$17,0)+IF(AND(N(Plan!$B$18)>0,N(K8)<=0),Plan!$D$18,0),0)))+IF(N(J8)<=0,0,MIN(J8*(1+Plan!$C$17/12),Plan!$D$17+IF(Plan!$E$17=$L9,Plan!$B$5+IF(AND(N(Plan!$B$9)>0,N(B8)<=0),Plan!$D$9,0)+IF(AND(N(Plan!$B$10)>0,N(C8)<=0),Plan!$D$10,0)+IF(AND(N(Plan!$B$11)>0,N(D8)<=0),Plan!$D$11,0)+IF(AND(N(Plan!$B$12)>0,N(E8)<=0),Plan!$D$12,0)+IF(AND(N(Plan!$B$13)>0,N(F8)<=0),Plan!$D$13,0)+IF(AND(N(Plan!$B$14)>0,N(G8)<=0),Plan!$D$14,0)+IF(AND(N(Plan!$B$15)>0,N(H8)<=0),Plan!$D$15,0)+IF(AND(N(Plan!$B$16)>0,N(I8)<=0),Plan!$D$16,0)+IF(AND(N(Plan!$B$17)>0,N(J8)<=0),Plan!$D$17,0)+IF(AND(N(Plan!$B$18)>0,N(K8)<=0),Plan!$D$18,0),0)))+IF(N(K8)<=0,0,MIN(K8*(1+Plan!$C$18/12),Plan!$D$18+IF(Plan!$E$18=$L9,Plan!$B$5+IF(AND(N(Plan!$B$9)>0,N(B8)<=0),Plan!$D$9,0)+IF(AND(N(Plan!$B$10)>0,N(C8)<=0),Plan!$D$10,0)+IF(AND(N(Plan!$B$11)>0,N(D8)<=0),Plan!$D$11,0)+IF(AND(N(Plan!$B$12)>0,N(E8)<=0),Plan!$D$12,0)+IF(AND(N(Plan!$B$13)>0,N(F8)<=0),Plan!$D$13,0)+IF(AND(N(Plan!$B$14)>0,N(G8)<=0),Plan!$D$14,0)+IF(AND(N(Plan!$B$15)>0,N(H8)<=0),Plan!$D$15,0)+IF(AND(N(Plan!$B$16)>0,N(I8)<=0),Plan!$D$16,0)+IF(AND(N(Plan!$B$17)>0,N(J8)<=0),Plan!$D$17,0)+IF(AND(N(Plan!$B$18)>0,N(K8)<=0),Plan!$D$18,0),0)))
A10: 6 | B10: =IF(N(B9)<=0,0,MAX(0,B9*(1+Plan!$C$9/12)-(Plan!$D$9+IF(Plan!$E$9=$L10,Plan!$B$5+IF(AND(N(Plan!$B$9)>0,N(B9)<=0),Plan!$D$9,0)+IF(AND(N(Plan!$B$10)>0,N(C9)<=0),Plan!$D$10,0)+IF(AND(N(Plan!$B$11)>0,N(D9)<=0),Plan!$D$11,0)+IF(AND(N(Plan!$B$12)>0,N(E9)<=0),Plan!$D$12,0)+IF(AND(N(Plan!$B$13)>0,N(F9)<=0),Plan!$D$13,0)+IF(AND(N(Plan!$B$14)>0,N(G9)<=0),Plan!$D$14,0)+IF(AND(N(Plan!$B$15)>0,N(H9)<=0),Plan!$D$15,0)+IF(AND(N(Plan!$B$16)>0,N(I9)<=0),Plan!$D$16,0)+IF(AND(N(Plan!$B$17)>0,N(J9)<=0),Plan!$D$17,0)+IF(AND(N(Plan!$B$18)>0,N(K9)<=0),Plan!$D$18,0),0)))) | C10: =IF(N(C9)<=0,0,MAX(0,C9*(1+Plan!$C$10/12)-(Plan!$D$10+IF(Plan!$E$10=$L10,Plan!$B$5+IF(AND(N(Plan!$B$9)>0,N(B9)<=0),Plan!$D$9,0)+IF(AND(N(Plan!$B$10)>0,N(C9)<=0),Plan!$D$10,0)+IF(AND(N(Plan!$B$11)>0,N(D9)<=0),Plan!$D$11,0)+IF(AND(N(Plan!$B$12)>0,N(E9)<=0),Plan!$D$12,0)+IF(AND(N(Plan!$B$13)>0,N(F9)<=0),Plan!$D$13,0)+IF(AND(N(Plan!$B$14)>0,N(G9)<=0),Plan!$D$14,0)+IF(AND(N(Plan!$B$15)>0,N(H9)<=0),Plan!$D$15,0)+IF(AND(N(Plan!$B$16)>0,N(I9)<=0),Plan!$D$16,0)+IF(AND(N(Plan!$B$17)>0,N(J9)<=0),Plan!$D$17,0)+IF(AND(N(Plan!$B$18)>0,N(K9)<=0),Plan!$D$18,0),0)))) | D10: =IF(N(D9)<=0,0,MAX(0,D9*(1+Plan!$C$11/12)-(Plan!$D$11+IF(Plan!$E$11=$L10,Plan!$B$5+IF(AND(N(Plan!$B$9)>0,N(B9)<=0),Plan!$D$9,0)+IF(AND(N(Plan!$B$10)>0,N(C9)<=0),Plan!$D$10,0)+IF(AND(N(Plan!$B$11)>0,N(D9)<=0),Plan!$D$11,0)+IF(AND(N(Plan!$B$12)>0,N(E9)<=0),Plan!$D$12,0)+IF(AND(N(Plan!$B$13)>0,N(F9)<=0),Plan!$D$13,0)+IF(AND(N(Plan!$B$14)>0,N(G9)<=0),Plan!$D$14,0)+IF(AND(N(Plan!$B$15)>0,N(H9)<=0),Plan!$D$15,0)+IF(AND(N(Plan!$B$16)>0,N(I9)<=0),Plan!$D$16,0)+IF(AND(N(Plan!$B$17)>0,N(J9)<=0),Plan!$D$17,0)+IF(AND(N(Plan!$B$18)>0,N(K9)<=0),Plan!$D$18,0),0)))) | E10: =IF(N(E9)<=0,0,MAX(0,E9*(1+Plan!$C$12/12)-(Plan!$D$12+IF(Plan!$E$12=$L10,Plan!$B$5+IF(AND(N(Plan!$B$9)>0,N(B9)<=0),Plan!$D$9,0)+IF(AND(N(Plan!$B$10)>0,N(C9)<=0),Plan!$D$10,0)+IF(AND(N(Plan!$B$11)>0,N(D9)<=0),Plan!$D$11,0)+IF(AND(N(Plan!$B$12)>0,N(E9)<=0),Plan!$D$12,0)+IF(AND(N(Plan!$B$13)>0,N(F9)<=0),Plan!$D$13,0)+IF(AND(N(Plan!$B$14)>0,N(G9)<=0),Plan!$D$14,0)+IF(AND(N(Plan!$B$15)>0,N(H9)<=0),Plan!$D$15,0)+IF(AND(N(Plan!$B$16)>0,N(I9)<=0),Plan!$D$16,0)+IF(AND(N(Plan!$B$17)>0,N(J9)<=0),Plan!$D$17,0)+IF(AND(N(Plan!$B$18)>0,N(K9)<=0),Plan!$D$18,0),0)))) | F10: =IF(N(F9)<=0,0,MAX(0,F9*(1+Plan!$C$13/12)-(Plan!$D$13+IF(Plan!$E$13=$L10,Plan!$B$5+IF(AND(N(Plan!$B$9)>0,N(B9)<=0),Plan!$D$9,0)+IF(AND(N(Plan!$B$10)>0,N(C9)<=0),Plan!$D$10,0)+IF(AND(N(Plan!$B$11)>0,N(D9)<=0),Plan!$D$11,0)+IF(AND(N(Plan!$B$12)>0,N(E9)<=0),Plan!$D$12,0)+IF(AND(N(Plan!$B$13)>0,N(F9)<=0),Plan!$D$13,0)+IF(AND(N(Plan!$B$14)>0,N(G9)<=0),Plan!$D$14,0)+IF(AND(N(Plan!$B$15)>0,N(H9)<=0),Plan!$D$15,0)+IF(AND(N(Plan!$B$16)>0,N(I9)<=0),Plan!$D$16,0)+IF(AND(N(Plan!$B$17)>0,N(J9)<=0),Plan!$D$17,0)+IF(AND(N(Plan!$B$18)>0,N(K9)<=0),Plan!$D$18,0),0)))) | G10: =IF(N(G9)<=0,0,MAX(0,G9*(1+Plan!$C$14/12)-(Plan!$D$14+IF(Plan!$E$14=$L10,Plan!$B$5+IF(AND(N(Plan!$B$9)>0,N(B9)<=0),Plan!$D$9,0)+IF(AND(N(Plan!$B$10)>0,N(C9)<=0),Plan!$D$10,0)+IF(AND(N(Plan!$B$11)>0,N(D9)<=0),Plan!$D$11,0)+IF(AND(N(Plan!$B$12)>0,N(E9)<=0),Plan!$D$12,0)+IF(AND(N(Plan!$B$13)>0,N(F9)<=0),Plan!$D$13,0)+IF(AND(N(Plan!$B$14)>0,N(G9)<=0),Plan!$D$14,0)+IF(AND(N(Plan!$B$15)>0,N(H9)<=0),Plan!$D$15,0)+IF(AND(N(Plan!$B$16)>0,N(I9)<=0),Plan!$D$16,0)+IF(AND(N(Plan!$B$17)>0,N(J9)<=0),Plan!$D$17,0)+IF(AND(N(Plan!$B$18)>0,N(K9)<=0),Plan!$D$18,0),0)))) | H10: =IF(N(H9)<=0,0,MAX(0,H9*(1+Plan!$C$15/12)-(Plan!$D$15+IF(Plan!$E$15=$L10,Plan!$B$5+IF(AND(N(Plan!$B$9)>0,N(B9)<=0),Plan!$D$9,0)+IF(AND(N(Plan!$B$10)>0,N(C9)<=0),Plan!$D$10,0)+IF(AND(N(Plan!$B$11)>0,N(D9)<=0),Plan!$D$11,0)+IF(AND(N(Plan!$B$12)>0,N(E9)<=0),Plan!$D$12,0)+IF(AND(N(Plan!$B$13)>0,N(F9)<=0),Plan!$D$13,0)+IF(AND(N(Plan!$B$14)>0,N(G9)<=0),Plan!$D$14,0)+IF(AND(N(Plan!$B$15)>0,N(H9)<=0),Plan!$D$15,0)+IF(AND(N(Plan!$B$16)>0,N(I9)<=0),Plan!$D$16,0)+IF(AND(N(Plan!$B$17)>0,N(J9)<=0),Plan!$D$17,0)+IF(AND(N(Plan!$B$18)>0,N(K9)<=0),Plan!$D$18,0),0)))) | I10: =IF(N(I9)<=0,0,MAX(0,I9*(1+Plan!$C$16/12)-(Plan!$D$16+IF(Plan!$E$16=$L10,Plan!$B$5+IF(AND(N(Plan!$B$9)>0,N(B9)<=0),Plan!$D$9,0)+IF(AND(N(Plan!$B$10)>0,N(C9)<=0),Plan!$D$10,0)+IF(AND(N(Plan!$B$11)>0,N(D9)<=0),Plan!$D$11,0)+IF(AND(N(Plan!$B$12)>0,N(E9)<=0),Plan!$D$12,0)+IF(AND(N(Plan!$B$13)>0,N(F9)<=0),Plan!$D$13,0)+IF(AND(N(Plan!$B$14)>0,N(G9)<=0),Plan!$D$14,0)+IF(AND(N(Plan!$B$15)>0,N(H9)<=0),Plan!$D$15,0)+IF(AND(N(Plan!$B$16)>0,N(I9)<=0),Plan!$D$16,0)+IF(AND(N(Plan!$B$17)>0,N(J9)<=0),Plan!$D$17,0)+IF(AND(N(Plan!$B$18)>0,N(K9)<=0),Plan!$D$18,0),0)))) | J10: =IF(N(J9)<=0,0,MAX(0,J9*(1+Plan!$C$17/12)-(Plan!$D$17+IF(Plan!$E$17=$L10,Plan!$B$5+IF(AND(N(Plan!$B$9)>0,N(B9)<=0),Plan!$D$9,0)+IF(AND(N(Plan!$B$10)>0,N(C9)<=0),Plan!$D$10,0)+IF(AND(N(Plan!$B$11)>0,N(D9)<=0),Plan!$D$11,0)+IF(AND(N(Plan!$B$12)>0,N(E9)<=0),Plan!$D$12,0)+IF(AND(N(Plan!$B$13)>0,N(F9)<=0),Plan!$D$13,0)+IF(AND(N(Plan!$B$14)>0,N(G9)<=0),Plan!$D$14,0)+IF(AND(N(Plan!$B$15)>0,N(H9)<=0),Plan!$D$15,0)+IF(AND(N(Plan!$B$16)>0,N(I9)<=0),Plan!$D$16,0)+IF(AND(N(Plan!$B$17)>0,N(J9)<=0),Plan!$D$17,0)+IF(AND(N(Plan!$B$18)>0,N(K9)<=0),Plan!$D$18,0),0)))) | K10: =IF(N(K9)<=0,0,MAX(0,K9*(1+Plan!$C$18/12)-(Plan!$D$18+IF(Plan!$E$18=$L10,Plan!$B$5+IF(AND(N(Plan!$B$9)>0,N(B9)<=0),Plan!$D$9,0)+IF(AND(N(Plan!$B$10)>0,N(C9)<=0),Plan!$D$10,0)+IF(AND(N(Plan!$B$11)>0,N(D9)<=0),Plan!$D$11,0)+IF(AND(N(Plan!$B$12)>0,N(E9)<=0),Plan!$D$12,0)+IF(AND(N(Plan!$B$13)>0,N(F9)<=0),Plan!$D$13,0)+IF(AND(N(Plan!$B$14)>0,N(G9)<=0),Plan!$D$14,0)+IF(AND(N(Plan!$B$15)>0,N(H9)<=0),Plan!$D$15,0)+IF(AND(N(Plan!$B$16)>0,N(I9)<=0),Plan!$D$16,0)+IF(AND(N(Plan!$B$17)>0,N(J9)<=0),Plan!$D$17,0)+IF(AND(N(Plan!$B$18)>0,N(K9)<=0),Plan!$D$18,0),0)))) | L10: =MIN(IF(N(B9)>0,Plan!$E$9,999),IF(N(C9)>0,Plan!$E$10,999),IF(N(D9)>0,Plan!$E$11,999),IF(N(E9)>0,Plan!$E$12,999),IF(N(F9)>0,Plan!$E$13,999),IF(N(G9)>0,Plan!$E$14,999),IF(N(H9)>0,Plan!$E$15,999),IF(N(I9)>0,Plan!$E$16,999),IF(N(J9)>0,Plan!$E$17,999),IF(N(K9)>0,Plan!$E$18,999)) | M10: =IF(N(B9)<=0,0,MIN(B9*(1+Plan!$C$9/12),Plan!$D$9+IF(Plan!$E$9=$L10,Plan!$B$5+IF(AND(N(Plan!$B$9)>0,N(B9)<=0),Plan!$D$9,0)+IF(AND(N(Plan!$B$10)>0,N(C9)<=0),Plan!$D$10,0)+IF(AND(N(Plan!$B$11)>0,N(D9)<=0),Plan!$D$11,0)+IF(AND(N(Plan!$B$12)>0,N(E9)<=0),Plan!$D$12,0)+IF(AND(N(Plan!$B$13)>0,N(F9)<=0),Plan!$D$13,0)+IF(AND(N(Plan!$B$14)>0,N(G9)<=0),Plan!$D$14,0)+IF(AND(N(Plan!$B$15)>0,N(H9)<=0),Plan!$D$15,0)+IF(AND(N(Plan!$B$16)>0,N(I9)<=0),Plan!$D$16,0)+IF(AND(N(Plan!$B$17)>0,N(J9)<=0),Plan!$D$17,0)+IF(AND(N(Plan!$B$18)>0,N(K9)<=0),Plan!$D$18,0),0)))+IF(N(C9)<=0,0,MIN(C9*(1+Plan!$C$10/12),Plan!$D$10+IF(Plan!$E$10=$L10,Plan!$B$5+IF(AND(N(Plan!$B$9)>0,N(B9)<=0),Plan!$D$9,0)+IF(AND(N(Plan!$B$10)>0,N(C9)<=0),Plan!$D$10,0)+IF(AND(N(Plan!$B$11)>0,N(D9)<=0),Plan!$D$11,0)+IF(AND(N(Plan!$B$12)>0,N(E9)<=0),Plan!$D$12,0)+IF(AND(N(Plan!$B$13)>0,N(F9)<=0),Plan!$D$13,0)+IF(AND(N(Plan!$B$14)>0,N(G9)<=0),Plan!$D$14,0)+IF(AND(N(Plan!$B$15)>0,N(H9)<=0),Plan!$D$15,0)+IF(AND(N(Plan!$B$16)>0,N(I9)<=0),Plan!$D$16,0)+IF(AND(N(Plan!$B$17)>0,N(J9)<=0),Plan!$D$17,0)+IF(AND(N(Plan!$B$18)>0,N(K9)<=0),Plan!$D$18,0),0)))+IF(N(D9)<=0,0,MIN(D9*(1+Plan!$C$11/12),Plan!$D$11+IF(Plan!$E$11=$L10,Plan!$B$5+IF(AND(N(Plan!$B$9)>0,N(B9)<=0),Plan!$D$9,0)+IF(AND(N(Plan!$B$10)>0,N(C9)<=0),Plan!$D$10,0)+IF(AND(N(Plan!$B$11)>0,N(D9)<=0),Plan!$D$11,0)+IF(AND(N(Plan!$B$12)>0,N(E9)<=0),Plan!$D$12,0)+IF(AND(N(Plan!$B$13)>0,N(F9)<=0),Plan!$D$13,0)+IF(AND(N(Plan!$B$14)>0,N(G9)<=0),Plan!$D$14,0)+IF(AND(N(Plan!$B$15)>0,N(H9)<=0),Plan!$D$15,0)+IF(AND(N(Plan!$B$16)>0,N(I9)<=0),Plan!$D$16,0)+IF(AND(N(Plan!$B$17)>0,N(J9)<=0),Plan!$D$17,0)+IF(AND(N(Plan!$B$18)>0,N(K9)<=0),Plan!$D$18,0),0)))+IF(N(E9)<=0,0,MIN(E9*(1+Plan!$C$12/12),Plan!$D$12+IF(Plan!$E$12=$L10,Plan!$B$5+IF(AND(N(Plan!$B$9)>0,N(B9)<=0),Plan!$D$9,0)+IF(AND(N(Plan!$B$10)>0,N(C9)<=0),Plan!$D$10,0)+IF(AND(N(Plan!$B$11)>0,N(D9)<=0),Plan!$D$11,0)+IF(AND(N(Plan!$B$12)>0,N(E9)<=0),Plan!$D$12,0)+IF(AND(N(Plan!$B$13)>0,N(F9)<=0),Plan!$D$13,0)+IF(AND(N(Plan!$B$14)>0,N(G9)<=0),Plan!$D$14,0)+IF(AND(N(Plan!$B$15)>0,N(H9)<=0),Plan!$D$15,0)+IF(AND(N(Plan!$B$16)>0,N(I9)<=0),Plan!$D$16,0)+IF(AND(N(Plan!$B$17)>0,N(J9)<=0),Plan!$D$17,0)+IF(AND(N(Plan!$B$18)>0,N(K9)<=0),Plan!$D$18,0),0)))+IF(N(F9)<=0,0,MIN(F9*(1+Plan!$C$13/12),Plan!$D$13+IF(Plan!$E$13=$L10,Plan!$B$5+IF(AND(N(Plan!$B$9)>0,N(B9)<=0),Plan!$D$9,0)+IF(AND(N(Plan!$B$10)>0,N(C9)<=0),Plan!$D$10,0)+IF(AND(N(Plan!$B$11)>0,N(D9)<=0),Plan!$D$11,0)+IF(AND(N(Plan!$B$12)>0,N(E9)<=0),Plan!$D$12,0)+IF(AND(N(Plan!$B$13)>0,N(F9)<=0),Plan!$D$13,0)+IF(AND(N(Plan!$B$14)>0,N(G9)<=0),Plan!$D$14,0)+IF(AND(N(Plan!$B$15)>0,N(H9)<=0),Plan!$D$15,0)+IF(AND(N(Plan!$B$16)>0,N(I9)<=0),Plan!$D$16,0)+IF(AND(N(Plan!$B$17)>0,N(J9)<=0),Plan!$D$17,0)+IF(AND(N(Plan!$B$18)>0,N(K9)<=0),Plan!$D$18,0),0)))+IF(N(G9)<=0,0,MIN(G9*(1+Plan!$C$14/12),Plan!$D$14+IF(Plan!$E$14=$L10,Plan!$B$5+IF(AND(N(Plan!$B$9)>0,N(B9)<=0),Plan!$D$9,0)+IF(AND(N(Plan!$B$10)>0,N(C9)<=0),Plan!$D$10,0)+IF(AND(N(Plan!$B$11)>0,N(D9)<=0),Plan!$D$11,0)+IF(AND(N(Plan!$B$12)>0,N(E9)<=0),Plan!$D$12,0)+IF(AND(N(Plan!$B$13)>0,N(F9)<=0),Plan!$D$13,0)+IF(AND(N(Plan!$B$14)>0,N(G9)<=0),Plan!$D$14,0)+IF(AND(N(Plan!$B$15)>0,N(H9)<=0),Plan!$D$15,0)+IF(AND(N(Plan!$B$16)>0,N(I9)<=0),Plan!$D$16,0)+IF(AND(N(Plan!$B$17)>0,N(J9)<=0),Plan!$D$17,0)+IF(AND(N(Plan!$B$18)>0,N(K9)<=0),Plan!$D$18,0),0)))+IF(N(H9)<=0,0,MIN(H9*(1+Plan!$C$15/12),Plan!$D$15+IF(Plan!$E$15=$L10,Plan!$B$5+IF(AND(N(Plan!$B$9)>0,N(B9)<=0),Plan!$D$9,0)+IF(AND(N(Plan!$B$10)>0,N(C9)<=0),Plan!$D$10,0)+IF(AND(N(Plan!$B$11)>0,N(D9)<=0),Plan!$D$11,0)+IF(AND(N(Plan!$B$12)>0,N(E9)<=0),Plan!$D$12,0)+IF(AND(N(Plan!$B$13)>0,N(F9)<=0),Plan!$D$13,0)+IF(AND(N(Plan!$B$14)>0,N(G9)<=0),Plan!$D$14,0)+IF(AND(N(Plan!$B$15)>0,N(H9)<=0),Plan!$D$15,0)+IF(AND(N(Plan!$B$16)>0,N(I9)<=0),Plan!$D$16,0)+IF(AND(N(Plan!$B$17)>0,N(J9)<=0),Plan!$D$17,0)+IF(AND(N(Plan!$B$18)>0,N(K9)<=0),Plan!$D$18,0),0)))+IF(N(I9)<=0,0,MIN(I9*(1+Plan!$C$16/12),Plan!$D$16+IF(Plan!$E$16=$L10,Plan!$B$5+IF(AND(N(Plan!$B$9)>0,N(B9)<=0),Plan!$D$9,0)+IF(AND(N(Plan!$B$10)>0,N(C9)<=0),Plan!$D$10,0)+IF(AND(N(Plan!$B$11)>0,N(D9)<=0),Plan!$D$11,0)+IF(AND(N(Plan!$B$12)>0,N(E9)<=0),Plan!$D$12,0)+IF(AND(N(Plan!$B$13)>0,N(F9)<=0),Plan!$D$13,0)+IF(AND(N(Plan!$B$14)>0,N(G9)<=0),Plan!$D$14,0)+IF(AND(N(Plan!$B$15)>0,N(H9)<=0),Plan!$D$15,0)+IF(AND(N(Plan!$B$16)>0,N(I9)<=0),Plan!$D$16,0)+IF(AND(N(Plan!$B$17)>0,N(J9)<=0),Plan!$D$17,0)+IF(AND(N(Plan!$B$18)>0,N(K9)<=0),Plan!$D$18,0),0)))+IF(N(J9)<=0,0,MIN(J9*(1+Plan!$C$17/12),Plan!$D$17+IF(Plan!$E$17=$L10,Plan!$B$5+IF(AND(N(Plan!$B$9)>0,N(B9)<=0),Plan!$D$9,0)+IF(AND(N(Plan!$B$10)>0,N(C9)<=0),Plan!$D$10,0)+IF(AND(N(Plan!$B$11)>0,N(D9)<=0),Plan!$D$11,0)+IF(AND(N(Plan!$B$12)>0,N(E9)<=0),Plan!$D$12,0)+IF(AND(N(Plan!$B$13)>0,N(F9)<=0),Plan!$D$13,0)+IF(AND(N(Plan!$B$14)>0,N(G9)<=0),Plan!$D$14,0)+IF(AND(N(Plan!$B$15)>0,N(H9)<=0),Plan!$D$15,0)+IF(AND(N(Plan!$B$16)>0,N(I9)<=0),Plan!$D$16,0)+IF(AND(N(Plan!$B$17)>0,N(J9)<=0),Plan!$D$17,0)+IF(AND(N(Plan!$B$18)>0,N(K9)<=0),Plan!$D$18,0),0)))+IF(N(K9)<=0,0,MIN(K9*(1+Plan!$C$18/12),Plan!$D$18+IF(Plan!$E$18=$L10,Plan!$B$5+IF(AND(N(Plan!$B$9)>0,N(B9)<=0),Plan!$D$9,0)+IF(AND(N(Plan!$B$10)>0,N(C9)<=0),Plan!$D$10,0)+IF(AND(N(Plan!$B$11)>0,N(D9)<=0),Plan!$D$11,0)+IF(AND(N(Plan!$B$12)>0,N(E9)<=0),Plan!$D$12,0)+IF(AND(N(Plan!$B$13)>0,N(F9)<=0),Plan!$D$13,0)+IF(AND(N(Plan!$B$14)>0,N(G9)<=0),Plan!$D$14,0)+IF(AND(N(Plan!$B$15)>0,N(H9)<=0),Plan!$D$15,0)+IF(AND(N(Plan!$B$16)>0,N(I9)<=0),Plan!$D$16,0)+IF(AND(N(Plan!$B$17)>0,N(J9)<=0),Plan!$D$17,0)+IF(AND(N(Plan!$B$18)>0,N(K9)<=0),Plan!$D$18,0),0)))
A11: 7 | B11: =IF(N(B10)<=0,0,MAX(0,B10*(1+Plan!$C$9/12)-(Plan!$D$9+IF(Plan!$E$9=$L11,Plan!$B$5+IF(AND(N(Plan!$B$9)>0,N(B10)<=0),Plan!$D$9,0)+IF(AND(N(Plan!$B$10)>0,N(C10)<=0),Plan!$D$10,0)+IF(AND(N(Plan!$B$11)>0,N(D10)<=0),Plan!$D$11,0)+IF(AND(N(Plan!$B$12)>0,N(E10)<=0),Plan!$D$12,0)+IF(AND(N(Plan!$B$13)>0,N(F10)<=0),Plan!$D$13,0)+IF(AND(N(Plan!$B$14)>0,N(G10)<=0),Plan!$D$14,0)+IF(AND(N(Plan!$B$15)>0,N(H10)<=0),Plan!$D$15,0)+IF(AND(N(Plan!$B$16)>0,N(I10)<=0),Plan!$D$16,0)+IF(AND(N(Plan!$B$17)>0,N(J10)<=0),Plan!$D$17,0)+IF(AND(N(Plan!$B$18)>0,N(K10)<=0),Plan!$D$18,0),0)))) | C11: =IF(N(C10)<=0,0,MAX(0,C10*(1+Plan!$C$10/12)-(Plan!$D$10+IF(Plan!$E$10=$L11,Plan!$B$5+IF(AND(N(Plan!$B$9)>0,N(B10)<=0),Plan!$D$9,0)+IF(AND(N(Plan!$B$10)>0,N(C10)<=0),Plan!$D$10,0)+IF(AND(N(Plan!$B$11)>0,N(D10)<=0),Plan!$D$11,0)+IF(AND(N(Plan!$B$12)>0,N(E10)<=0),Plan!$D$12,0)+IF(AND(N(Plan!$B$13)>0,N(F10)<=0),Plan!$D$13,0)+IF(AND(N(Plan!$B$14)>0,N(G10)<=0),Plan!$D$14,0)+IF(AND(N(Plan!$B$15)>0,N(H10)<=0),Plan!$D$15,0)+IF(AND(N(Plan!$B$16)>0,N(I10)<=0),Plan!$D$16,0)+IF(AND(N(Plan!$B$17)>0,N(J10)<=0),Plan!$D$17,0)+IF(AND(N(Plan!$B$18)>0,N(K10)<=0),Plan!$D$18,0),0)))) | D11: =IF(N(D10)<=0,0,MAX(0,D10*(1+Plan!$C$11/12)-(Plan!$D$11+IF(Plan!$E$11=$L11,Plan!$B$5+IF(AND(N(Plan!$B$9)>0,N(B10)<=0),Plan!$D$9,0)+IF(AND(N(Plan!$B$10)>0,N(C10)<=0),Plan!$D$10,0)+IF(AND(N(Plan!$B$11)>0,N(D10)<=0),Plan!$D$11,0)+IF(AND(N(Plan!$B$12)>0,N(E10)<=0),Plan!$D$12,0)+IF(AND(N(Plan!$B$13)>0,N(F10)<=0),Plan!$D$13,0)+IF(AND(N(Plan!$B$14)>0,N(G10)<=0),Plan!$D$14,0)+IF(AND(N(Plan!$B$15)>0,N(H10)<=0),Plan!$D$15,0)+IF(AND(N(Plan!$B$16)>0,N(I10)<=0),Plan!$D$16,0)+IF(AND(N(Plan!$B$17)>0,N(J10)<=0),Plan!$D$17,0)+IF(AND(N(Plan!$B$18)>0,N(K10)<=0),Plan!$D$18,0),0)))) | E11: =IF(N(E10)<=0,0,MAX(0,E10*(1+Plan!$C$12/12)-(Plan!$D$12+IF(Plan!$E$12=$L11,Plan!$B$5+IF(AND(N(Plan!$B$9)>0,N(B10)<=0),Plan!$D$9,0)+IF(AND(N(Plan!$B$10)>0,N(C10)<=0),Plan!$D$10,0)+IF(AND(N(Plan!$B$11)>0,N(D10)<=0),Plan!$D$11,0)+IF(AND(N(Plan!$B$12)>0,N(E10)<=0),Plan!$D$12,0)+IF(AND(N(Plan!$B$13)>0,N(F10)<=0),Plan!$D$13,0)+IF(AND(N(Plan!$B$14)>0,N(G10)<=0),Plan!$D$14,0)+IF(AND(N(Plan!$B$15)>0,N(H10)<=0),Plan!$D$15,0)+IF(AND(N(Plan!$B$16)>0,N(I10)<=0),Plan!$D$16,0)+IF(AND(N(Plan!$B$17)>0,N(J10)<=0),Plan!$D$17,0)+IF(AND(N(Plan!$B$18)>0,N(K10)<=0),Plan!$D$18,0),0)))) | F11: =IF(N(F10)<=0,0,MAX(0,F10*(1+Plan!$C$13/12)-(Plan!$D$13+IF(Plan!$E$13=$L11,Plan!$B$5+IF(AND(N(Plan!$B$9)>0,N(B10)<=0),Plan!$D$9,0)+IF(AND(N(Plan!$B$10)>0,N(C10)<=0),Plan!$D$10,0)+IF(AND(N(Plan!$B$11)>0,N(D10)<=0),Plan!$D$11,0)+IF(AND(N(Plan!$B$12)>0,N(E10)<=0),Plan!$D$12,0)+IF(AND(N(Plan!$B$13)>0,N(F10)<=0),Plan!$D$13,0)+IF(AND(N(Plan!$B$14)>0,N(G10)<=0),Plan!$D$14,0)+IF(AND(N(Plan!$B$15)>0,N(H10)<=0),Plan!$D$15,0)+IF(AND(N(Plan!$B$16)>0,N(I10)<=0),Plan!$D$16,0)+IF(AND(N(Plan!$B$17)>0,N(J10)<=0),Plan!$D$17,0)+IF(AND(N(Plan!$B$18)>0,N(K10)<=0),Plan!$D$18,0),0)))) | G11: =IF(N(G10)<=0,0,MAX(0,G10*(1+Plan!$C$14/12)-(Plan!$D$14+IF(Plan!$E$14=$L11,Plan!$B$5+IF(AND(N(Plan!$B$9)>0,N(B10)<=0),Plan!$D$9,0)+IF(AND(N(Plan!$B$10)>0,N(C10)<=0),Plan!$D$10,0)+IF(AND(N(Plan!$B$11)>0,N(D10)<=0),Plan!$D$11,0)+IF(AND(N(Plan!$B$12)>0,N(E10)<=0),Plan!$D$12,0)+IF(AND(N(Plan!$B$13)>0,N(F10)<=0),Plan!$D$13,0)+IF(AND(N(Plan!$B$14)>0,N(G10)<=0),Plan!$D$14,0)+IF(AND(N(Plan!$B$15)>0,N(H10)<=0),Plan!$D$15,0)+IF(AND(N(Plan!$B$16)>0,N(I10)<=0),Plan!$D$16,0)+IF(AND(N(Plan!$B$17)>0,N(J10)<=0),Plan!$D$17,0)+IF(AND(N(Plan!$B$18)>0,N(K10)<=0),Plan!$D$18,0),0)))) | H11: =IF(N(H10)<=0,0,MAX(0,H10*(1+Plan!$C$15/12)-(Plan!$D$15+IF(Plan!$E$15=$L11,Plan!$B$5+IF(AND(N(Plan!$B$9)>0,N(B10)<=0),Plan!$D$9,0)+IF(AND(N(Plan!$B$10)>0,N(C10)<=0),Plan!$D$10,0)+IF(AND(N(Plan!$B$11)>0,N(D10)<=0),Plan!$D$11,0)+IF(AND(N(Plan!$B$12)>0,N(E10)<=0),Plan!$D$12,0)+IF(AND(N(Plan!$B$13)>0,N(F10)<=0),Plan!$D$13,0)+IF(AND(N(Plan!$B$14)>0,N(G10)<=0),Plan!$D$14,0)+IF(AND(N(Plan!$B$15)>0,N(H10)<=0),Plan!$D$15,0)+IF(AND(N(Plan!$B$16)>0,N(I10)<=0),Plan!$D$16,0)+IF(AND(N(Plan!$B$17)>0,N(J10)<=0),Plan!$D$17,0)+IF(AND(N(Plan!$B$18)>0,N(K10)<=0),Plan!$D$18,0),0)))) | I11: =IF(N(I10)<=0,0,MAX(0,I10*(1+Plan!$C$16/12)-(Plan!$D$16+IF(Plan!$E$16=$L11,Plan!$B$5+IF(AND(N(Plan!$B$9)>0,N(B10)<=0),Plan!$D$9,0)+IF(AND(N(Plan!$B$10)>0,N(C10)<=0),Plan!$D$10,0)+IF(AND(N(Plan!$B$11)>0,N(D10)<=0),Plan!$D$11,0)+IF(AND(N(Plan!$B$12)>0,N(E10)<=0),Plan!$D$12,0)+IF(AND(N(Plan!$B$13)>0,N(F10)<=0),Plan!$D$13,0)+IF(AND(N(Plan!$B$14)>0,N(G10)<=0),Plan!$D$14,0)+IF(AND(N(Plan!$B$15)>0,N(H10)<=0),Plan!$D$15,0)+IF(AND(N(Plan!$B$16)>0,N(I10)<=0),Plan!$D$16,0)+IF(AND(N(Plan!$B$17)>0,N(J10)<=0),Plan!$D$17,0)+IF(AND(N(Plan!$B$18)>0,N(K10)<=0),Plan!$D$18,0),0)))) | J11: =IF(N(J10)<=0,0,MAX(0,J10*(1+Plan!$C$17/12)-(Plan!$D$17+IF(Plan!$E$17=$L11,Plan!$B$5+IF(AND(N(Plan!$B$9)>0,N(B10)<=0),Plan!$D$9,0)+IF(AND(N(Plan!$B$10)>0,N(C10)<=0),Plan!$D$10,0)+IF(AND(N(Plan!$B$11)>0,N(D10)<=0),Plan!$D$11,0)+IF(AND(N(Plan!$B$12)>0,N(E10)<=0),Plan!$D$12,0)+IF(AND(N(Plan!$B$13)>0,N(F10)<=0),Plan!$D$13,0)+IF(AND(N(Plan!$B$14)>0,N(G10)<=0),Plan!$D$14,0)+IF(AND(N(Plan!$B$15)>0,N(H10)<=0),Plan!$D$15,0)+IF(AND(N(Plan!$B$16)>0,N(I10)<=0),Plan!$D$16,0)+IF(AND(N(Plan!$B$17)>0,N(J10)<=0),Plan!$D$17,0)+IF(AND(N(Plan!$B$18)>0,N(K10)<=0),Plan!$D$18,0),0)))) | K11: =IF(N(K10)<=0,0,MAX(0,K10*(1+Plan!$C$18/12)-(Plan!$D$18+IF(Plan!$E$18=$L11,Plan!$B$5+IF(AND(N(Plan!$B$9)>0,N(B10)<=0),Plan!$D$9,0)+IF(AND(N(Plan!$B$10)>0,N(C10)<=0),Plan!$D$10,0)+IF(AND(N(Plan!$B$11)>0,N(D10)<=0),Plan!$D$11,0)+IF(AND(N(Plan!$B$12)>0,N(E10)<=0),Plan!$D$12,0)+IF(AND(N(Plan!$B$13)>0,N(F10)<=0),Plan!$D$13,0)+IF(AND(N(Plan!$B$14)>0,N(G10)<=0),Plan!$D$14,0)+IF(AND(N(Plan!$B$15)>0,N(H10)<=0),Plan!$D$15,0)+IF(AND(N(Plan!$B$16)>0,N(I10)<=0),Plan!$D$16,0)+IF(AND(N(Plan!$B$17)>0,N(J10)<=0),Plan!$D$17,0)+IF(AND(N(Plan!$B$18)>0,N(K10)<=0),Plan!$D$18,0),0)))) | L11: =MIN(IF(N(B10)>0,Plan!$E$9,999),IF(N(C10)>0,Plan!$E$10,999),IF(N(D10)>0,Plan!$E$11,999),IF(N(E10)>0,Plan!$E$12,999),IF(N(F10)>0,Plan!$E$13,999),IF(N(G10)>0,Plan!$E$14,999),IF(N(H10)>0,Plan!$E$15,999),IF(N(I10)>0,Plan!$E$16,999),IF(N(J10)>0,Plan!$E$17,999),IF(N(K10)>0,Plan!$E$18,999)) | M11: =IF(N(B10)<=0,0,MIN(B10*(1+Plan!$C$9/12),Plan!$D$9+IF(Plan!$E$9=$L11,Plan!$B$5+IF(AND(N(Plan!$B$9)>0,N(B10)<=0),Plan!$D$9,0)+IF(AND(N(Plan!$B$10)>0,N(C10)<=0),Plan!$D$10,0)+IF(AND(N(Plan!$B$11)>0,N(D10)<=0),Plan!$D$11,0)+IF(AND(N(Plan!$B$12)>0,N(E10)<=0),Plan!$D$12,0)+IF(AND(N(Plan!$B$13)>0,N(F10)<=0),Plan!$D$13,0)+IF(AND(N(Plan!$B$14)>0,N(G10)<=0),Plan!$D$14,0)+IF(AND(N(Plan!$B$15)>0,N(H10)<=0),Plan!$D$15,0)+IF(AND(N(Plan!$B$16)>0,N(I10)<=0),Plan!$D$16,0)+IF(AND(N(Plan!$B$17)>0,N(J10)<=0),Plan!$D$17,0)+IF(AND(N(Plan!$B$18)>0,N(K10)<=0),Plan!$D$18,0),0)))+IF(N(C10)<=0,0,MIN(C10*(1+Plan!$C$10/12),Plan!$D$10+IF(Plan!$E$10=$L11,Plan!$B$5+IF(AND(N(Plan!$B$9)>0,N(B10)<=0),Plan!$D$9,0)+IF(AND(N(Plan!$B$10)>0,N(C10)<=0),Plan!$D$10,0)+IF(AND(N(Plan!$B$11)>0,N(D10)<=0),Plan!$D$11,0)+IF(AND(N(Plan!$B$12)>0,N(E10)<=0),Plan!$D$12,0)+IF(AND(N(Plan!$B$13)>0,N(F10)<=0),Plan!$D$13,0)+IF(AND(N(Plan!$B$14)>0,N(G10)<=0),Plan!$D$14,0)+IF(AND(N(Plan!$B$15)>0,N(H10)<=0),Plan!$D$15,0)+IF(AND(N(Plan!$B$16)>0,N(I10)<=0),Plan!$D$16,0)+IF(AND(N(Plan!$B$17)>0,N(J10)<=0),Plan!$D$17,0)+IF(AND(N(Plan!$B$18)>0,N(K10)<=0),Plan!$D$18,0),0)))+IF(N(D10)<=0,0,MIN(D10*(1+Plan!$C$11/12),Plan!$D$11+IF(Plan!$E$11=$L11,Plan!$B$5+IF(AND(N(Plan!$B$9)>0,N(B10)<=0),Plan!$D$9,0)+IF(AND(N(Plan!$B$10)>0,N(C10)<=0),Plan!$D$10,0)+IF(AND(N(Plan!$B$11)>0,N(D10)<=0),Plan!$D$11,0)+IF(AND(N(Plan!$B$12)>0,N(E10)<=0),Plan!$D$12,0)+IF(AND(N(Plan!$B$13)>0,N(F10)<=0),Plan!$D$13,0)+IF(AND(N(Plan!$B$14)>0,N(G10)<=0),Plan!$D$14,0)+IF(AND(N(Plan!$B$15)>0,N(H10)<=0),Plan!$D$15,0)+IF(AND(N(Plan!$B$16)>0,N(I10)<=0),Plan!$D$16,0)+IF(AND(N(Plan!$B$17)>0,N(J10)<=0),Plan!$D$17,0)+IF(AND(N(Plan!$B$18)>0,N(K10)<=0),Plan!$D$18,0),0)))+IF(N(E10)<=0,0,MIN(E10*(1+Plan!$C$12/12),Plan!$D$12+IF(Plan!$E$12=$L11,Plan!$B$5+IF(AND(N(Plan!$B$9)>0,N(B10)<=0),Plan!$D$9,0)+IF(AND(N(Plan!$B$10)>0,N(C10)<=0),Plan!$D$10,0)+IF(AND(N(Plan!$B$11)>0,N(D10)<=0),Plan!$D$11,0)+IF(AND(N(Plan!$B$12)>0,N(E10)<=0),Plan!$D$12,0)+IF(AND(N(Plan!$B$13)>0,N(F10)<=0),Plan!$D$13,0)+IF(AND(N(Plan!$B$14)>0,N(G10)<=0),Plan!$D$14,0)+IF(AND(N(Plan!$B$15)>0,N(H10)<=0),Plan!$D$15,0)+IF(AND(N(Plan!$B$16)>0,N(I10)<=0),Plan!$D$16,0)+IF(AND(N(Plan!$B$17)>0,N(J10)<=0),Plan!$D$17,0)+IF(AND(N(Plan!$B$18)>0,N(K10)<=0),Plan!$D$18,0),0)))+IF(N(F10)<=0,0,MIN(F10*(1+Plan!$C$13/12),Plan!$D$13+IF(Plan!$E$13=$L11,Plan!$B$5+IF(AND(N(Plan!$B$9)>0,N(B10)<=0),Plan!$D$9,0)+IF(AND(N(Plan!$B$10)>0,N(C10)<=0),Plan!$D$10,0)+IF(AND(N(Plan!$B$11)>0,N(D10)<=0),Plan!$D$11,0)+IF(AND(N(Plan!$B$12)>0,N(E10)<=0),Plan!$D$12,0)+IF(AND(N(Plan!$B$13)>0,N(F10)<=0),Plan!$D$13,0)+IF(AND(N(Plan!$B$14)>0,N(G10)<=0),Plan!$D$14,0)+IF(AND(N(Plan!$B$15)>0,N(H10)<=0),Plan!$D$15,0)+IF(AND(N(Plan!$B$16)>0,N(I10)<=0),Plan!$D$16,0)+IF(AND(N(Plan!$B$17)>0,N(J10)<=0),Plan!$D$17,0)+IF(AND(N(Plan!$B$18)>0,N(K10)<=0),Plan!$D$18,0),0)))+IF(N(G10)<=0,0,MIN(G10*(1+Plan!$C$14/12),Plan!$D$14+IF(Plan!$E$14=$L11,Plan!$B$5+IF(AND(N(Plan!$B$9)>0,N(B10)<=0),Plan!$D$9,0)+IF(AND(N(Plan!$B$10)>0,N(C10)<=0),Plan!$D$10,0)+IF(AND(N(Plan!$B$11)>0,N(D10)<=0),Plan!$D$11,0)+IF(AND(N(Plan!$B$12)>0,N(E10)<=0),Plan!$D$12,0)+IF(AND(N(Plan!$B$13)>0,N(F10)<=0),Plan!$D$13,0)+IF(AND(N(Plan!$B$14)>0,N(G10)<=0),Plan!$D$14,0)+IF(AND(N(Plan!$B$15)>0,N(H10)<=0),Plan!$D$15,0)+IF(AND(N(Plan!$B$16)>0,N(I10)<=0),Plan!$D$16,0)+IF(AND(N(Plan!$B$17)>0,N(J10)<=0),Plan!$D$17,0)+IF(AND(N(Plan!$B$18)>0,N(K10)<=0),Plan!$D$18,0),0)))+IF(N(H10)<=0,0,MIN(H10*(1+Plan!$C$15/12),Plan!$D$15+IF(Plan!$E$15=$L11,Plan!$B$5+IF(AND(N(Plan!$B$9)>0,N(B10)<=0),Plan!$D$9,0)+IF(AND(N(Plan!$B$10)>0,N(C10)<=0),Plan!$D$10,0)+IF(AND(N(Plan!$B$11)>0,N(D10)<=0),Plan!$D$11,0)+IF(AND(N(Plan!$B$12)>0,N(E10)<=0),Plan!$D$12,0)+IF(AND(N(Plan!$B$13)>0,N(F10)<=0),Plan!$D$13,0)+IF(AND(N(Plan!$B$14)>0,N(G10)<=0),Plan!$D$14,0)+IF(AND(N(Plan!$B$15)>0,N(H10)<=0),Plan!$D$15,0)+IF(AND(N(Plan!$B$16)>0,N(I10)<=0),Plan!$D$16,0)+IF(AND(N(Plan!$B$17)>0,N(J10)<=0),Plan!$D$17,0)+IF(AND(N(Plan!$B$18)>0,N(K10)<=0),Plan!$D$18,0),0)))+IF(N(I10)<=0,0,MIN(I10*(1+Plan!$C$16/12),Plan!$D$16+IF(Plan!$E$16=$L11,Plan!$B$5+IF(AND(N(Plan!$B$9)>0,N(B10)<=0),Plan!$D$9,0)+IF(AND(N(Plan!$B$10)>0,N(C10)<=0),Plan!$D$10,0)+IF(AND(N(Plan!$B$11)>0,N(D10)<=0),Plan!$D$11,0)+IF(AND(N(Plan!$B$12)>0,N(E10)<=0),Plan!$D$12,0)+IF(AND(N(Plan!$B$13)>0,N(F10)<=0),Plan!$D$13,0)+IF(AND(N(Plan!$B$14)>0,N(G10)<=0),Plan!$D$14,0)+IF(AND(N(Plan!$B$15)>0,N(H10)<=0),Plan!$D$15,0)+IF(AND(N(Plan!$B$16)>0,N(I10)<=0),Plan!$D$16,0)+IF(AND(N(Plan!$B$17)>0,N(J10)<=0),Plan!$D$17,0)+IF(AND(N(Plan!$B$18)>0,N(K10)<=0),Plan!$D$18,0),0)))+IF(N(J10)<=0,0,MIN(J10*(1+Plan!$C$17/12),Plan!$D$17+IF(Plan!$E$17=$L11,Plan!$B$5+IF(AND(N(Plan!$B$9)>0,N(B10)<=0),Plan!$D$9,0)+IF(AND(N(Plan!$B$10)>0,N(C10)<=0),Plan!$D$10,0)+IF(AND(N(Plan!$B$11)>0,N(D10)<=0),Plan!$D$11,0)+IF(AND(N(Plan!$B$12)>0,N(E10)<=0),Plan!$D$12,0)+IF(AND(N(Plan!$B$13)>0,N(F10)<=0),Plan!$D$13,0)+IF(AND(N(Plan!$B$14)>0,N(G10)<=0),Plan!$D$14,0)+IF(AND(N(Plan!$B$15)>0,N(H10)<=0),Plan!$D$15,0)+IF(AND(N(Plan!$B$16)>0,N(I10)<=0),Plan!$D$16,0)+IF(AND(N(Plan!$B$17)>0,N(J10)<=0),Plan!$D$17,0)+IF(AND(N(Plan!$B$18)>0,N(K10)<=0),Plan!$D$18,0),0)))+IF(N(K10)<=0,0,MIN(K10*(1+Plan!$C$18/12),Plan!$D$18+IF(Plan!$E$18=$L11,Plan!$B$5+IF(AND(N(Plan!$B$9)>0,N(B10)<=0),Plan!$D$9,0)+IF(AND(N(Plan!$B$10)>0,N(C10)<=0),Plan!$D$10,0)+IF(AND(N(Plan!$B$11)>0,N(D10)<=0),Plan!$D$11,0)+IF(AND(N(Plan!$B$12)>0,N(E10)<=0),Plan!$D$12,0)+IF(AND(N(Plan!$B$13)>0,N(F10)<=0),Plan!$D$13,0)+IF(AND(N(Plan!$B$14)>0,N(G10)<=0),Plan!$D$14,0)+IF(AND(N(Plan!$B$15)>0,N(H10)<=0),Plan!$D$15,0)+IF(AND(N(Plan!$B$16)>0,N(I10)<=0),Plan!$D$16,0)+IF(AND(N(Plan!$B$17)>0,N(J10)<=0),Plan!$D$17,0)+IF(AND(N(Plan!$B$18)>0,N(K10)<=0),Plan!$D$18,0),0)))
A12: 8 | B12: =IF(N(B11)<=0,0,MAX(0,B11*(1+Plan!$C$9/12)-(Plan!$D$9+IF(Plan!$E$9=$L12,Plan!$B$5+IF(AND(N(Plan!$B$9)>0,N(B11)<=0),Plan!$D$9,0)+IF(AND(N(Plan!$B$10)>0,N(C11)<=0),Plan!$D$10,0)+IF(AND(N(Plan!$B$11)>0,N(D11)<=0),Plan!$D$11,0)+IF(AND(N(Plan!$B$12)>0,N(E11)<=0),Plan!$D$12,0)+IF(AND(N(Plan!$B$13)>0,N(F11)<=0),Plan!$D$13,0)+IF(AND(N(Plan!$B$14)>0,N(G11)<=0),Plan!$D$14,0)+IF(AND(N(Plan!$B$15)>0,N(H11)<=0),Plan!$D$15,0)+IF(AND(N(Plan!$B$16)>0,N(I11)<=0),Plan!$D$16,0)+IF(AND(N(Plan!$B$17)>0,N(J11)<=0),Plan!$D$17,0)+IF(AND(N(Plan!$B$18)>0,N(K11)<=0),Plan!$D$18,0),0)))) | C12: =IF(N(C11)<=0,0,MAX(0,C11*(1+Plan!$C$10/12)-(Plan!$D$10+IF(Plan!$E$10=$L12,Plan!$B$5+IF(AND(N(Plan!$B$9)>0,N(B11)<=0),Plan!$D$9,0)+IF(AND(N(Plan!$B$10)>0,N(C11)<=0),Plan!$D$10,0)+IF(AND(N(Plan!$B$11)>0,N(D11)<=0),Plan!$D$11,0)+IF(AND(N(Plan!$B$12)>0,N(E11)<=0),Plan!$D$12,0)+IF(AND(N(Plan!$B$13)>0,N(F11)<=0),Plan!$D$13,0)+IF(AND(N(Plan!$B$14)>0,N(G11)<=0),Plan!$D$14,0)+IF(AND(N(Plan!$B$15)>0,N(H11)<=0),Plan!$D$15,0)+IF(AND(N(Plan!$B$16)>0,N(I11)<=0),Plan!$D$16,0)+IF(AND(N(Plan!$B$17)>0,N(J11)<=0),Plan!$D$17,0)+IF(AND(N(Plan!$B$18)>0,N(K11)<=0),Plan!$D$18,0),0)))) | D12: =IF(N(D11)<=0,0,MAX(0,D11*(1+Plan!$C$11/12)-(Plan!$D$11+IF(Plan!$E$11=$L12,Plan!$B$5+IF(AND(N(Plan!$B$9)>0,N(B11)<=0),Plan!$D$9,0)+IF(AND(N(Plan!$B$10)>0,N(C11)<=0),Plan!$D$10,0)+IF(AND(N(Plan!$B$11)>0,N(D11)<=0),Plan!$D$11,0)+IF(AND(N(Plan!$B$12)>0,N(E11)<=0),Plan!$D$12,0)+IF(AND(N(Plan!$B$13)>0,N(F11)<=0),Plan!$D$13,0)+IF(AND(N(Plan!$B$14)>0,N(G11)<=0),Plan!$D$14,0)+IF(AND(N(Plan!$B$15)>0,N(H11)<=0),Plan!$D$15,0)+IF(AND(N(Plan!$B$16)>0,N(I11)<=0),Plan!$D$16,0)+IF(AND(N(Plan!$B$17)>0,N(J11)<=0),Plan!$D$17,0)+IF(AND(N(Plan!$B$18)>0,N(K11)<=0),Plan!$D$18,0),0)))) | E12: =IF(N(E11)<=0,0,MAX(0,E11*(1+Plan!$C$12/12)-(Plan!$D$12+IF(Plan!$E$12=$L12,Plan!$B$5+IF(AND(N(Plan!$B$9)>0,N(B11)<=0),Plan!$D$9,0)+IF(AND(N(Plan!$B$10)>0,N(C11)<=0),Plan!$D$10,0)+IF(AND(N(Plan!$B$11)>0,N(D11)<=0),Plan!$D$11,0)+IF(AND(N(Plan!$B$12)>0,N(E11)<=0),Plan!$D$12,0)+IF(AND(N(Plan!$B$13)>0,N(F11)<=0),Plan!$D$13,0)+IF(AND(N(Plan!$B$14)>0,N(G11)<=0),Plan!$D$14,0)+IF(AND(N(Plan!$B$15)>0,N(H11)<=0),Plan!$D$15,0)+IF(AND(N(Plan!$B$16)>0,N(I11)<=0),Plan!$D$16,0)+IF(AND(N(Plan!$B$17)>0,N(J11)<=0),Plan!$D$17,0)+IF(AND(N(Plan!$B$18)>0,N(K11)<=0),Plan!$D$18,0),0)))) | F12: =IF(N(F11)<=0,0,MAX(0,F11*(1+Plan!$C$13/12)-(Plan!$D$13+IF(Plan!$E$13=$L12,Plan!$B$5+IF(AND(N(Plan!$B$9)>0,N(B11)<=0),Plan!$D$9,0)+IF(AND(N(Plan!$B$10)>0,N(C11)<=0),Plan!$D$10,0)+IF(AND(N(Plan!$B$11)>0,N(D11)<=0),Plan!$D$11,0)+IF(AND(N(Plan!$B$12)>0,N(E11)<=0),Plan!$D$12,0)+IF(AND(N(Plan!$B$13)>0,N(F11)<=0),Plan!$D$13,0)+IF(AND(N(Plan!$B$14)>0,N(G11)<=0),Plan!$D$14,0)+IF(AND(N(Plan!$B$15)>0,N(H11)<=0),Plan!$D$15,0)+IF(AND(N(Plan!$B$16)>0,N(I11)<=0),Plan!$D$16,0)+IF(AND(N(Plan!$B$17)>0,N(J11)<=0),Plan!$D$17,0)+IF(AND(N(Plan!$B$18)>0,N(K11)<=0),Plan!$D$18,0),0)))) | G12: =IF(N(G11)<=0,0,MAX(0,G11*(1+Plan!$C$14/12)-(Plan!$D$14+IF(Plan!$E$14=$L12,Plan!$B$5+IF(AND(N(Plan!$B$9)>0,N(B11)<=0),Plan!$D$9,0)+IF(AND(N(Plan!$B$10)>0,N(C11)<=0),Plan!$D$10,0)+IF(AND(N(Plan!$B$11)>0,N(D11)<=0),Plan!$D$11,0)+IF(AND(N(Plan!$B$12)>0,N(E11)<=0),Plan!$D$12,0)+IF(AND(N(Plan!$B$13)>0,N(F11)<=0),Plan!$D$13,0)+IF(AND(N(Plan!$B$14)>0,N(G11)<=0),Plan!$D$14,0)+IF(AND(N(Plan!$B$15)>0,N(H11)<=0),Plan!$D$15,0)+IF(AND(N(Plan!$B$16)>0,N(I11)<=0),Plan!$D$16,0)+IF(AND(N(Plan!$B$17)>0,N(J11)<=0),Plan!$D$17,0)+IF(AND(N(Plan!$B$18)>0,N(K11)<=0),Plan!$D$18,0),0)))) | H12: =IF(N(H11)<=0,0,MAX(0,H11*(1+Plan!$C$15/12)-(Plan!$D$15+IF(Plan!$E$15=$L12,Plan!$B$5+IF(AND(N(Plan!$B$9)>0,N(B11)<=0),Plan!$D$9,0)+IF(AND(N(Plan!$B$10)>0,N(C11)<=0),Plan!$D$10,0)+IF(AND(N(Plan!$B$11)>0,N(D11)<=0),Plan!$D$11,0)+IF(AND(N(Plan!$B$12)>0,N(E11)<=0),Plan!$D$12,0)+IF(AND(N(Plan!$B$13)>0,N(F11)<=0),Plan!$D$13,0)+IF(AND(N(Plan!$B$14)>0,N(G11)<=0),Plan!$D$14,0)+IF(AND(N(Plan!$B$15)>0,N(H11)<=0),Plan!$D$15,0)+IF(AND(N(Plan!$B$16)>0,N(I11)<=0),Plan!$D$16,0)+IF(AND(N(Plan!$B$17)>0,N(J11)<=0),Plan!$D$17,0)+IF(AND(N(Plan!$B$18)>0,N(K11)<=0),Plan!$D$18,0),0)))) | I12: =IF(N(I11)<=0,0,MAX(0,I11*(1+Plan!$C$16/12)-(Plan!$D$16+IF(Plan!$E$16=$L12,Plan!$B$5+IF(AND(N(Plan!$B$9)>0,N(B11)<=0),Plan!$D$9,0)+IF(AND(N(Plan!$B$10)>0,N(C11)<=0),Plan!$D$10,0)+IF(AND(N(Plan!$B$11)>0,N(D11)<=0),Plan!$D$11,0)+IF(AND(N(Plan!$B$12)>0,N(E11)<=0),Plan!$D$12,0)+IF(AND(N(Plan!$B$13)>0,N(F11)<=0),Plan!$D$13,0)+IF(AND(N(Plan!$B$14)>0,N(G11)<=0),Plan!$D$14,0)+IF(AND(N(Plan!$B$15)>0,N(H11)<=0),Plan!$D$15,0)+IF(AND(N(Plan!$B$16)>0,N(I11)<=0),Plan!$D$16,0)+IF(AND(N(Plan!$B$17)>0,N(J11)<=0),Plan!$D$17,0)+IF(AND(N(Plan!$B$18)>0,N(K11)<=0),Plan!$D$18,0),0)))) | J12: =IF(N(J11)<=0,0,MAX(0,J11*(1+Plan!$C$17/12)-(Plan!$D$17+IF(Plan!$E$17=$L12,Plan!$B$5+IF(AND(N(Plan!$B$9)>0,N(B11)<=0),Plan!$D$9,0)+IF(AND(N(Plan!$B$10)>0,N(C11)<=0),Plan!$D$10,0)+IF(AND(N(Plan!$B$11)>0,N(D11)<=0),Plan!$D$11,0)+IF(AND(N(Plan!$B$12)>0,N(E11)<=0),Plan!$D$12,0)+IF(AND(N(Plan!$B$13)>0,N(F11)<=0),Plan!$D$13,0)+IF(AND(N(Plan!$B$14)>0,N(G11)<=0),Plan!$D$14,0)+IF(AND(N(Plan!$B$15)>0,N(H11)<=0),Plan!$D$15,0)+IF(AND(N(Plan!$B$16)>0,N(I11)<=0),Plan!$D$16,0)+IF(AND(N(Plan!$B$17)>0,N(J11)<=0),Plan!$D$17,0)+IF(AND(N(Plan!$B$18)>0,N(K11)<=0),Plan!$D$18,0),0)))) | K12: =IF(N(K11)<=0,0,MAX(0,K11*(1+Plan!$C$18/12)-(Plan!$D$18+IF(Plan!$E$18=$L12,Plan!$B$5+IF(AND(N(Plan!$B$9)>0,N(B11)<=0),Plan!$D$9,0)+IF(AND(N(Plan!$B$10)>0,N(C11)<=0),Plan!$D$10,0)+IF(AND(N(Plan!$B$11)>0,N(D11)<=0),Plan!$D$11,0)+IF(AND(N(Plan!$B$12)>0,N(E11)<=0),Plan!$D$12,0)+IF(AND(N(Plan!$B$13)>0,N(F11)<=0),Plan!$D$13,0)+IF(AND(N(Plan!$B$14)>0,N(G11)<=0),Plan!$D$14,0)+IF(AND(N(Plan!$B$15)>0,N(H11)<=0),Plan!$D$15,0)+IF(AND(N(Plan!$B$16)>0,N(I11)<=0),Plan!$D$16,0)+IF(AND(N(Plan!$B$17)>0,N(J11)<=0),Plan!$D$17,0)+IF(AND(N(Plan!$B$18)>0,N(K11)<=0),Plan!$D$18,0),0)))) | L12: =MIN(IF(N(B11)>0,Plan!$E$9,999),IF(N(C11)>0,Plan!$E$10,999),IF(N(D11)>0,Plan!$E$11,999),IF(N(E11)>0,Plan!$E$12,999),IF(N(F11)>0,Plan!$E$13,999),IF(N(G11)>0,Plan!$E$14,999),IF(N(H11)>0,Plan!$E$15,999),IF(N(I11)>0,Plan!$E$16,999),IF(N(J11)>0,Plan!$E$17,999),IF(N(K11)>0,Plan!$E$18,999)) | M12: =IF(N(B11)<=0,0,MIN(B11*(1+Plan!$C$9/12),Plan!$D$9+IF(Plan!$E$9=$L12,Plan!$B$5+IF(AND(N(Plan!$B$9)>0,N(B11)<=0),Plan!$D$9,0)+IF(AND(N(Plan!$B$10)>0,N(C11)<=0),Plan!$D$10,0)+IF(AND(N(Plan!$B$11)>0,N(D11)<=0),Plan!$D$11,0)+IF(AND(N(Plan!$B$12)>0,N(E11)<=0),Plan!$D$12,0)+IF(AND(N(Plan!$B$13)>0,N(F11)<=0),Plan!$D$13,0)+IF(AND(N(Plan!$B$14)>0,N(G11)<=0),Plan!$D$14,0)+IF(AND(N(Plan!$B$15)>0,N(H11)<=0),Plan!$D$15,0)+IF(AND(N(Plan!$B$16)>0,N(I11)<=0),Plan!$D$16,0)+IF(AND(N(Plan!$B$17)>0,N(J11)<=0),Plan!$D$17,0)+IF(AND(N(Plan!$B$18)>0,N(K11)<=0),Plan!$D$18,0),0)))+IF(N(C11)<=0,0,MIN(C11*(1+Plan!$C$10/12),Plan!$D$10+IF(Plan!$E$10=$L12,Plan!$B$5+IF(AND(N(Plan!$B$9)>0,N(B11)<=0),Plan!$D$9,0)+IF(AND(N(Plan!$B$10)>0,N(C11)<=0),Plan!$D$10,0)+IF(AND(N(Plan!$B$11)>0,N(D11)<=0),Plan!$D$11,0)+IF(AND(N(Plan!$B$12)>0,N(E11)<=0),Plan!$D$12,0)+IF(AND(N(Plan!$B$13)>0,N(F11)<=0),Plan!$D$13,0)+IF(AND(N(Plan!$B$14)>0,N(G11)<=0),Plan!$D$14,0)+IF(AND(N(Plan!$B$15)>0,N(H11)<=0),Plan!$D$15,0)+IF(AND(N(Plan!$B$16)>0,N(I11)<=0),Plan!$D$16,0)+IF(AND(N(Plan!$B$17)>0,N(J11)<=0),Plan!$D$17,0)+IF(AND(N(Plan!$B$18)>0,N(K11)<=0),Plan!$D$18,0),0)))+IF(N(D11)<=0,0,MIN(D11*(1+Plan!$C$11/12),Plan!$D$11+IF(Plan!$E$11=$L12,Plan!$B$5+IF(AND(N(Plan!$B$9)>0,N(B11)<=0),Plan!$D$9,0)+IF(AND(N(Plan!$B$10)>0,N(C11)<=0),Plan!$D$10,0)+IF(AND(N(Plan!$B$11)>0,N(D11)<=0),Plan!$D$11,0)+IF(AND(N(Plan!$B$12)>0,N(E11)<=0),Plan!$D$12,0)+IF(AND(N(Plan!$B$13)>0,N(F11)<=0),Plan!$D$13,0)+IF(AND(N(Plan!$B$14)>0,N(G11)<=0),Plan!$D$14,0)+IF(AND(N(Plan!$B$15)>0,N(H11)<=0),Plan!$D$15,0)+IF(AND(N(Plan!$B$16)>0,N(I11)<=0),Plan!$D$16,0)+IF(AND(N(Plan!$B$17)>0,N(J11)<=0),Plan!$D$17,0)+IF(AND(N(Plan!$B$18)>0,N(K11)<=0),Plan!$D$18,0),0)))+IF(N(E11)<=0,0,MIN(E11*(1+Plan!$C$12/12),Plan!$D$12+IF(Plan!$E$12=$L12,Plan!$B$5+IF(AND(N(Plan!$B$9)>0,N(B11)<=0),Plan!$D$9,0)+IF(AND(N(Plan!$B$10)>0,N(C11)<=0),Plan!$D$10,0)+IF(AND(N(Plan!$B$11)>0,N(D11)<=0),Plan!$D$11,0)+IF(AND(N(Plan!$B$12)>0,N(E11)<=0),Plan!$D$12,0)+IF(AND(N(Plan!$B$13)>0,N(F11)<=0),Plan!$D$13,0)+IF(AND(N(Plan!$B$14)>0,N(G11)<=0),Plan!$D$14,0)+IF(AND(N(Plan!$B$15)>0,N(H11)<=0),Plan!$D$15,0)+IF(AND(N(Plan!$B$16)>0,N(I11)<=0),Plan!$D$16,0)+IF(AND(N(Plan!$B$17)>0,N(J11)<=0),Plan!$D$17,0)+IF(AND(N(Plan!$B$18)>0,N(K11)<=0),Plan!$D$18,0),0)))+IF(N(F11)<=0,0,MIN(F11*(1+Plan!$C$13/12),Plan!$D$13+IF(Plan!$E$13=$L12,Plan!$B$5+IF(AND(N(Plan!$B$9)>0,N(B11)<=0),Plan!$D$9,0)+IF(AND(N(Plan!$B$10)>0,N(C11)<=0),Plan!$D$10,0)+IF(AND(N(Plan!$B$11)>0,N(D11)<=0),Plan!$D$11,0)+IF(AND(N(Plan!$B$12)>0,N(E11)<=0),Plan!$D$12,0)+IF(AND(N(Plan!$B$13)>0,N(F11)<=0),Plan!$D$13,0)+IF(AND(N(Plan!$B$14)>0,N(G11)<=0),Plan!$D$14,0)+IF(AND(N(Plan!$B$15)>0,N(H11)<=0),Plan!$D$15,0)+IF(AND(N(Plan!$B$16)>0,N(I11)<=0),Plan!$D$16,0)+IF(AND(N(Plan!$B$17)>0,N(J11)<=0),Plan!$D$17,0)+IF(AND(N(Plan!$B$18)>0,N(K11)<=0),Plan!$D$18,0),0)))+IF(N(G11)<=0,0,MIN(G11*(1+Plan!$C$14/12),Plan!$D$14+IF(Plan!$E$14=$L12,Plan!$B$5+IF(AND(N(Plan!$B$9)>0,N(B11)<=0),Plan!$D$9,0)+IF(AND(N(Plan!$B$10)>0,N(C11)<=0),Plan!$D$10,0)+IF(AND(N(Plan!$B$11)>0,N(D11)<=0),Plan!$D$11,0)+IF(AND(N(Plan!$B$12)>0,N(E11)<=0),Plan!$D$12,0)+IF(AND(N(Plan!$B$13)>0,N(F11)<=0),Plan!$D$13,0)+IF(AND(N(Plan!$B$14)>0,N(G11)<=0),Plan!$D$14,0)+IF(AND(N(Plan!$B$15)>0,N(H11)<=0),Plan!$D$15,0)+IF(AND(N(Plan!$B$16)>0,N(I11)<=0),Plan!$D$16,0)+IF(AND(N(Plan!$B$17)>0,N(J11)<=0),Plan!$D$17,0)+IF(AND(N(Plan!$B$18)>0,N(K11)<=0),Plan!$D$18,0),0)))+IF(N(H11)<=0,0,MIN(H11*(1+Plan!$C$15/12),Plan!$D$15+IF(Plan!$E$15=$L12,Plan!$B$5+IF(AND(N(Plan!$B$9)>0,N(B11)<=0),Plan!$D$9,0)+IF(AND(N(Plan!$B$10)>0,N(C11)<=0),Plan!$D$10,0)+IF(AND(N(Plan!$B$11)>0,N(D11)<=0),Plan!$D$11,0)+IF(AND(N(Plan!$B$12)>0,N(E11)<=0),Plan!$D$12,0)+IF(AND(N(Plan!$B$13)>0,N(F11)<=0),Plan!$D$13,0)+IF(AND(N(Plan!$B$14)>0,N(G11)<=0),Plan!$D$14,0)+IF(AND(N(Plan!$B$15)>0,N(H11)<=0),Plan!$D$15,0)+IF(AND(N(Plan!$B$16)>0,N(I11)<=0),Plan!$D$16,0)+IF(AND(N(Plan!$B$17)>0,N(J11)<=0),Plan!$D$17,0)+IF(AND(N(Plan!$B$18)>0,N(K11)<=0),Plan!$D$18,0),0)))+IF(N(I11)<=0,0,MIN(I11*(1+Plan!$C$16/12),Plan!$D$16+IF(Plan!$E$16=$L12,Plan!$B$5+IF(AND(N(Plan!$B$9)>0,N(B11)<=0),Plan!$D$9,0)+IF(AND(N(Plan!$B$10)>0,N(C11)<=0),Plan!$D$10,0)+IF(AND(N(Plan!$B$11)>0,N(D11)<=0),Plan!$D$11,0)+IF(AND(N(Plan!$B$12)>0,N(E11)<=0),Plan!$D$12,0)+IF(AND(N(Plan!$B$13)>0,N(F11)<=0),Plan!$D$13,0)+IF(AND(N(Plan!$B$14)>0,N(G11)<=0),Plan!$D$14,0)+IF(AND(N(Plan!$B$15)>0,N(H11)<=0),Plan!$D$15,0)+IF(AND(N(Plan!$B$16)>0,N(I11)<=0),Plan!$D$16,0)+IF(AND(N(Plan!$B$17)>0,N(J11)<=0),Plan!$D$17,0)+IF(AND(N(Plan!$B$18)>0,N(K11)<=0),Plan!$D$18,0),0)))+IF(N(J11)<=0,0,MIN(J11*(1+Plan!$C$17/12),Plan!$D$17+IF(Plan!$E$17=$L12,Plan!$B$5+IF(AND(N(Plan!$B$9)>0,N(B11)<=0),Plan!$D$9,0)+IF(AND(N(Plan!$B$10)>0,N(C11)<=0),Plan!$D$10,0)+IF(AND(N(Plan!$B$11)>0,N(D11)<=0),Plan!$D$11,0)+IF(AND(N(Plan!$B$12)>0,N(E11)<=0),Plan!$D$12,0)+IF(AND(N(Plan!$B$13)>0,N(F11)<=0),Plan!$D$13,0)+IF(AND(N(Plan!$B$14)>0,N(G11)<=0),Plan!$D$14,0)+IF(AND(N(Plan!$B$15)>0,N(H11)<=0),Plan!$D$15,0)+IF(AND(N(Plan!$B$16)>0,N(I11)<=0),Plan!$D$16,0)+IF(AND(N(Plan!$B$17)>0,N(J11)<=0),Plan!$D$17,0)+IF(AND(N(Plan!$B$18)>0,N(K11)<=0),Plan!$D$18,0),0)))+IF(N(K11)<=0,0,MIN(K11*(1+Plan!$C$18/12),Plan!$D$18+IF(Plan!$E$18=$L12,Plan!$B$5+IF(AND(N(Plan!$B$9)>0,N(B11)<=0),Plan!$D$9,0)+IF(AND(N(Plan!$B$10)>0,N(C11)<=0),Plan!$D$10,0)+IF(AND(N(Plan!$B$11)>0,N(D11)<=0),Plan!$D$11,0)+IF(AND(N(Plan!$B$12)>0,N(E11)<=0),Plan!$D$12,0)+IF(AND(N(Plan!$B$13)>0,N(F11)<=0),Plan!$D$13,0)+IF(AND(N(Plan!$B$14)>0,N(G11)<=0),Plan!$D$14,0)+IF(AND(N(Plan!$B$15)>0,N(H11)<=0),Plan!$D$15,0)+IF(AND(N(Plan!$B$16)>0,N(I11)<=0),Plan!$D$16,0)+IF(AND(N(Plan!$B$17)>0,N(J11)<=0),Plan!$D$17,0)+IF(AND(N(Plan!$B$18)>0,N(K11)<=0),Plan!$D$18,0),0)))
A13: 9 | B13: =IF(N(B12)<=0,0,MAX(0,B12*(1+Plan!$C$9/12)-(Plan!$D$9+IF(Plan!$E$9=$L13,Plan!$B$5+IF(AND(N(Plan!$B$9)>0,N(B12)<=0),Plan!$D$9,0)+IF(AND(N(Plan!$B$10)>0,N(C12)<=0),Plan!$D$10,0)+IF(AND(N(Plan!$B$11)>0,N(D12)<=0),Plan!$D$11,0)+IF(AND(N(Plan!$B$12)>0,N(E12)<=0),Plan!$D$12,0)+IF(AND(N(Plan!$B$13)>0,N(F12)<=0),Plan!$D$13,0)+IF(AND(N(Plan!$B$14)>0,N(G12)<=0),Plan!$D$14,0)+IF(AND(N(Plan!$B$15)>0,N(H12)<=0),Plan!$D$15,0)+IF(AND(N(Plan!$B$16)>0,N(I12)<=0),Plan!$D$16,0)+IF(AND(N(Plan!$B$17)>0,N(J12)<=0),Plan!$D$17,0)+IF(AND(N(Plan!$B$18)>0,N(K12)<=0),Plan!$D$18,0),0)))) | C13: =IF(N(C12)<=0,0,MAX(0,C12*(1+Plan!$C$10/12)-(Plan!$D$10+IF(Plan!$E$10=$L13,Plan!$B$5+IF(AND(N(Plan!$B$9)>0,N(B12)<=0),Plan!$D$9,0)+IF(AND(N(Plan!$B$10)>0,N(C12)<=0),Plan!$D$10,0)+IF(AND(N(Plan!$B$11)>0,N(D12)<=0),Plan!$D$11,0)+IF(AND(N(Plan!$B$12)>0,N(E12)<=0),Plan!$D$12,0)+IF(AND(N(Plan!$B$13)>0,N(F12)<=0),Plan!$D$13,0)+IF(AND(N(Plan!$B$14)>0,N(G12)<=0),Plan!$D$14,0)+IF(AND(N(Plan!$B$15)>0,N(H12)<=0),Plan!$D$15,0)+IF(AND(N(Plan!$B$16)>0,N(I12)<=0),Plan!$D$16,0)+IF(AND(N(Plan!$B$17)>0,N(J12)<=0),Plan!$D$17,0)+IF(AND(N(Plan!$B$18)>0,N(K12)<=0),Plan!$D$18,0),0)))) | D13: =IF(N(D12)<=0,0,MAX(0,D12*(1+Plan!$C$11/12)-(Plan!$D$11+IF(Plan!$E$11=$L13,Plan!$B$5+IF(AND(N(Plan!$B$9)>0,N(B12)<=0),Plan!$D$9,0)+IF(AND(N(Plan!$B$10)>0,N(C12)<=0),Plan!$D$10,0)+IF(AND(N(Plan!$B$11)>0,N(D12)<=0),Plan!$D$11,0)+IF(AND(N(Plan!$B$12)>0,N(E12)<=0),Plan!$D$12,0)+IF(AND(N(Plan!$B$13)>0,N(F12)<=0),Plan!$D$13,0)+IF(AND(N(Plan!$B$14)>0,N(G12)<=0),Plan!$D$14,0)+IF(AND(N(Plan!$B$15)>0,N(H12)<=0),Plan!$D$15,0)+IF(AND(N(Plan!$B$16)>0,N(I12)<=0),Plan!$D$16,0)+IF(AND(N(Plan!$B$17)>0,N(J12)<=0),Plan!$D$17,0)+IF(AND(N(Plan!$B$18)>0,N(K12)<=0),Plan!$D$18,0),0)))) | E13: =IF(N(E12)<=0,0,MAX(0,E12*(1+Plan!$C$12/12)-(Plan!$D$12+IF(Plan!$E$12=$L13,Plan!$B$5+IF(AND(N(Plan!$B$9)>0,N(B12)<=0),Plan!$D$9,0)+IF(AND(N(Plan!$B$10)>0,N(C12)<=0),Plan!$D$10,0)+IF(AND(N(Plan!$B$11)>0,N(D12)<=0),Plan!$D$11,0)+IF(AND(N(Plan!$B$12)>0,N(E12)<=0),Plan!$D$12,0)+IF(AND(N(Plan!$B$13)>0,N(F12)<=0),Plan!$D$13,0)+IF(AND(N(Plan!$B$14)>0,N(G12)<=0),Plan!$D$14,0)+IF(AND(N(Plan!$B$15)>0,N(H12)<=0),Plan!$D$15,0)+IF(AND(N(Plan!$B$16)>0,N(I12)<=0),Plan!$D$16,0)+IF(AND(N(Plan!$B$17)>0,N(J12)<=0),Plan!$D$17,0)+IF(AND(N(Plan!$B$18)>0,N(K12)<=0),Plan!$D$18,0),0)))) | F13: =IF(N(F12)<=0,0,MAX(0,F12*(1+Plan!$C$13/12)-(Plan!$D$13+IF(Plan!$E$13=$L13,Plan!$B$5+IF(AND(N(Plan!$B$9)>0,N(B12)<=0),Plan!$D$9,0)+IF(AND(N(Plan!$B$10)>0,N(C12)<=0),Plan!$D$10,0)+IF(AND(N(Plan!$B$11)>0,N(D12)<=0),Plan!$D$11,0)+IF(AND(N(Plan!$B$12)>0,N(E12)<=0),Plan!$D$12,0)+IF(AND(N(Plan!$B$13)>0,N(F12)<=0),Plan!$D$13,0)+IF(AND(N(Plan!$B$14)>0,N(G12)<=0),Plan!$D$14,0)+IF(AND(N(Plan!$B$15)>0,N(H12)<=0),Plan!$D$15,0)+IF(AND(N(Plan!$B$16)>0,N(I12)<=0),Plan!$D$16,0)+IF(AND(N(Plan!$B$17)>0,N(J12)<=0),Plan!$D$17,0)+IF(AND(N(Plan!$B$18)>0,N(K12)<=0),Plan!$D$18,0),0)))) | G13: =IF(N(G12)<=0,0,MAX(0,G12*(1+Plan!$C$14/12)-(Plan!$D$14+IF(Plan!$E$14=$L13,Plan!$B$5+IF(AND(N(Plan!$B$9)>0,N(B12)<=0),Plan!$D$9,0)+IF(AND(N(Plan!$B$10)>0,N(C12)<=0),Plan!$D$10,0)+IF(AND(N(Plan!$B$11)>0,N(D12)<=0),Plan!$D$11,0)+IF(AND(N(Plan!$B$12)>0,N(E12)<=0),Plan!$D$12,0)+IF(AND(N(Plan!$B$13)>0,N(F12)<=0),Plan!$D$13,0)+IF(AND(N(Plan!$B$14)>0,N(G12)<=0),Plan!$D$14,0)+IF(AND(N(Plan!$B$15)>0,N(H12)<=0),Plan!$D$15,0)+IF(AND(N(Plan!$B$16)>0,N(I12)<=0),Plan!$D$16,0)+IF(AND(N(Plan!$B$17)>0,N(J12)<=0),Plan!$D$17,0)+IF(AND(N(Plan!$B$18)>0,N(K12)<=0),Plan!$D$18,0),0)))) | H13: =IF(N(H12)<=0,0,MAX(0,H12*(1+Plan!$C$15/12)-(Plan!$D$15+IF(Plan!$E$15=$L13,Plan!$B$5+IF(AND(N(Plan!$B$9)>0,N(B12)<=0),Plan!$D$9,0)+IF(AND(N(Plan!$B$10)>0,N(C12)<=0),Plan!$D$10,0)+IF(AND(N(Plan!$B$11)>0,N(D12)<=0),Plan!$D$11,0)+IF(AND(N(Plan!$B$12)>0,N(E12)<=0),Plan!$D$12,0)+IF(AND(N(Plan!$B$13)>0,N(F12)<=0),Plan!$D$13,0)+IF(AND(N(Plan!$B$14)>0,N(G12)<=0),Plan!$D$14,0)+IF(AND(N(Plan!$B$15)>0,N(H12)<=0),Plan!$D$15,0)+IF(AND(N(Plan!$B$16)>0,N(I12)<=0),Plan!$D$16,0)+IF(AND(N(Plan!$B$17)>0,N(J12)<=0),Plan!$D$17,0)+IF(AND(N(Plan!$B$18)>0,N(K12)<=0),Plan!$D$18,0),0)))) | I13: =IF(N(I12)<=0,0,MAX(0,I12*(1+Plan!$C$16/12)-(Plan!$D$16+IF(Plan!$E$16=$L13,Plan!$B$5+IF(AND(N(Plan!$B$9)>0,N(B12)<=0),Plan!$D$9,0)+IF(AND(N(Plan!$B$10)>0,N(C12)<=0),Plan!$D$10,0)+IF(AND(N(Plan!$B$11)>0,N(D12)<=0),Plan!$D$11,0)+IF(AND(N(Plan!$B$12)>0,N(E12)<=0),Plan!$D$12,0)+IF(AND(N(Plan!$B$13)>0,N(F12)<=0),Plan!$D$13,0)+IF(AND(N(Plan!$B$14)>0,N(G12)<=0),Plan!$D$14,0)+IF(AND(N(Plan!$B$15)>0,N(H12)<=0),Plan!$D$15,0)+IF(AND(N(Plan!$B$16)>0,N(I12)<=0),Plan!$D$16,0)+IF(AND(N(Plan!$B$17)>0,N(J12)<=0),Plan!$D$17,0)+IF(AND(N(Plan!$B$18)>0,N(K12)<=0),Plan!$D$18,0),0)))) | J13: =IF(N(J12)<=0,0,MAX(0,J12*(1+Plan!$C$17/12)-(Plan!$D$17+IF(Plan!$E$17=$L13,Plan!$B$5+IF(AND(N(Plan!$B$9)>0,N(B12)<=0),Plan!$D$9,0)+IF(AND(N(Plan!$B$10)>0,N(C12)<=0),Plan!$D$10,0)+IF(AND(N(Plan!$B$11)>0,N(D12)<=0),Plan!$D$11,0)+IF(AND(N(Plan!$B$12)>0,N(E12)<=0),Plan!$D$12,0)+IF(AND(N(Plan!$B$13)>0,N(F12)<=0),Plan!$D$13,0)+IF(AND(N(Plan!$B$14)>0,N(G12)<=0),Plan!$D$14,0)+IF(AND(N(Plan!$B$15)>0,N(H12)<=0),Plan!$D$15,0)+IF(AND(N(Plan!$B$16)>0,N(I12)<=0),Plan!$D$16,0)+IF(AND(N(Plan!$B$17)>0,N(J12)<=0),Plan!$D$17,0)+IF(AND(N(Plan!$B$18)>0,N(K12)<=0),Plan!$D$18,0),0)))) | K13: =IF(N(K12)<=0,0,MAX(0,K12*(1+Plan!$C$18/12)-(Plan!$D$18+IF(Plan!$E$18=$L13,Plan!$B$5+IF(AND(N(Plan!$B$9)>0,N(B12)<=0),Plan!$D$9,0)+IF(AND(N(Plan!$B$10)>0,N(C12)<=0),Plan!$D$10,0)+IF(AND(N(Plan!$B$11)>0,N(D12)<=0),Plan!$D$11,0)+IF(AND(N(Plan!$B$12)>0,N(E12)<=0),Plan!$D$12,0)+IF(AND(N(Plan!$B$13)>0,N(F12)<=0),Plan!$D$13,0)+IF(AND(N(Plan!$B$14)>0,N(G12)<=0),Plan!$D$14,0)+IF(AND(N(Plan!$B$15)>0,N(H12)<=0),Plan!$D$15,0)+IF(AND(N(Plan!$B$16)>0,N(I12)<=0),Plan!$D$16,0)+IF(AND(N(Plan!$B$17)>0,N(J12)<=0),Plan!$D$17,0)+IF(AND(N(Plan!$B$18)>0,N(K12)<=0),Plan!$D$18,0),0)))) | L13: =MIN(IF(N(B12)>0,Plan!$E$9,999),IF(N(C12)>0,Plan!$E$10,999),IF(N(D12)>0,Plan!$E$11,999),IF(N(E12)>0,Plan!$E$12,999),IF(N(F12)>0,Plan!$E$13,999),IF(N(G12)>0,Plan!$E$14,999),IF(N(H12)>0,Plan!$E$15,999),IF(N(I12)>0,Plan!$E$16,999),IF(N(J12)>0,Plan!$E$17,999),IF(N(K12)>0,Plan!$E$18,999)) | M13: =IF(N(B12)<=0,0,MIN(B12*(1+Plan!$C$9/12),Plan!$D$9+IF(Plan!$E$9=$L13,Plan!$B$5+IF(AND(N(Plan!$B$9)>0,N(B12)<=0),Plan!$D$9,0)+IF(AND(N(Plan!$B$10)>0,N(C12)<=0),Plan!$D$10,0)+IF(AND(N(Plan!$B$11)>0,N(D12)<=0),Plan!$D$11,0)+IF(AND(N(Plan!$B$12)>0,N(E12)<=0),Plan!$D$12,0)+IF(AND(N(Plan!$B$13)>0,N(F12)<=0),Plan!$D$13,0)+IF(AND(N(Plan!$B$14)>0,N(G12)<=0),Plan!$D$14,0)+IF(AND(N(Plan!$B$15)>0,N(H12)<=0),Plan!$D$15,0)+IF(AND(N(Plan!$B$16)>0,N(I12)<=0),Plan!$D$16,0)+IF(AND(N(Plan!$B$17)>0,N(J12)<=0),Plan!$D$17,0)+IF(AND(N(Plan!$B$18)>0,N(K12)<=0),Plan!$D$18,0),0)))+IF(N(C12)<=0,0,MIN(C12*(1+Plan!$C$10/12),Plan!$D$10+IF(Plan!$E$10=$L13,Plan!$B$5+IF(AND(N(Plan!$B$9)>0,N(B12)<=0),Plan!$D$9,0)+IF(AND(N(Plan!$B$10)>0,N(C12)<=0),Plan!$D$10,0)+IF(AND(N(Plan!$B$11)>0,N(D12)<=0),Plan!$D$11,0)+IF(AND(N(Plan!$B$12)>0,N(E12)<=0),Plan!$D$12,0)+IF(AND(N(Plan!$B$13)>0,N(F12)<=0),Plan!$D$13,0)+IF(AND(N(Plan!$B$14)>0,N(G12)<=0),Plan!$D$14,0)+IF(AND(N(Plan!$B$15)>0,N(H12)<=0),Plan!$D$15,0)+IF(AND(N(Plan!$B$16)>0,N(I12)<=0),Plan!$D$16,0)+IF(AND(N(Plan!$B$17)>0,N(J12)<=0),Plan!$D$17,0)+IF(AND(N(Plan!$B$18)>0,N(K12)<=0),Plan!$D$18,0),0)))+IF(N(D12)<=0,0,MIN(D12*(1+Plan!$C$11/12),Plan!$D$11+IF(Plan!$E$11=$L13,Plan!$B$5+IF(AND(N(Plan!$B$9)>0,N(B12)<=0),Plan!$D$9,0)+IF(AND(N(Plan!$B$10)>0,N(C12)<=0),Plan!$D$10,0)+IF(AND(N(Plan!$B$11)>0,N(D12)<=0),Plan!$D$11,0)+IF(AND(N(Plan!$B$12)>0,N(E12)<=0),Plan!$D$12,0)+IF(AND(N(Plan!$B$13)>0,N(F12)<=0),Plan!$D$13,0)+IF(AND(N(Plan!$B$14)>0,N(G12)<=0),Plan!$D$14,0)+IF(AND(N(Plan!$B$15)>0,N(H12)<=0),Plan!$D$15,0)+IF(AND(N(Plan!$B$16)>0,N(I12)<=0),Plan!$D$16,0)+IF(AND(N(Plan!$B$17)>0,N(J12)<=0),Plan!$D$17,0)+IF(AND(N(Plan!$B$18)>0,N(K12)<=0),Plan!$D$18,0),0)))+IF(N(E12)<=0,0,MIN(E12*(1+Plan!$C$12/12),Plan!$D$12+IF(Plan!$E$12=$L13,Plan!$B$5+IF(AND(N(Plan!$B$9)>0,N(B12)<=0),Plan!$D$9,0)+IF(AND(N(Plan!$B$10)>0,N(C12)<=0),Plan!$D$10,0)+IF(AND(N(Plan!$B$11)>0,N(D12)<=0),Plan!$D$11,0)+IF(AND(N(Plan!$B$12)>0,N(E12)<=0),Plan!$D$12,0)+IF(AND(N(Plan!$B$13)>0,N(F12)<=0),Plan!$D$13,0)+IF(AND(N(Plan!$B$14)>0,N(G12)<=0),Plan!$D$14,0)+IF(AND(N(Plan!$B$15)>0,N(H12)<=0),Plan!$D$15,0)+IF(AND(N(Plan!$B$16)>0,N(I12)<=0),Plan!$D$16,0)+IF(AND(N(Plan!$B$17)>0,N(J12)<=0),Plan!$D$17,0)+IF(AND(N(Plan!$B$18)>0,N(K12)<=0),Plan!$D$18,0),0)))+IF(N(F12)<=0,0,MIN(F12*(1+Plan!$C$13/12),Plan!$D$13+IF(Plan!$E$13=$L13,Plan!$B$5+IF(AND(N(Plan!$B$9)>0,N(B12)<=0),Plan!$D$9,0)+IF(AND(N(Plan!$B$10)>0,N(C12)<=0),Plan!$D$10,0)+IF(AND(N(Plan!$B$11)>0,N(D12)<=0),Plan!$D$11,0)+IF(AND(N(Plan!$B$12)>0,N(E12)<=0),Plan!$D$12,0)+IF(AND(N(Plan!$B$13)>0,N(F12)<=0),Plan!$D$13,0)+IF(AND(N(Plan!$B$14)>0,N(G12)<=0),Plan!$D$14,0)+IF(AND(N(Plan!$B$15)>0,N(H12)<=0),Plan!$D$15,0)+IF(AND(N(Plan!$B$16)>0,N(I12)<=0),Plan!$D$16,0)+IF(AND(N(Plan!$B$17)>0,N(J12)<=0),Plan!$D$17,0)+IF(AND(N(Plan!$B$18)>0,N(K12)<=0),Plan!$D$18,0),0)))+IF(N(G12)<=0,0,MIN(G12*(1+Plan!$C$14/12),Plan!$D$14+IF(Plan!$E$14=$L13,Plan!$B$5+IF(AND(N(Plan!$B$9)>0,N(B12)<=0),Plan!$D$9,0)+IF(AND(N(Plan!$B$10)>0,N(C12)<=0),Plan!$D$10,0)+IF(AND(N(Plan!$B$11)>0,N(D12)<=0),Plan!$D$11,0)+IF(AND(N(Plan!$B$12)>0,N(E12)<=0),Plan!$D$12,0)+IF(AND(N(Plan!$B$13)>0,N(F12)<=0),Plan!$D$13,0)+IF(AND(N(Plan!$B$14)>0,N(G12)<=0),Plan!$D$14,0)+IF(AND(N(Plan!$B$15)>0,N(H12)<=0),Plan!$D$15,0)+IF(AND(N(Plan!$B$16)>0,N(I12)<=0),Plan!$D$16,0)+IF(AND(N(Plan!$B$17)>0,N(J12)<=0),Plan!$D$17,0)+IF(AND(N(Plan!$B$18)>0,N(K12)<=0),Plan!$D$18,0),0)))+IF(N(H12)<=0,0,MIN(H12*(1+Plan!$C$15/12),Plan!$D$15+IF(Plan!$E$15=$L13,Plan!$B$5+IF(AND(N(Plan!$B$9)>0,N(B12)<=0),Plan!$D$9,0)+IF(AND(N(Plan!$B$10)>0,N(C12)<=0),Plan!$D$10,0)+IF(AND(N(Plan!$B$11)>0,N(D12)<=0),Plan!$D$11,0)+IF(AND(N(Plan!$B$12)>0,N(E12)<=0),Plan!$D$12,0)+IF(AND(N(Plan!$B$13)>0,N(F12)<=0),Plan!$D$13,0)+IF(AND(N(Plan!$B$14)>0,N(G12)<=0),Plan!$D$14,0)+IF(AND(N(Plan!$B$15)>0,N(H12)<=0),Plan!$D$15,0)+IF(AND(N(Plan!$B$16)>0,N(I12)<=0),Plan!$D$16,0)+IF(AND(N(Plan!$B$17)>0,N(J12)<=0),Plan!$D$17,0)+IF(AND(N(Plan!$B$18)>0,N(K12)<=0),Plan!$D$18,0),0)))+IF(N(I12)<=0,0,MIN(I12*(1+Plan!$C$16/12),Plan!$D$16+IF(Plan!$E$16=$L13,Plan!$B$5+IF(AND(N(Plan!$B$9)>0,N(B12)<=0),Plan!$D$9,0)+IF(AND(N(Plan!$B$10)>0,N(C12)<=0),Plan!$D$10,0)+IF(AND(N(Plan!$B$11)>0,N(D12)<=0),Plan!$D$11,0)+IF(AND(N(Plan!$B$12)>0,N(E12)<=0),Plan!$D$12,0)+IF(AND(N(Plan!$B$13)>0,N(F12)<=0),Plan!$D$13,0)+IF(AND(N(Plan!$B$14)>0,N(G12)<=0),Plan!$D$14,0)+IF(AND(N(Plan!$B$15)>0,N(H12)<=0),Plan!$D$15,0)+IF(AND(N(Plan!$B$16)>0,N(I12)<=0),Plan!$D$16,0)+IF(AND(N(Plan!$B$17)>0,N(J12)<=0),Plan!$D$17,0)+IF(AND(N(Plan!$B$18)>0,N(K12)<=0),Plan!$D$18,0),0)))+IF(N(J12)<=0,0,MIN(J12*(1+Plan!$C$17/12),Plan!$D$17+IF(Plan!$E$17=$L13,Plan!$B$5+IF(AND(N(Plan!$B$9)>0,N(B12)<=0),Plan!$D$9,0)+IF(AND(N(Plan!$B$10)>0,N(C12)<=0),Plan!$D$10,0)+IF(AND(N(Plan!$B$11)>0,N(D12)<=0),Plan!$D$11,0)+IF(AND(N(Plan!$B$12)>0,N(E12)<=0),Plan!$D$12,0)+IF(AND(N(Plan!$B$13)>0,N(F12)<=0),Plan!$D$13,0)+IF(AND(N(Plan!$B$14)>0,N(G12)<=0),Plan!$D$14,0)+IF(AND(N(Plan!$B$15)>0,N(H12)<=0),Plan!$D$15,0)+IF(AND(N(Plan!$B$16)>0,N(I12)<=0),Plan!$D$16,0)+IF(AND(N(Plan!$B$17)>0,N(J12)<=0),Plan!$D$17,0)+IF(AND(N(Plan!$B$18)>0,N(K12)<=0),Plan!$D$18,0),0)))+IF(N(K12)<=0,0,MIN(K12*(1+Plan!$C$18/12),Plan!$D$18+IF(Plan!$E$18=$L13,Plan!$B$5+IF(AND(N(Plan!$B$9)>0,N(B12)<=0),Plan!$D$9,0)+IF(AND(N(Plan!$B$10)>0,N(C12)<=0),Plan!$D$10,0)+IF(AND(N(Plan!$B$11)>0,N(D12)<=0),Plan!$D$11,0)+IF(AND(N(Plan!$B$12)>0,N(E12)<=0),Plan!$D$12,0)+IF(AND(N(Plan!$B$13)>0,N(F12)<=0),Plan!$D$13,0)+IF(AND(N(Plan!$B$14)>0,N(G12)<=0),Plan!$D$14,0)+IF(AND(N(Plan!$B$15)>0,N(H12)<=0),Plan!$D$15,0)+IF(AND(N(Plan!$B$16)>0,N(I12)<=0),Plan!$D$16,0)+IF(AND(N(Plan!$B$17)>0,N(J12)<=0),Plan!$D$17,0)+IF(AND(N(Plan!$B$18)>0,N(K12)<=0),Plan!$D$18,0),0)))
A14: 10 | B14: =IF(N(B13)<=0,0,MAX(0,B13*(1+Plan!$C$9/12)-(Plan!$D$9+IF(Plan!$E$9=$L14,Plan!$B$5+IF(AND(N(Plan!$B$9)>0,N(B13)<=0),Plan!$D$9,0)+IF(AND(N(Plan!$B$10)>0,N(C13)<=0),Plan!$D$10,0)+IF(AND(N(Plan!$B$11)>0,N(D13)<=0),Plan!$D$11,0)+IF(AND(N(Plan!$B$12)>0,N(E13)<=0),Plan!$D$12,0)+IF(AND(N(Plan!$B$13)>0,N(F13)<=0),Plan!$D$13,0)+IF(AND(N(Plan!$B$14)>0,N(G13)<=0),Plan!$D$14,0)+IF(AND(N(Plan!$B$15)>0,N(H13)<=0),Plan!$D$15,0)+IF(AND(N(Plan!$B$16)>0,N(I13)<=0),Plan!$D$16,0)+IF(AND(N(Plan!$B$17)>0,N(J13)<=0),Plan!$D$17,0)+IF(AND(N(Plan!$B$18)>0,N(K13)<=0),Plan!$D$18,0),0)))) | C14: =IF(N(C13)<=0,0,MAX(0,C13*(1+Plan!$C$10/12)-(Plan!$D$10+IF(Plan!$E$10=$L14,Plan!$B$5+IF(AND(N(Plan!$B$9)>0,N(B13)<=0),Plan!$D$9,0)+IF(AND(N(Plan!$B$10)>0,N(C13)<=0),Plan!$D$10,0)+IF(AND(N(Plan!$B$11)>0,N(D13)<=0),Plan!$D$11,0)+IF(AND(N(Plan!$B$12)>0,N(E13)<=0),Plan!$D$12,0)+IF(AND(N(Plan!$B$13)>0,N(F13)<=0),Plan!$D$13,0)+IF(AND(N(Plan!$B$14)>0,N(G13)<=0),Plan!$D$14,0)+IF(AND(N(Plan!$B$15)>0,N(H13)<=0),Plan!$D$15,0)+IF(AND(N(Plan!$B$16)>0,N(I13)<=0),Plan!$D$16,0)+IF(AND(N(Plan!$B$17)>0,N(J13)<=0),Plan!$D$17,0)+IF(AND(N(Plan!$B$18)>0,N(K13)<=0),Plan!$D$18,0),0)))) | D14: =IF(N(D13)<=0,0,MAX(0,D13*(1+Plan!$C$11/12)-(Plan!$D$11+IF(Plan!$E$11=$L14,Plan!$B$5+IF(AND(N(Plan!$B$9)>0,N(B13)<=0),Plan!$D$9,0)+IF(AND(N(Plan!$B$10)>0,N(C13)<=0),Plan!$D$10,0)+IF(AND(N(Plan!$B$11)>0,N(D13)<=0),Plan!$D$11,0)+IF(AND(N(Plan!$B$12)>0,N(E13)<=0),Plan!$D$12,0)+IF(AND(N(Plan!$B$13)>0,N(F13)<=0),Plan!$D$13,0)+IF(AND(N(Plan!$B$14)>0,N(G13)<=0),Plan!$D$14,0)+IF(AND(N(Plan!$B$15)>0,N(H13)<=0),Plan!$D$15,0)+IF(AND(N(Plan!$B$16)>0,N(I13)<=0),Plan!$D$16,0)+IF(AND(N(Plan!$B$17)>0,N(J13)<=0),Plan!$D$17,0)+IF(AND(N(Plan!$B$18)>0,N(K13)<=0),Plan!$D$18,0),0)))) | E14: =IF(N(E13)<=0,0,MAX(0,E13*(1+Plan!$C$12/12)-(Plan!$D$12+IF(Plan!$E$12=$L14,Plan!$B$5+IF(AND(N(Plan!$B$9)>0,N(B13)<=0),Plan!$D$9,0)+IF(AND(N(Plan!$B$10)>0,N(C13)<=0),Plan!$D$10,0)+IF(AND(N(Plan!$B$11)>0,N(D13)<=0),Plan!$D$11,0)+IF(AND(N(Plan!$B$12)>0,N(E13)<=0),Plan!$D$12,0)+IF(AND(N(Plan!$B$13)>0,N(F13)<=0),Plan!$D$13,0)+IF(AND(N(Plan!$B$14)>0,N(G13)<=0),Plan!$D$14,0)+IF(AND(N(Plan!$B$15)>0,N(H13)<=0),Plan!$D$15,0)+IF(AND(N(Plan!$B$16)>0,N(I13)<=0),Plan!$D$16,0)+IF(AND(N(Plan!$B$17)>0,N(J13)<=0),Plan!$D$17,0)+IF(AND(N(Plan!$B$18)>0,N(K13)<=0),Plan!$D$18,0),0)))) | F14: =IF(N(F13)<=0,0,MAX(0,F13*(1+Plan!$C$13/12)-(Plan!$D$13+IF(Plan!$E$13=$L14,Plan!$B$5+IF(AND(N(Plan!$B$9)>0,N(B13)<=0),Plan!$D$9,0)+IF(AND(N(Plan!$B$10)>0,N(C13)<=0),Plan!$D$10,0)+IF(AND(N(Plan!$B$11)>0,N(D13)<=0),Plan!$D$11,0)+IF(AND(N(Plan!$B$12)>0,N(E13)<=0),Plan!$D$12,0)+IF(AND(N(Plan!$B$13)>0,N(F13)<=0),Plan!$D$13,0)+IF(AND(N(Plan!$B$14)>0,N(G13)<=0),Plan!$D$14,0)+IF(AND(N(Plan!$B$15)>0,N(H13)<=0),Plan!$D$15,0)+IF(AND(N(Plan!$B$16)>0,N(I13)<=0),Plan!$D$16,0)+IF(AND(N(Plan!$B$17)>0,N(J13)<=0),Plan!$D$17,0)+IF(AND(N(Plan!$B$18)>0,N(K13)<=0),Plan!$D$18,0),0)))) | G14: =IF(N(G13)<=0,0,MAX(0,G13*(1+Plan!$C$14/12)-(Plan!$D$14+IF(Plan!$E$14=$L14,Plan!$B$5+IF(AND(N(Plan!$B$9)>0,N(B13)<=0),Plan!$D$9,0)+IF(AND(N(Plan!$B$10)>0,N(C13)<=0),Plan!$D$10,0)+IF(AND(N(Plan!$B$11)>0,N(D13)<=0),Plan!$D$11,0)+IF(AND(N(Plan!$B$12)>0,N(E13)<=0),Plan!$D$12,0)+IF(AND(N(Plan!$B$13)>0,N(F13)<=0),Plan!$D$13,0)+IF(AND(N(Plan!$B$14)>0,N(G13)<=0),Plan!$D$14,0)+IF(AND(N(Plan!$B$15)>0,N(H13)<=0),Plan!$D$15,0)+IF(AND(N(Plan!$B$16)>0,N(I13)<=0),Plan!$D$16,0)+IF(AND(N(Plan!$B$17)>0,N(J13)<=0),Plan!$D$17,0)+IF(AND(N(Plan!$B$18)>0,N(K13)<=0),Plan!$D$18,0),0)))) | H14: =IF(N(H13)<=0,0,MAX(0,H13*(1+Plan!$C$15/12)-(Plan!$D$15+IF(Plan!$E$15=$L14,Plan!$B$5+IF(AND(N(Plan!$B$9)>0,N(B13)<=0),Plan!$D$9,0)+IF(AND(N(Plan!$B$10)>0,N(C13)<=0),Plan!$D$10,0)+IF(AND(N(Plan!$B$11)>0,N(D13)<=0),Plan!$D$11,0)+IF(AND(N(Plan!$B$12)>0,N(E13)<=0),Plan!$D$12,0)+IF(AND(N(Plan!$B$13)>0,N(F13)<=0),Plan!$D$13,0)+IF(AND(N(Plan!$B$14)>0,N(G13)<=0),Plan!$D$14,0)+IF(AND(N(Plan!$B$15)>0,N(H13)<=0),Plan!$D$15,0)+IF(AND(N(Plan!$B$16)>0,N(I13)<=0),Plan!$D$16,0)+IF(AND(N(Plan!$B$17)>0,N(J13)<=0),Plan!$D$17,0)+IF(AND(N(Plan!$B$18)>0,N(K13)<=0),Plan!$D$18,0),0)))) | I14: =IF(N(I13)<=0,0,MAX(0,I13*(1+Plan!$C$16/12)-(Plan!$D$16+IF(Plan!$E$16=$L14,Plan!$B$5+IF(AND(N(Plan!$B$9)>0,N(B13)<=0),Plan!$D$9,0)+IF(AND(N(Plan!$B$10)>0,N(C13)<=0),Plan!$D$10,0)+IF(AND(N(Plan!$B$11)>0,N(D13)<=0),Plan!$D$11,0)+IF(AND(N(Plan!$B$12)>0,N(E13)<=0),Plan!$D$12,0)+IF(AND(N(Plan!$B$13)>0,N(F13)<=0),Plan!$D$13,0)+IF(AND(N(Plan!$B$14)>0,N(G13)<=0),Plan!$D$14,0)+IF(AND(N(Plan!$B$15)>0,N(H13)<=0),Plan!$D$15,0)+IF(AND(N(Plan!$B$16)>0,N(I13)<=0),Plan!$D$16,0)+IF(AND(N(Plan!$B$17)>0,N(J13)<=0),Plan!$D$17,0)+IF(AND(N(Plan!$B$18)>0,N(K13)<=0),Plan!$D$18,0),0)))) | J14: =IF(N(J13)<=0,0,MAX(0,J13*(1+Plan!$C$17/12)-(Plan!$D$17+IF(Plan!$E$17=$L14,Plan!$B$5+IF(AND(N(Plan!$B$9)>0,N(B13)<=0),Plan!$D$9,0)+IF(AND(N(Plan!$B$10)>0,N(C13)<=0),Plan!$D$10,0)+IF(AND(N(Plan!$B$11)>0,N(D13)<=0),Plan!$D$11,0)+IF(AND(N(Plan!$B$12)>0,N(E13)<=0),Plan!$D$12,0)+IF(AND(N(Plan!$B$13)>0,N(F13)<=0),Plan!$D$13,0)+IF(AND(N(Plan!$B$14)>0,N(G13)<=0),Plan!$D$14,0)+IF(AND(N(Plan!$B$15)>0,N(H13)<=0),Plan!$D$15,0)+IF(AND(N(Plan!$B$16)>0,N(I13)<=0),Plan!$D$16,0)+IF(AND(N(Plan!$B$17)>0,N(J13)<=0),Plan!$D$17,0)+IF(AND(N(Plan!$B$18)>0,N(K13)<=0),Plan!$D$18,0),0)))) | K14: =IF(N(K13)<=0,0,MAX(0,K13*(1+Plan!$C$18/12)-(Plan!$D$18+IF(Plan!$E$18=$L14,Plan!$B$5+IF(AND(N(Plan!$B$9)>0,N(B13)<=0),Plan!$D$9,0)+IF(AND(N(Plan!$B$10)>0,N(C13)<=0),Plan!$D$10,0)+IF(AND(N(Plan!$B$11)>0,N(D13)<=0),Plan!$D$11,0)+IF(AND(N(Plan!$B$12)>0,N(E13)<=0),Plan!$D$12,0)+IF(AND(N(Plan!$B$13)>0,N(F13)<=0),Plan!$D$13,0)+IF(AND(N(Plan!$B$14)>0,N(G13)<=0),Plan!$D$14,0)+IF(AND(N(Plan!$B$15)>0,N(H13)<=0),Plan!$D$15,0)+IF(AND(N(Plan!$B$16)>0,N(I13)<=0),Plan!$D$16,0)+IF(AND(N(Plan!$B$17)>0,N(J13)<=0),Plan!$D$17,0)+IF(AND(N(Plan!$B$18)>0,N(K13)<=0),Plan!$D$18,0),0)))) | L14: =MIN(IF(N(B13)>0,Plan!$E$9,999),IF(N(C13)>0,Plan!$E$10,999),IF(N(D13)>0,Plan!$E$11,999),IF(N(E13)>0,Plan!$E$12,999),IF(N(F13)>0,Plan!$E$13,999),IF(N(G13)>0,Plan!$E$14,999),IF(N(H13)>0,Plan!$E$15,999),IF(N(I13)>0,Plan!$E$16,999),IF(N(J13)>0,Plan!$E$17,999),IF(N(K13)>0,Plan!$E$18,999)) | M14: =IF(N(B13)<=0,0,MIN(B13*(1+Plan!$C$9/12),Plan!$D$9+IF(Plan!$E$9=$L14,Plan!$B$5+IF(AND(N(Plan!$B$9)>0,N(B13)<=0),Plan!$D$9,0)+IF(AND(N(Plan!$B$10)>0,N(C13)<=0),Plan!$D$10,0)+IF(AND(N(Plan!$B$11)>0,N(D13)<=0),Plan!$D$11,0)+IF(AND(N(Plan!$B$12)>0,N(E13)<=0),Plan!$D$12,0)+IF(AND(N(Plan!$B$13)>0,N(F13)<=0),Plan!$D$13,0)+IF(AND(N(Plan!$B$14)>0,N(G13)<=0),Plan!$D$14,0)+IF(AND(N(Plan!$B$15)>0,N(H13)<=0),Plan!$D$15,0)+IF(AND(N(Plan!$B$16)>0,N(I13)<=0),Plan!$D$16,0)+IF(AND(N(Plan!$B$17)>0,N(J13)<=0),Plan!$D$17,0)+IF(AND(N(Plan!$B$18)>0,N(K13)<=0),Plan!$D$18,0),0)))+IF(N(C13)<=0,0,MIN(C13*(1+Plan!$C$10/12),Plan!$D$10+IF(Plan!$E$10=$L14,Plan!$B$5+IF(AND(N(Plan!$B$9)>0,N(B13)<=0),Plan!$D$9,0)+IF(AND(N(Plan!$B$10)>0,N(C13)<=0),Plan!$D$10,0)+IF(AND(N(Plan!$B$11)>0,N(D13)<=0),Plan!$D$11,0)+IF(AND(N(Plan!$B$12)>0,N(E13)<=0),Plan!$D$12,0)+IF(AND(N(Plan!$B$13)>0,N(F13)<=0),Plan!$D$13,0)+IF(AND(N(Plan!$B$14)>0,N(G13)<=0),Plan!$D$14,0)+IF(AND(N(Plan!$B$15)>0,N(H13)<=0),Plan!$D$15,0)+IF(AND(N(Plan!$B$16)>0,N(I13)<=0),Plan!$D$16,0)+IF(AND(N(Plan!$B$17)>0,N(J13)<=0),Plan!$D$17,0)+IF(AND(N(Plan!$B$18)>0,N(K13)<=0),Plan!$D$18,0),0)))+IF(N(D13)<=0,0,MIN(D13*(1+Plan!$C$11/12),Plan!$D$11+IF(Plan!$E$11=$L14,Plan!$B$5+IF(AND(N(Plan!$B$9)>0,N(B13)<=0),Plan!$D$9,0)+IF(AND(N(Plan!$B$10)>0,N(C13)<=0),Plan!$D$10,0)+IF(AND(N(Plan!$B$11)>0,N(D13)<=0),Plan!$D$11,0)+IF(AND(N(Plan!$B$12)>0,N(E13)<=0),Plan!$D$12,0)+IF(AND(N(Plan!$B$13)>0,N(F13)<=0),Plan!$D$13,0)+IF(AND(N(Plan!$B$14)>0,N(G13)<=0),Plan!$D$14,0)+IF(AND(N(Plan!$B$15)>0,N(H13)<=0),Plan!$D$15,0)+IF(AND(N(Plan!$B$16)>0,N(I13)<=0),Plan!$D$16,0)+IF(AND(N(Plan!$B$17)>0,N(J13)<=0),Plan!$D$17,0)+IF(AND(N(Plan!$B$18)>0,N(K13)<=0),Plan!$D$18,0),0)))+IF(N(E13)<=0,0,MIN(E13*(1+Plan!$C$12/12),Plan!$D$12+IF(Plan!$E$12=$L14,Plan!$B$5+IF(AND(N(Plan!$B$9)>0,N(B13)<=0),Plan!$D$9,0)+IF(AND(N(Plan!$B$10)>0,N(C13)<=0),Plan!$D$10,0)+IF(AND(N(Plan!$B$11)>0,N(D13)<=0),Plan!$D$11,0)+IF(AND(N(Plan!$B$12)>0,N(E13)<=0),Plan!$D$12,0)+IF(AND(N(Plan!$B$13)>0,N(F13)<=0),Plan!$D$13,0)+IF(AND(N(Plan!$B$14)>0,N(G13)<=0),Plan!$D$14,0)+IF(AND(N(Plan!$B$15)>0,N(H13)<=0),Plan!$D$15,0)+IF(AND(N(Plan!$B$16)>0,N(I13)<=0),Plan!$D$16,0)+IF(AND(N(Plan!$B$17)>0,N(J13)<=0),Plan!$D$17,0)+IF(AND(N(Plan!$B$18)>0,N(K13)<=0),Plan!$D$18,0),0)))+IF(N(F13)<=0,0,MIN(F13*(1+Plan!$C$13/12),Plan!$D$13+IF(Plan!$E$13=$L14,Plan!$B$5+IF(AND(N(Plan!$B$9)>0,N(B13)<=0),Plan!$D$9,0)+IF(AND(N(Plan!$B$10)>0,N(C13)<=0),Plan!$D$10,0)+IF(AND(N(Plan!$B$11)>0,N(D13)<=0),Plan!$D$11,0)+IF(AND(N(Plan!$B$12)>0,N(E13)<=0),Plan!$D$12,0)+IF(AND(N(Plan!$B$13)>0,N(F13)<=0),Plan!$D$13,0)+IF(AND(N(Plan!$B$14)>0,N(G13)<=0),Plan!$D$14,0)+IF(AND(N(Plan!$B$15)>0,N(H13)<=0),Plan!$D$15,0)+IF(AND(N(Plan!$B$16)>0,N(I13)<=0),Plan!$D$16,0)+IF(AND(N(Plan!$B$17)>0,N(J13)<=0),Plan!$D$17,0)+IF(AND(N(Plan!$B$18)>0,N(K13)<=0),Plan!$D$18,0),0)))+IF(N(G13)<=0,0,MIN(G13*(1+Plan!$C$14/12),Plan!$D$14+IF(Plan!$E$14=$L14,Plan!$B$5+IF(AND(N(Plan!$B$9)>0,N(B13)<=0),Plan!$D$9,0)+IF(AND(N(Plan!$B$10)>0,N(C13)<=0),Plan!$D$10,0)+IF(AND(N(Plan!$B$11)>0,N(D13)<=0),Plan!$D$11,0)+IF(AND(N(Plan!$B$12)>0,N(E13)<=0),Plan!$D$12,0)+IF(AND(N(Plan!$B$13)>0,N(F13)<=0),Plan!$D$13,0)+IF(AND(N(Plan!$B$14)>0,N(G13)<=0),Plan!$D$14,0)+IF(AND(N(Plan!$B$15)>0,N(H13)<=0),Plan!$D$15,0)+IF(AND(N(Plan!$B$16)>0,N(I13)<=0),Plan!$D$16,0)+IF(AND(N(Plan!$B$17)>0,N(J13)<=0),Plan!$D$17,0)+IF(AND(N(Plan!$B$18)>0,N(K13)<=0),Plan!$D$18,0),0)))+IF(N(H13)<=0,0,MIN(H13*(1+Plan!$C$15/12),Plan!$D$15+IF(Plan!$E$15=$L14,Plan!$B$5+IF(AND(N(Plan!$B$9)>0,N(B13)<=0),Plan!$D$9,0)+IF(AND(N(Plan!$B$10)>0,N(C13)<=0),Plan!$D$10,0)+IF(AND(N(Plan!$B$11)>0,N(D13)<=0),Plan!$D$11,0)+IF(AND(N(Plan!$B$12)>0,N(E13)<=0),Plan!$D$12,0)+IF(AND(N(Plan!$B$13)>0,N(F13)<=0),Plan!$D$13,0)+IF(AND(N(Plan!$B$14)>0,N(G13)<=0),Plan!$D$14,0)+IF(AND(N(Plan!$B$15)>0,N(H13)<=0),Plan!$D$15,0)+IF(AND(N(Plan!$B$16)>0,N(I13)<=0),Plan!$D$16,0)+IF(AND(N(Plan!$B$17)>0,N(J13)<=0),Plan!$D$17,0)+IF(AND(N(Plan!$B$18)>0,N(K13)<=0),Plan!$D$18,0),0)))+IF(N(I13)<=0,0,MIN(I13*(1+Plan!$C$16/12),Plan!$D$16+IF(Plan!$E$16=$L14,Plan!$B$5+IF(AND(N(Plan!$B$9)>0,N(B13)<=0),Plan!$D$9,0)+IF(AND(N(Plan!$B$10)>0,N(C13)<=0),Plan!$D$10,0)+IF(AND(N(Plan!$B$11)>0,N(D13)<=0),Plan!$D$11,0)+IF(AND(N(Plan!$B$12)>0,N(E13)<=0),Plan!$D$12,0)+IF(AND(N(Plan!$B$13)>0,N(F13)<=0),Plan!$D$13,0)+IF(AND(N(Plan!$B$14)>0,N(G13)<=0),Plan!$D$14,0)+IF(AND(N(Plan!$B$15)>0,N(H13)<=0),Plan!$D$15,0)+IF(AND(N(Plan!$B$16)>0,N(I13)<=0),Plan!$D$16,0)+IF(AND(N(Plan!$B$17)>0,N(J13)<=0),Plan!$D$17,0)+IF(AND(N(Plan!$B$18)>0,N(K13)<=0),Plan!$D$18,0),0)))+IF(N(J13)<=0,0,MIN(J13*(1+Plan!$C$17/12),Plan!$D$17+IF(Plan!$E$17=$L14,Plan!$B$5+IF(AND(N(Plan!$B$9)>0,N(B13)<=0),Plan!$D$9,0)+IF(AND(N(Plan!$B$10)>0,N(C13)<=0),Plan!$D$10,0)+IF(AND(N(Plan!$B$11)>0,N(D13)<=0),Plan!$D$11,0)+IF(AND(N(Plan!$B$12)>0,N(E13)<=0),Plan!$D$12,0)+IF(AND(N(Plan!$B$13)>0,N(F13)<=0),Plan!$D$13,0)+IF(AND(N(Plan!$B$14)>0,N(G13)<=0),Plan!$D$14,0)+IF(AND(N(Plan!$B$15)>0,N(H13)<=0),Plan!$D$15,0)+IF(AND(N(Plan!$B$16)>0,N(I13)<=0),Plan!$D$16,0)+IF(AND(N(Plan!$B$17)>0,N(J13)<=0),Plan!$D$17,0)+IF(AND(N(Plan!$B$18)>0,N(K13)<=0),Plan!$D$18,0),0)))+IF(N(K13)<=0,0,MIN(K13*(1+Plan!$C$18/12),Plan!$D$18+IF(Plan!$E$18=$L14,Plan!$B$5+IF(AND(N(Plan!$B$9)>0,N(B13)<=0),Plan!$D$9,0)+IF(AND(N(Plan!$B$10)>0,N(C13)<=0),Plan!$D$10,0)+IF(AND(N(Plan!$B$11)>0,N(D13)<=0),Plan!$D$11,0)+IF(AND(N(Plan!$B$12)>0,N(E13)<=0),Plan!$D$12,0)+IF(AND(N(Plan!$B$13)>0,N(F13)<=0),Plan!$D$13,0)+IF(AND(N(Plan!$B$14)>0,N(G13)<=0),Plan!$D$14,0)+IF(AND(N(Plan!$B$15)>0,N(H13)<=0),Plan!$D$15,0)+IF(AND(N(Plan!$B$16)>0,N(I13)<=0),Plan!$D$16,0)+IF(AND(N(Plan!$B$17)>0,N(J13)<=0),Plan!$D$17,0)+IF(AND(N(Plan!$B$18)>0,N(K13)<=0),Plan!$D$18,0),0)))
A15: 11 | B15: =IF(N(B14)<=0,0,MAX(0,B14*(1+Plan!$C$9/12)-(Plan!$D$9+IF(Plan!$E$9=$L15,Plan!$B$5+IF(AND(N(Plan!$B$9)>0,N(B14)<=0),Plan!$D$9,0)+IF(AND(N(Plan!$B$10)>0,N(C14)<=0),Plan!$D$10,0)+IF(AND(N(Plan!$B$11)>0,N(D14)<=0),Plan!$D$11,0)+IF(AND(N(Plan!$B$12)>0,N(E14)<=0),Plan!$D$12,0)+IF(AND(N(Plan!$B$13)>0,N(F14)<=0),Plan!$D$13,0)+IF(AND(N(Plan!$B$14)>0,N(G14)<=0),Plan!$D$14,0)+IF(AND(N(Plan!$B$15)>0,N(H14)<=0),Plan!$D$15,0)+IF(AND(N(Plan!$B$16)>0,N(I14)<=0),Plan!$D$16,0)+IF(AND(N(Plan!$B$17)>0,N(J14)<=0),Plan!$D$17,0)+IF(AND(N(Plan!$B$18)>0,N(K14)<=0),Plan!$D$18,0),0)))) | C15: =IF(N(C14)<=0,0,MAX(0,C14*(1+Plan!$C$10/12)-(Plan!$D$10+IF(Plan!$E$10=$L15,Plan!$B$5+IF(AND(N(Plan!$B$9)>0,N(B14)<=0),Plan!$D$9,0)+IF(AND(N(Plan!$B$10)>0,N(C14)<=0),Plan!$D$10,0)+IF(AND(N(Plan!$B$11)>0,N(D14)<=0),Plan!$D$11,0)+IF(AND(N(Plan!$B$12)>0,N(E14)<=0),Plan!$D$12,0)+IF(AND(N(Plan!$B$13)>0,N(F14)<=0),Plan!$D$13,0)+IF(AND(N(Plan!$B$14)>0,N(G14)<=0),Plan!$D$14,0)+IF(AND(N(Plan!$B$15)>0,N(H14)<=0),Plan!$D$15,0)+IF(AND(N(Plan!$B$16)>0,N(I14)<=0),Plan!$D$16,0)+IF(AND(N(Plan!$B$17)>0,N(J14)<=0),Plan!$D$17,0)+IF(AND(N(Plan!$B$18)>0,N(K14)<=0),Plan!$D$18,0),0)))) | D15: =IF(N(D14)<=0,0,MAX(0,D14*(1+Plan!$C$11/12)-(Plan!$D$11+IF(Plan!$E$11=$L15,Plan!$B$5+IF(AND(N(Plan!$B$9)>0,N(B14)<=0),Plan!$D$9,0)+IF(AND(N(Plan!$B$10)>0,N(C14)<=0),Plan!$D$10,0)+IF(AND(N(Plan!$B$11)>0,N(D14)<=0),Plan!$D$11,0)+IF(AND(N(Plan!$B$12)>0,N(E14)<=0),Plan!$D$12,0)+IF(AND(N(Plan!$B$13)>0,N(F14)<=0),Plan!$D$13,0)+IF(AND(N(Plan!$B$14)>0,N(G14)<=0),Plan!$D$14,0)+IF(AND(N(Plan!$B$15)>0,N(H14)<=0),Plan!$D$15,0)+IF(AND(N(Plan!$B$16)>0,N(I14)<=0),Plan!$D$16,0)+IF(AND(N(Plan!$B$17)>0,N(J14)<=0),Plan!$D$17,0)+IF(AND(N(Plan!$B$18)>0,N(K14)<=0),Plan!$D$18,0),0)))) | E15: =IF(N(E14)<=0,0,MAX(0,E14*(1+Plan!$C$12/12)-(Plan!$D$12+IF(Plan!$E$12=$L15,Plan!$B$5+IF(AND(N(Plan!$B$9)>0,N(B14)<=0),Plan!$D$9,0)+IF(AND(N(Plan!$B$10)>0,N(C14)<=0),Plan!$D$10,0)+IF(AND(N(Plan!$B$11)>0,N(D14)<=0),Plan!$D$11,0)+IF(AND(N(Plan!$B$12)>0,N(E14)<=0),Plan!$D$12,0)+IF(AND(N(Plan!$B$13)>0,N(F14)<=0),Plan!$D$13,0)+IF(AND(N(Plan!$B$14)>0,N(G14)<=0),Plan!$D$14,0)+IF(AND(N(Plan!$B$15)>0,N(H14)<=0),Plan!$D$15,0)+IF(AND(N(Plan!$B$16)>0,N(I14)<=0),Plan!$D$16,0)+IF(AND(N(Plan!$B$17)>0,N(J14)<=0),Plan!$D$17,0)+IF(AND(N(Plan!$B$18)>0,N(K14)<=0),Plan!$D$18,0),0)))) | F15: =IF(N(F14)<=0,0,MAX(0,F14*(1+Plan!$C$13/12)-(Plan!$D$13+IF(Plan!$E$13=$L15,Plan!$B$5+IF(AND(N(Plan!$B$9)>0,N(B14)<=0),Plan!$D$9,0)+IF(AND(N(Plan!$B$10)>0,N(C14)<=0),Plan!$D$10,0)+IF(AND(N(Plan!$B$11)>0,N(D14)<=0),Plan!$D$11,0)+IF(AND(N(Plan!$B$12)>0,N(E14)<=0),Plan!$D$12,0)+IF(AND(N(Plan!$B$13)>0,N(F14)<=0),Plan!$D$13,0)+IF(AND(N(Plan!$B$14)>0,N(G14)<=0),Plan!$D$14,0)+IF(AND(N(Plan!$B$15)>0,N(H14)<=0),Plan!$D$15,0)+IF(AND(N(Plan!$B$16)>0,N(I14)<=0),Plan!$D$16,0)+IF(AND(N(Plan!$B$17)>0,N(J14)<=0),Plan!$D$17,0)+IF(AND(N(Plan!$B$18)>0,N(K14)<=0),Plan!$D$18,0),0)))) | G15: =IF(N(G14)<=0,0,MAX(0,G14*(1+Plan!$C$14/12)-(Plan!$D$14+IF(Plan!$E$14=$L15,Plan!$B$5+IF(AND(N(Plan!$B$9)>0,N(B14)<=0),Plan!$D$9,0)+IF(AND(N(Plan!$B$10)>0,N(C14)<=0),Plan!$D$10,0)+IF(AND(N(Plan!$B$11)>0,N(D14)<=0),Plan!$D$11,0)+IF(AND(N(Plan!$B$12)>0,N(E14)<=0),Plan!$D$12,0)+IF(AND(N(Plan!$B$13)>0,N(F14)<=0),Plan!$D$13,0)+IF(AND(N(Plan!$B$14)>0,N(G14)<=0),Plan!$D$14,0)+IF(AND(N(Plan!$B$15)>0,N(H14)<=0),Plan!$D$15,0)+IF(AND(N(Plan!$B$16)>0,N(I14)<=0),Plan!$D$16,0)+IF(AND(N(Plan!$B$17)>0,N(J14)<=0),Plan!$D$17,0)+IF(AND(N(Plan!$B$18)>0,N(K14)<=0),Plan!$D$18,0),0)))) | H15: =IF(N(H14)<=0,0,MAX(0,H14*(1+Plan!$C$15/12)-(Plan!$D$15+IF(Plan!$E$15=$L15,Plan!$B$5+IF(AND(N(Plan!$B$9)>0,N(B14)<=0),Plan!$D$9,0)+IF(AND(N(Plan!$B$10)>0,N(C14)<=0),Plan!$D$10,0)+IF(AND(N(Plan!$B$11)>0,N(D14)<=0),Plan!$D$11,0)+IF(AND(N(Plan!$B$12)>0,N(E14)<=0),Plan!$D$12,0)+IF(AND(N(Plan!$B$13)>0,N(F14)<=0),Plan!$D$13,0)+IF(AND(N(Plan!$B$14)>0,N(G14)<=0),Plan!$D$14,0)+IF(AND(N(Plan!$B$15)>0,N(H14)<=0),Plan!$D$15,0)+IF(AND(N(Plan!$B$16)>0,N(I14)<=0),Plan!$D$16,0)+IF(AND(N(Plan!$B$17)>0,N(J14)<=0),Plan!$D$17,0)+IF(AND(N(Plan!$B$18)>0,N(K14)<=0),Plan!$D$18,0),0)))) | I15: =IF(N(I14)<=0,0,MAX(0,I14*(1+Plan!$C$16/12)-(Plan!$D$16+IF(Plan!$E$16=$L15,Plan!$B$5+IF(AND(N(Plan!$B$9)>0,N(B14)<=0),Plan!$D$9,0)+IF(AND(N(Plan!$B$10)>0,N(C14)<=0),Plan!$D$10,0)+IF(AND(N(Plan!$B$11)>0,N(D14)<=0),Plan!$D$11,0)+IF(AND(N(Plan!$B$12)>0,N(E14)<=0),Plan!$D$12,0)+IF(AND(N(Plan!$B$13)>0,N(F14)<=0),Plan!$D$13,0)+IF(AND(N(Plan!$B$14)>0,N(G14)<=0),Plan!$D$14,0)+IF(AND(N(Plan!$B$15)>0,N(H14)<=0),Plan!$D$15,0)+IF(AND(N(Plan!$B$16)>0,N(I14)<=0),Plan!$D$16,0)+IF(AND(N(Plan!$B$17)>0,N(J14)<=0),Plan!$D$17,0)+IF(AND(N(Plan!$B$18)>0,N(K14)<=0),Plan!$D$18,0),0)))) | J15: =IF(N(J14)<=0,0,MAX(0,J14*(1+Plan!$C$17/12)-(Plan!$D$17+IF(Plan!$E$17=$L15,Plan!$B$5+IF(AND(N(Plan!$B$9)>0,N(B14)<=0),Plan!$D$9,0)+IF(AND(N(Plan!$B$10)>0,N(C14)<=0),Plan!$D$10,0)+IF(AND(N(Plan!$B$11)>0,N(D14)<=0),Plan!$D$11,0)+IF(AND(N(Plan!$B$12)>0,N(E14)<=0),Plan!$D$12,0)+IF(AND(N(Plan!$B$13)>0,N(F14)<=0),Plan!$D$13,0)+IF(AND(N(Plan!$B$14)>0,N(G14)<=0),Plan!$D$14,0)+IF(AND(N(Plan!$B$15)>0,N(H14)<=0),Plan!$D$15,0)+IF(AND(N(Plan!$B$16)>0,N(I14)<=0),Plan!$D$16,0)+IF(AND(N(Plan!$B$17)>0,N(J14)<=0),Plan!$D$17,0)+IF(AND(N(Plan!$B$18)>0,N(K14)<=0),Plan!$D$18,0),0)))) | K15: =IF(N(K14)<=0,0,MAX(0,K14*(1+Plan!$C$18/12)-(Plan!$D$18+IF(Plan!$E$18=$L15,Plan!$B$5+IF(AND(N(Plan!$B$9)>0,N(B14)<=0),Plan!$D$9,0)+IF(AND(N(Plan!$B$10)>0,N(C14)<=0),Plan!$D$10,0)+IF(AND(N(Plan!$B$11)>0,N(D14)<=0),Plan!$D$11,0)+IF(AND(N(Plan!$B$12)>0,N(E14)<=0),Plan!$D$12,0)+IF(AND(N(Plan!$B$13)>0,N(F14)<=0),Plan!$D$13,0)+IF(AND(N(Plan!$B$14)>0,N(G14)<=0),Plan!$D$14,0)+IF(AND(N(Plan!$B$15)>0,N(H14)<=0),Plan!$D$15,0)+IF(AND(N(Plan!$B$16)>0,N(I14)<=0),Plan!$D$16,0)+IF(AND(N(Plan!$B$17)>0,N(J14)<=0),Plan!$D$17,0)+IF(AND(N(Plan!$B$18)>0,N(K14)<=0),Plan!$D$18,0),0)))) | L15: =MIN(IF(N(B14)>0,Plan!$E$9,999),IF(N(C14)>0,Plan!$E$10,999),IF(N(D14)>0,Plan!$E$11,999),IF(N(E14)>0,Plan!$E$12,999),IF(N(F14)>0,Plan!$E$13,999),IF(N(G14)>0,Plan!$E$14,999),IF(N(H14)>0,Plan!$E$15,999),IF(N(I14)>0,Plan!$E$16,999),IF(N(J14)>0,Plan!$E$17,999),IF(N(K14)>0,Plan!$E$18,999)) | M15: =IF(N(B14)<=0,0,MIN(B14*(1+Plan!$C$9/12),Plan!$D$9+IF(Plan!$E$9=$L15,Plan!$B$5+IF(AND(N(Plan!$B$9)>0,N(B14)<=0),Plan!$D$9,0)+IF(AND(N(Plan!$B$10)>0,N(C14)<=0),Plan!$D$10,0)+IF(AND(N(Plan!$B$11)>0,N(D14)<=0),Plan!$D$11,0)+IF(AND(N(Plan!$B$12)>0,N(E14)<=0),Plan!$D$12,0)+IF(AND(N(Plan!$B$13)>0,N(F14)<=0),Plan!$D$13,0)+IF(AND(N(Plan!$B$14)>0,N(G14)<=0),Plan!$D$14,0)+IF(AND(N(Plan!$B$15)>0,N(H14)<=0),Plan!$D$15,0)+IF(AND(N(Plan!$B$16)>0,N(I14)<=0),Plan!$D$16,0)+IF(AND(N(Plan!$B$17)>0,N(J14)<=0),Plan!$D$17,0)+IF(AND(N(Plan!$B$18)>0,N(K14)<=0),Plan!$D$18,0),0)))+IF(N(C14)<=0,0,MIN(C14*(1+Plan!$C$10/12),Plan!$D$10+IF(Plan!$E$10=$L15,Plan!$B$5+IF(AND(N(Plan!$B$9)>0,N(B14)<=0),Plan!$D$9,0)+IF(AND(N(Plan!$B$10)>0,N(C14)<=0),Plan!$D$10,0)+IF(AND(N(Plan!$B$11)>0,N(D14)<=0),Plan!$D$11,0)+IF(AND(N(Plan!$B$12)>0,N(E14)<=0),Plan!$D$12,0)+IF(AND(N(Plan!$B$13)>0,N(F14)<=0),Plan!$D$13,0)+IF(AND(N(Plan!$B$14)>0,N(G14)<=0),Plan!$D$14,0)+IF(AND(N(Plan!$B$15)>0,N(H14)<=0),Plan!$D$15,0)+IF(AND(N(Plan!$B$16)>0,N(I14)<=0),Plan!$D$16,0)+IF(AND(N(Plan!$B$17)>0,N(J14)<=0),Plan!$D$17,0)+IF(AND(N(Plan!$B$18)>0,N(K14)<=0),Plan!$D$18,0),0)))+IF(N(D14)<=0,0,MIN(D14*(1+Plan!$C$11/12),Plan!$D$11+IF(Plan!$E$11=$L15,Plan!$B$5+IF(AND(N(Plan!$B$9)>0,N(B14)<=0),Plan!$D$9,0)+IF(AND(N(Plan!$B$10)>0,N(C14)<=0),Plan!$D$10,0)+IF(AND(N(Plan!$B$11)>0,N(D14)<=0),Plan!$D$11,0)+IF(AND(N(Plan!$B$12)>0,N(E14)<=0),Plan!$D$12,0)+IF(AND(N(Plan!$B$13)>0,N(F14)<=0),Plan!$D$13,0)+IF(AND(N(Plan!$B$14)>0,N(G14)<=0),Plan!$D$14,0)+IF(AND(N(Plan!$B$15)>0,N(H14)<=0),Plan!$D$15,0)+IF(AND(N(Plan!$B$16)>0,N(I14)<=0),Plan!$D$16,0)+IF(AND(N(Plan!$B$17)>0,N(J14)<=0),Plan!$D$17,0)+IF(AND(N(Plan!$B$18)>0,N(K14)<=0),Plan!$D$18,0),0)))+IF(N(E14)<=0,0,MIN(E14*(1+Plan!$C$12/12),Plan!$D$12+IF(Plan!$E$12=$L15,Plan!$B$5+IF(AND(N(Plan!$B$9)>0,N(B14)<=0),Plan!$D$9,0)+IF(AND(N(Plan!$B$10)>0,N(C14)<=0),Plan!$D$10,0)+IF(AND(N(Plan!$B$11)>0,N(D14)<=0),Plan!$D$11,0)+IF(AND(N(Plan!$B$12)>0,N(E14)<=0),Plan!$D$12,0)+IF(AND(N(Plan!$B$13)>0,N(F14)<=0),Plan!$D$13,0)+IF(AND(N(Plan!$B$14)>0,N(G14)<=0),Plan!$D$14,0)+IF(AND(N(Plan!$B$15)>0,N(H14)<=0),Plan!$D$15,0)+IF(AND(N(Plan!$B$16)>0,N(I14)<=0),Plan!$D$16,0)+IF(AND(N(Plan!$B$17)>0,N(J14)<=0),Plan!$D$17,0)+IF(AND(N(Plan!$B$18)>0,N(K14)<=0),Plan!$D$18,0),0)))+IF(N(F14)<=0,0,MIN(F14*(1+Plan!$C$13/12),Plan!$D$13+IF(Plan!$E$13=$L15,Plan!$B$5+IF(AND(N(Plan!$B$9)>0,N(B14)<=0),Plan!$D$9,0)+IF(AND(N(Plan!$B$10)>0,N(C14)<=0),Plan!$D$10,0)+IF(AND(N(Plan!$B$11)>0,N(D14)<=0),Plan!$D$11,0)+IF(AND(N(Plan!$B$12)>0,N(E14)<=0),Plan!$D$12,0)+IF(AND(N(Plan!$B$13)>0,N(F14)<=0),Plan!$D$13,0)+IF(AND(N(Plan!$B$14)>0,N(G14)<=0),Plan!$D$14,0)+IF(AND(N(Plan!$B$15)>0,N(H14)<=0),Plan!$D$15,0)+IF(AND(N(Plan!$B$16)>0,N(I14)<=0),Plan!$D$16,0)+IF(AND(N(Plan!$B$17)>0,N(J14)<=0),Plan!$D$17,0)+IF(AND(N(Plan!$B$18)>0,N(K14)<=0),Plan!$D$18,0),0)))+IF(N(G14)<=0,0,MIN(G14*(1+Plan!$C$14/12),Plan!$D$14+IF(Plan!$E$14=$L15,Plan!$B$5+IF(AND(N(Plan!$B$9)>0,N(B14)<=0),Plan!$D$9,0)+IF(AND(N(Plan!$B$10)>0,N(C14)<=0),Plan!$D$10,0)+IF(AND(N(Plan!$B$11)>0,N(D14)<=0),Plan!$D$11,0)+IF(AND(N(Plan!$B$12)>0,N(E14)<=0),Plan!$D$12,0)+IF(AND(N(Plan!$B$13)>0,N(F14)<=0),Plan!$D$13,0)+IF(AND(N(Plan!$B$14)>0,N(G14)<=0),Plan!$D$14,0)+IF(AND(N(Plan!$B$15)>0,N(H14)<=0),Plan!$D$15,0)+IF(AND(N(Plan!$B$16)>0,N(I14)<=0),Plan!$D$16,0)+IF(AND(N(Plan!$B$17)>0,N(J14)<=0),Plan!$D$17,0)+IF(AND(N(Plan!$B$18)>0,N(K14)<=0),Plan!$D$18,0),0)))+IF(N(H14)<=0,0,MIN(H14*(1+Plan!$C$15/12),Plan!$D$15+IF(Plan!$E$15=$L15,Plan!$B$5+IF(AND(N(Plan!$B$9)>0,N(B14)<=0),Plan!$D$9,0)+IF(AND(N(Plan!$B$10)>0,N(C14)<=0),Plan!$D$10,0)+IF(AND(N(Plan!$B$11)>0,N(D14)<=0),Plan!$D$11,0)+IF(AND(N(Plan!$B$12)>0,N(E14)<=0),Plan!$D$12,0)+IF(AND(N(Plan!$B$13)>0,N(F14)<=0),Plan!$D$13,0)+IF(AND(N(Plan!$B$14)>0,N(G14)<=0),Plan!$D$14,0)+IF(AND(N(Plan!$B$15)>0,N(H14)<=0),Plan!$D$15,0)+IF(AND(N(Plan!$B$16)>0,N(I14)<=0),Plan!$D$16,0)+IF(AND(N(Plan!$B$17)>0,N(J14)<=0),Plan!$D$17,0)+IF(AND(N(Plan!$B$18)>0,N(K14)<=0),Plan!$D$18,0),0)))+IF(N(I14)<=0,0,MIN(I14*(1+Plan!$C$16/12),Plan!$D$16+IF(Plan!$E$16=$L15,Plan!$B$5+IF(AND(N(Plan!$B$9)>0,N(B14)<=0),Plan!$D$9,0)+IF(AND(N(Plan!$B$10)>0,N(C14)<=0),Plan!$D$10,0)+IF(AND(N(Plan!$B$11)>0,N(D14)<=0),Plan!$D$11,0)+IF(AND(N(Plan!$B$12)>0,N(E14)<=0),Plan!$D$12,0)+IF(AND(N(Plan!$B$13)>0,N(F14)<=0),Plan!$D$13,0)+IF(AND(N(Plan!$B$14)>0,N(G14)<=0),Plan!$D$14,0)+IF(AND(N(Plan!$B$15)>0,N(H14)<=0),Plan!$D$15,0)+IF(AND(N(Plan!$B$16)>0,N(I14)<=0),Plan!$D$16,0)+IF(AND(N(Plan!$B$17)>0,N(J14)<=0),Plan!$D$17,0)+IF(AND(N(Plan!$B$18)>0,N(K14)<=0),Plan!$D$18,0),0)))+IF(N(J14)<=0,0,MIN(J14*(1+Plan!$C$17/12),Plan!$D$17+IF(Plan!$E$17=$L15,Plan!$B$5+IF(AND(N(Plan!$B$9)>0,N(B14)<=0),Plan!$D$9,0)+IF(AND(N(Plan!$B$10)>0,N(C14)<=0),Plan!$D$10,0)+IF(AND(N(Plan!$B$11)>0,N(D14)<=0),Plan!$D$11,0)+IF(AND(N(Plan!$B$12)>0,N(E14)<=0),Plan!$D$12,0)+IF(AND(N(Plan!$B$13)>0,N(F14)<=0),Plan!$D$13,0)+IF(AND(N(Plan!$B$14)>0,N(G14)<=0),Plan!$D$14,0)+IF(AND(N(Plan!$B$15)>0,N(H14)<=0),Plan!$D$15,0)+IF(AND(N(Plan!$B$16)>0,N(I14)<=0),Plan!$D$16,0)+IF(AND(N(Plan!$B$17)>0,N(J14)<=0),Plan!$D$17,0)+IF(AND(N(Plan!$B$18)>0,N(K14)<=0),Plan!$D$18,0),0)))+IF(N(K14)<=0,0,MIN(K14*(1+Plan!$C$18/12),Plan!$D$18+IF(Plan!$E$18=$L15,Plan!$B$5+IF(AND(N(Plan!$B$9)>0,N(B14)<=0),Plan!$D$9,0)+IF(AND(N(Plan!$B$10)>0,N(C14)<=0),Plan!$D$10,0)+IF(AND(N(Plan!$B$11)>0,N(D14)<=0),Plan!$D$11,0)+IF(AND(N(Plan!$B$12)>0,N(E14)<=0),Plan!$D$12,0)+IF(AND(N(Plan!$B$13)>0,N(F14)<=0),Plan!$D$13,0)+IF(AND(N(Plan!$B$14)>0,N(G14)<=0),Plan!$D$14,0)+IF(AND(N(Plan!$B$15)>0,N(H14)<=0),Plan!$D$15,0)+IF(AND(N(Plan!$B$16)>0,N(I14)<=0),Plan!$D$16,0)+IF(AND(N(Plan!$B$17)>0,N(J14)<=0),Plan!$D$17,0)+IF(AND(N(Plan!$B$18)>0,N(K14)<=0),Plan!$D$18,0),0)))
A16: 12 | B16: =IF(N(B15)<=0,0,MAX(0,B15*(1+Plan!$C$9/12)-(Plan!$D$9+IF(Plan!$E$9=$L16,Plan!$B$5+IF(AND(N(Plan!$B$9)>0,N(B15)<=0),Plan!$D$9,0)+IF(AND(N(Plan!$B$10)>0,N(C15)<=0),Plan!$D$10,0)+IF(AND(N(Plan!$B$11)>0,N(D15)<=0),Plan!$D$11,0)+IF(AND(N(Plan!$B$12)>0,N(E15)<=0),Plan!$D$12,0)+IF(AND(N(Plan!$B$13)>0,N(F15)<=0),Plan!$D$13,0)+IF(AND(N(Plan!$B$14)>0,N(G15)<=0),Plan!$D$14,0)+IF(AND(N(Plan!$B$15)>0,N(H15)<=0),Plan!$D$15,0)+IF(AND(N(Plan!$B$16)>0,N(I15)<=0),Plan!$D$16,0)+IF(AND(N(Plan!$B$17)>0,N(J15)<=0),Plan!$D$17,0)+IF(AND(N(Plan!$B$18)>0,N(K15)<=0),Plan!$D$18,0),0)))) | C16: =IF(N(C15)<=0,0,MAX(0,C15*(1+Plan!$C$10/12)-(Plan!$D$10+IF(Plan!$E$10=$L16,Plan!$B$5+IF(AND(N(Plan!$B$9)>0,N(B15)<=0),Plan!$D$9,0)+IF(AND(N(Plan!$B$10)>0,N(C15)<=0),Plan!$D$10,0)+IF(AND(N(Plan!$B$11)>0,N(D15)<=0),Plan!$D$11,0)+IF(AND(N(Plan!$B$12)>0,N(E15)<=0),Plan!$D$12,0)+IF(AND(N(Plan!$B$13)>0,N(F15)<=0),Plan!$D$13,0)+IF(AND(N(Plan!$B$14)>0,N(G15)<=0),Plan!$D$14,0)+IF(AND(N(Plan!$B$15)>0,N(H15)<=0),Plan!$D$15,0)+IF(AND(N(Plan!$B$16)>0,N(I15)<=0),Plan!$D$16,0)+IF(AND(N(Plan!$B$17)>0,N(J15)<=0),Plan!$D$17,0)+IF(AND(N(Plan!$B$18)>0,N(K15)<=0),Plan!$D$18,0),0)))) | D16: =IF(N(D15)<=0,0,MAX(0,D15*(1+Plan!$C$11/12)-(Plan!$D$11+IF(Plan!$E$11=$L16,Plan!$B$5+IF(AND(N(Plan!$B$9)>0,N(B15)<=0),Plan!$D$9,0)+IF(AND(N(Plan!$B$10)>0,N(C15)<=0),Plan!$D$10,0)+IF(AND(N(Plan!$B$11)>0,N(D15)<=0),Plan!$D$11,0)+IF(AND(N(Plan!$B$12)>0,N(E15)<=0),Plan!$D$12,0)+IF(AND(N(Plan!$B$13)>0,N(F15)<=0),Plan!$D$13,0)+IF(AND(N(Plan!$B$14)>0,N(G15)<=0),Plan!$D$14,0)+IF(AND(N(Plan!$B$15)>0,N(H15)<=0),Plan!$D$15,0)+IF(AND(N(Plan!$B$16)>0,N(I15)<=0),Plan!$D$16,0)+IF(AND(N(Plan!$B$17)>0,N(J15)<=0),Plan!$D$17,0)+IF(AND(N(Plan!$B$18)>0,N(K15)<=0),Plan!$D$18,0),0)))) | E16: =IF(N(E15)<=0,0,MAX(0,E15*(1+Plan!$C$12/12)-(Plan!$D$12+IF(Plan!$E$12=$L16,Plan!$B$5+IF(AND(N(Plan!$B$9)>0,N(B15)<=0),Plan!$D$9,0)+IF(AND(N(Plan!$B$10)>0,N(C15)<=0),Plan!$D$10,0)+IF(AND(N(Plan!$B$11)>0,N(D15)<=0),Plan!$D$11,0)+IF(AND(N(Plan!$B$12)>0,N(E15)<=0),Plan!$D$12,0)+IF(AND(N(Plan!$B$13)>0,N(F15)<=0),Plan!$D$13,0)+IF(AND(N(Plan!$B$14)>0,N(G15)<=0),Plan!$D$14,0)+IF(AND(N(Plan!$B$15)>0,N(H15)<=0),Plan!$D$15,0)+IF(AND(N(Plan!$B$16)>0,N(I15)<=0),Plan!$D$16,0)+IF(AND(N(Plan!$B$17)>0,N(J15)<=0),Plan!$D$17,0)+IF(AND(N(Plan!$B$18)>0,N(K15)<=0),Plan!$D$18,0),0)))) | F16: =IF(N(F15)<=0,0,MAX(0,F15*(1+Plan!$C$13/12)-(Plan!$D$13+IF(Plan!$E$13=$L16,Plan!$B$5+IF(AND(N(Plan!$B$9)>0,N(B15)<=0),Plan!$D$9,0)+IF(AND(N(Plan!$B$10)>0,N(C15)<=0),Plan!$D$10,0)+IF(AND(N(Plan!$B$11)>0,N(D15)<=0),Plan!$D$11,0)+IF(AND(N(Plan!$B$12)>0,N(E15)<=0),Plan!$D$12,0)+IF(AND(N(Plan!$B$13)>0,N(F15)<=0),Plan!$D$13,0)+IF(AND(N(Plan!$B$14)>0,N(G15)<=0),Plan!$D$14,0)+IF(AND(N(Plan!$B$15)>0,N(H15)<=0),Plan!$D$15,0)+IF(AND(N(Plan!$B$16)>0,N(I15)<=0),Plan!$D$16,0)+IF(AND(N(Plan!$B$17)>0,N(J15)<=0),Plan!$D$17,0)+IF(AND(N(Plan!$B$18)>0,N(K15)<=0),Plan!$D$18,0),0)))) | G16: =IF(N(G15)<=0,0,MAX(0,G15*(1+Plan!$C$14/12)-(Plan!$D$14+IF(Plan!$E$14=$L16,Plan!$B$5+IF(AND(N(Plan!$B$9)>0,N(B15)<=0),Plan!$D$9,0)+IF(AND(N(Plan!$B$10)>0,N(C15)<=0),Plan!$D$10,0)+IF(AND(N(Plan!$B$11)>0,N(D15)<=0),Plan!$D$11,0)+IF(AND(N(Plan!$B$12)>0,N(E15)<=0),Plan!$D$12,0)+IF(AND(N(Plan!$B$13)>0,N(F15)<=0),Plan!$D$13,0)+IF(AND(N(Plan!$B$14)>0,N(G15)<=0),Plan!$D$14,0)+IF(AND(N(Plan!$B$15)>0,N(H15)<=0),Plan!$D$15,0)+IF(AND(N(Plan!$B$16)>0,N(I15)<=0),Plan!$D$16,0)+IF(AND(N(Plan!$B$17)>0,N(J15)<=0),Plan!$D$17,0)+IF(AND(N(Plan!$B$18)>0,N(K15)<=0),Plan!$D$18,0),0)))) | H16: =IF(N(H15)<=0,0,MAX(0,H15*(1+Plan!$C$15/12)-(Plan!$D$15+IF(Plan!$E$15=$L16,Plan!$B$5+IF(AND(N(Plan!$B$9)>0,N(B15)<=0),Plan!$D$9,0)+IF(AND(N(Plan!$B$10)>0,N(C15)<=0),Plan!$D$10,0)+IF(AND(N(Plan!$B$11)>0,N(D15)<=0),Plan!$D$11,0)+IF(AND(N(Plan!$B$12)>0,N(E15)<=0),Plan!$D$12,0)+IF(AND(N(Plan!$B$13)>0,N(F15)<=0),Plan!$D$13,0)+IF(AND(N(Plan!$B$14)>0,N(G15)<=0),Plan!$D$14,0)+IF(AND(N(Plan!$B$15)>0,N(H15)<=0),Plan!$D$15,0)+IF(AND(N(Plan!$B$16)>0,N(I15)<=0),Plan!$D$16,0)+IF(AND(N(Plan!$B$17)>0,N(J15)<=0),Plan!$D$17,0)+IF(AND(N(Plan!$B$18)>0,N(K15)<=0),Plan!$D$18,0),0)))) | I16: =IF(N(I15)<=0,0,MAX(0,I15*(1+Plan!$C$16/12)-(Plan!$D$16+IF(Plan!$E$16=$L16,Plan!$B$5+IF(AND(N(Plan!$B$9)>0,N(B15)<=0),Plan!$D$9,0)+IF(AND(N(Plan!$B$10)>0,N(C15)<=0),Plan!$D$10,0)+IF(AND(N(Plan!$B$11)>0,N(D15)<=0),Plan!$D$11,0)+IF(AND(N(Plan!$B$12)>0,N(E15)<=0),Plan!$D$12,0)+IF(AND(N(Plan!$B$13)>0,N(F15)<=0),Plan!$D$13,0)+IF(AND(N(Plan!$B$14)>0,N(G15)<=0),Plan!$D$14,0)+IF(AND(N(Plan!$B$15)>0,N(H15)<=0),Plan!$D$15,0)+IF(AND(N(Plan!$B$16)>0,N(I15)<=0),Plan!$D$16,0)+IF(AND(N(Plan!$B$17)>0,N(J15)<=0),Plan!$D$17,0)+IF(AND(N(Plan!$B$18)>0,N(K15)<=0),Plan!$D$18,0),0)))) | J16: =IF(N(J15)<=0,0,MAX(0,J15*(1+Plan!$C$17/12)-(Plan!$D$17+IF(Plan!$E$17=$L16,Plan!$B$5+IF(AND(N(Plan!$B$9)>0,N(B15)<=0),Plan!$D$9,0)+IF(AND(N(Plan!$B$10)>0,N(C15)<=0),Plan!$D$10,0)+IF(AND(N(Plan!$B$11)>0,N(D15)<=0),Plan!$D$11,0)+IF(AND(N(Plan!$B$12)>0,N(E15)<=0),Plan!$D$12,0)+IF(AND(N(Plan!$B$13)>0,N(F15)<=0),Plan!$D$13,0)+IF(AND(N(Plan!$B$14)>0,N(G15)<=0),Plan!$D$14,0)+IF(AND(N(Plan!$B$15)>0,N(H15)<=0),Plan!$D$15,0)+IF(AND(N(Plan!$B$16)>0,N(I15)<=0),Plan!$D$16,0)+IF(AND(N(Plan!$B$17)>0,N(J15)<=0),Plan!$D$17,0)+IF(AND(N(Plan!$B$18)>0,N(K15)<=0),Plan!$D$18,0),0)))) | K16: =IF(N(K15)<=0,0,MAX(0,K15*(1+Plan!$C$18/12)-(Plan!$D$18+IF(Plan!$E$18=$L16,Plan!$B$5+IF(AND(N(Plan!$B$9)>0,N(B15)<=0),Plan!$D$9,0)+IF(AND(N(Plan!$B$10)>0,N(C15)<=0),Plan!$D$10,0)+IF(AND(N(Plan!$B$11)>0,N(D15)<=0),Plan!$D$11,0)+IF(AND(N(Plan!$B$12)>0,N(E15)<=0),Plan!$D$12,0)+IF(AND(N(Plan!$B$13)>0,N(F15)<=0),Plan!$D$13,0)+IF(AND(N(Plan!$B$14)>0,N(G15)<=0),Plan!$D$14,0)+IF(AND(N(Plan!$B$15)>0,N(H15)<=0),Plan!$D$15,0)+IF(AND(N(Plan!$B$16)>0,N(I15)<=0),Plan!$D$16,0)+IF(AND(N(Plan!$B$17)>0,N(J15)<=0),Plan!$D$17,0)+IF(AND(N(Plan!$B$18)>0,N(K15)<=0),Plan!$D$18,0),0)))) | L16: =MIN(IF(N(B15)>0,Plan!$E$9,999),IF(N(C15)>0,Plan!$E$10,999),IF(N(D15)>0,Plan!$E$11,999),IF(N(E15)>0,Plan!$E$12,999),IF(N(F15)>0,Plan!$E$13,999),IF(N(G15)>0,Plan!$E$14,999),IF(N(H15)>0,Plan!$E$15,999),IF(N(I15)>0,Plan!$E$16,999),IF(N(J15)>0,Plan!$E$17,999),IF(N(K15)>0,Plan!$E$18,999)) | M16: =IF(N(B15)<=0,0,MIN(B15*(1+Plan!$C$9/12),Plan!$D$9+IF(Plan!$E$9=$L16,Plan!$B$5+IF(AND(N(Plan!$B$9)>0,N(B15)<=0),Plan!$D$9,0)+IF(AND(N(Plan!$B$10)>0,N(C15)<=0),Plan!$D$10,0)+IF(AND(N(Plan!$B$11)>0,N(D15)<=0),Plan!$D$11,0)+IF(AND(N(Plan!$B$12)>0,N(E15)<=0),Plan!$D$12,0)+IF(AND(N(Plan!$B$13)>0,N(F15)<=0),Plan!$D$13,0)+IF(AND(N(Plan!$B$14)>0,N(G15)<=0),Plan!$D$14,0)+IF(AND(N(Plan!$B$15)>0,N(H15)<=0),Plan!$D$15,0)+IF(AND(N(Plan!$B$16)>0,N(I15)<=0),Plan!$D$16,0)+IF(AND(N(Plan!$B$17)>0,N(J15)<=0),Plan!$D$17,0)+IF(AND(N(Plan!$B$18)>0,N(K15)<=0),Plan!$D$18,0),0)))+IF(N(C15)<=0,0,MIN(C15*(1+Plan!$C$10/12),Plan!$D$10+IF(Plan!$E$10=$L16,Plan!$B$5+IF(AND(N(Plan!$B$9)>0,N(B15)<=0),Plan!$D$9,0)+IF(AND(N(Plan!$B$10)>0,N(C15)<=0),Plan!$D$10,0)+IF(AND(N(Plan!$B$11)>0,N(D15)<=0),Plan!$D$11,0)+IF(AND(N(Plan!$B$12)>0,N(E15)<=0),Plan!$D$12,0)+IF(AND(N(Plan!$B$13)>0,N(F15)<=0),Plan!$D$13,0)+IF(AND(N(Plan!$B$14)>0,N(G15)<=0),Plan!$D$14,0)+IF(AND(N(Plan!$B$15)>0,N(H15)<=0),Plan!$D$15,0)+IF(AND(N(Plan!$B$16)>0,N(I15)<=0),Plan!$D$16,0)+IF(AND(N(Plan!$B$17)>0,N(J15)<=0),Plan!$D$17,0)+IF(AND(N(Plan!$B$18)>0,N(K15)<=0),Plan!$D$18,0),0)))+IF(N(D15)<=0,0,MIN(D15*(1+Plan!$C$11/12),Plan!$D$11+IF(Plan!$E$11=$L16,Plan!$B$5+IF(AND(N(Plan!$B$9)>0,N(B15)<=0),Plan!$D$9,0)+IF(AND(N(Plan!$B$10)>0,N(C15)<=0),Plan!$D$10,0)+IF(AND(N(Plan!$B$11)>0,N(D15)<=0),Plan!$D$11,0)+IF(AND(N(Plan!$B$12)>0,N(E15)<=0),Plan!$D$12,0)+IF(AND(N(Plan!$B$13)>0,N(F15)<=0),Plan!$D$13,0)+IF(AND(N(Plan!$B$14)>0,N(G15)<=0),Plan!$D$14,0)+IF(AND(N(Plan!$B$15)>0,N(H15)<=0),Plan!$D$15,0)+IF(AND(N(Plan!$B$16)>0,N(I15)<=0),Plan!$D$16,0)+IF(AND(N(Plan!$B$17)>0,N(J15)<=0),Plan!$D$17,0)+IF(AND(N(Plan!$B$18)>0,N(K15)<=0),Plan!$D$18,0),0)))+IF(N(E15)<=0,0,MIN(E15*(1+Plan!$C$12/12),Plan!$D$12+IF(Plan!$E$12=$L16,Plan!$B$5+IF(AND(N(Plan!$B$9)>0,N(B15)<=0),Plan!$D$9,0)+IF(AND(N(Plan!$B$10)>0,N(C15)<=0),Plan!$D$10,0)+IF(AND(N(Plan!$B$11)>0,N(D15)<=0),Plan!$D$11,0)+IF(AND(N(Plan!$B$12)>0,N(E15)<=0),Plan!$D$12,0)+IF(AND(N(Plan!$B$13)>0,N(F15)<=0),Plan!$D$13,0)+IF(AND(N(Plan!$B$14)>0,N(G15)<=0),Plan!$D$14,0)+IF(AND(N(Plan!$B$15)>0,N(H15)<=0),Plan!$D$15,0)+IF(AND(N(Plan!$B$16)>0,N(I15)<=0),Plan!$D$16,0)+IF(AND(N(Plan!$B$17)>0,N(J15)<=0),Plan!$D$17,0)+IF(AND(N(Plan!$B$18)>0,N(K15)<=0),Plan!$D$18,0),0)))+IF(N(F15)<=0,0,MIN(F15*(1+Plan!$C$13/12),Plan!$D$13+IF(Plan!$E$13=$L16,Plan!$B$5+IF(AND(N(Plan!$B$9)>0,N(B15)<=0),Plan!$D$9,0)+IF(AND(N(Plan!$B$10)>0,N(C15)<=0),Plan!$D$10,0)+IF(AND(N(Plan!$B$11)>0,N(D15)<=0),Plan!$D$11,0)+IF(AND(N(Plan!$B$12)>0,N(E15)<=0),Plan!$D$12,0)+IF(AND(N(Plan!$B$13)>0,N(F15)<=0),Plan!$D$13,0)+IF(AND(N(Plan!$B$14)>0,N(G15)<=0),Plan!$D$14,0)+IF(AND(N(Plan!$B$15)>0,N(H15)<=0),Plan!$D$15,0)+IF(AND(N(Plan!$B$16)>0,N(I15)<=0),Plan!$D$16,0)+IF(AND(N(Plan!$B$17)>0,N(J15)<=0),Plan!$D$17,0)+IF(AND(N(Plan!$B$18)>0,N(K15)<=0),Plan!$D$18,0),0)))+IF(N(G15)<=0,0,MIN(G15*(1+Plan!$C$14/12),Plan!$D$14+IF(Plan!$E$14=$L16,Plan!$B$5+IF(AND(N(Plan!$B$9)>0,N(B15)<=0),Plan!$D$9,0)+IF(AND(N(Plan!$B$10)>0,N(C15)<=0),Plan!$D$10,0)+IF(AND(N(Plan!$B$11)>0,N(D15)<=0),Plan!$D$11,0)+IF(AND(N(Plan!$B$12)>0,N(E15)<=0),Plan!$D$12,0)+IF(AND(N(Plan!$B$13)>0,N(F15)<=0),Plan!$D$13,0)+IF(AND(N(Plan!$B$14)>0,N(G15)<=0),Plan!$D$14,0)+IF(AND(N(Plan!$B$15)>0,N(H15)<=0),Plan!$D$15,0)+IF(AND(N(Plan!$B$16)>0,N(I15)<=0),Plan!$D$16,0)+IF(AND(N(Plan!$B$17)>0,N(J15)<=0),Plan!$D$17,0)+IF(AND(N(Plan!$B$18)>0,N(K15)<=0),Plan!$D$18,0),0)))+IF(N(H15)<=0,0,MIN(H15*(1+Plan!$C$15/12),Plan!$D$15+IF(Plan!$E$15=$L16,Plan!$B$5+IF(AND(N(Plan!$B$9)>0,N(B15)<=0),Plan!$D$9,0)+IF(AND(N(Plan!$B$10)>0,N(C15)<=0),Plan!$D$10,0)+IF(AND(N(Plan!$B$11)>0,N(D15)<=0),Plan!$D$11,0)+IF(AND(N(Plan!$B$12)>0,N(E15)<=0),Plan!$D$12,0)+IF(AND(N(Plan!$B$13)>0,N(F15)<=0),Plan!$D$13,0)+IF(AND(N(Plan!$B$14)>0,N(G15)<=0),Plan!$D$14,0)+IF(AND(N(Plan!$B$15)>0,N(H15)<=0),Plan!$D$15,0)+IF(AND(N(Plan!$B$16)>0,N(I15)<=0),Plan!$D$16,0)+IF(AND(N(Plan!$B$17)>0,N(J15)<=0),Plan!$D$17,0)+IF(AND(N(Plan!$B$18)>0,N(K15)<=0),Plan!$D$18,0),0)))+IF(N(I15)<=0,0,MIN(I15*(1+Plan!$C$16/12),Plan!$D$16+IF(Plan!$E$16=$L16,Plan!$B$5+IF(AND(N(Plan!$B$9)>0,N(B15)<=0),Plan!$D$9,0)+IF(AND(N(Plan!$B$10)>0,N(C15)<=0),Plan!$D$10,0)+IF(AND(N(Plan!$B$11)>0,N(D15)<=0),Plan!$D$11,0)+IF(AND(N(Plan!$B$12)>0,N(E15)<=0),Plan!$D$12,0)+IF(AND(N(Plan!$B$13)>0,N(F15)<=0),Plan!$D$13,0)+IF(AND(N(Plan!$B$14)>0,N(G15)<=0),Plan!$D$14,0)+IF(AND(N(Plan!$B$15)>0,N(H15)<=0),Plan!$D$15,0)+IF(AND(N(Plan!$B$16)>0,N(I15)<=0),Plan!$D$16,0)+IF(AND(N(Plan!$B$17)>0,N(J15)<=0),Plan!$D$17,0)+IF(AND(N(Plan!$B$18)>0,N(K15)<=0),Plan!$D$18,0),0)))+IF(N(J15)<=0,0,MIN(J15*(1+Plan!$C$17/12),Plan!$D$17+IF(Plan!$E$17=$L16,Plan!$B$5+IF(AND(N(Plan!$B$9)>0,N(B15)<=0),Plan!$D$9,0)+IF(AND(N(Plan!$B$10)>0,N(C15)<=0),Plan!$D$10,0)+IF(AND(N(Plan!$B$11)>0,N(D15)<=0),Plan!$D$11,0)+IF(AND(N(Plan!$B$12)>0,N(E15)<=0),Plan!$D$12,0)+IF(AND(N(Plan!$B$13)>0,N(F15)<=0),Plan!$D$13,0)+IF(AND(N(Plan!$B$14)>0,N(G15)<=0),Plan!$D$14,0)+IF(AND(N(Plan!$B$15)>0,N(H15)<=0),Plan!$D$15,0)+IF(AND(N(Plan!$B$16)>0,N(I15)<=0),Plan!$D$16,0)+IF(AND(N(Plan!$B$17)>0,N(J15)<=0),Plan!$D$17,0)+IF(AND(N(Plan!$B$18)>0,N(K15)<=0),Plan!$D$18,0),0)))+IF(N(K15)<=0,0,MIN(K15*(1+Plan!$C$18/12),Plan!$D$18+IF(Plan!$E$18=$L16,Plan!$B$5+IF(AND(N(Plan!$B$9)>0,N(B15)<=0),Plan!$D$9,0)+IF(AND(N(Plan!$B$10)>0,N(C15)<=0),Plan!$D$10,0)+IF(AND(N(Plan!$B$11)>0,N(D15)<=0),Plan!$D$11,0)+IF(AND(N(Plan!$B$12)>0,N(E15)<=0),Plan!$D$12,0)+IF(AND(N(Plan!$B$13)>0,N(F15)<=0),Plan!$D$13,0)+IF(AND(N(Plan!$B$14)>0,N(G15)<=0),Plan!$D$14,0)+IF(AND(N(Plan!$B$15)>0,N(H15)<=0),Plan!$D$15,0)+IF(AND(N(Plan!$B$16)>0,N(I15)<=0),Plan!$D$16,0)+IF(AND(N(Plan!$B$17)>0,N(J15)<=0),Plan!$D$17,0)+IF(AND(N(Plan!$B$18)>0,N(K15)<=0),Plan!$D$18,0),0)))
A17: 13 | B17: =IF(N(B16)<=0,0,MAX(0,B16*(1+Plan!$C$9/12)-(Plan!$D$9+IF(Plan!$E$9=$L17,Plan!$B$5+IF(AND(N(Plan!$B$9)>0,N(B16)<=0),Plan!$D$9,0)+IF(AND(N(Plan!$B$10)>0,N(C16)<=0),Plan!$D$10,0)+IF(AND(N(Plan!$B$11)>0,N(D16)<=0),Plan!$D$11,0)+IF(AND(N(Plan!$B$12)>0,N(E16)<=0),Plan!$D$12,0)+IF(AND(N(Plan!$B$13)>0,N(F16)<=0),Plan!$D$13,0)+IF(AND(N(Plan!$B$14)>0,N(G16)<=0),Plan!$D$14,0)+IF(AND(N(Plan!$B$15)>0,N(H16)<=0),Plan!$D$15,0)+IF(AND(N(Plan!$B$16)>0,N(I16)<=0),Plan!$D$16,0)+IF(AND(N(Plan!$B$17)>0,N(J16)<=0),Plan!$D$17,0)+IF(AND(N(Plan!$B$18)>0,N(K16)<=0),Plan!$D$18,0),0)))) | C17: =IF(N(C16)<=0,0,MAX(0,C16*(1+Plan!$C$10/12)-(Plan!$D$10+IF(Plan!$E$10=$L17,Plan!$B$5+IF(AND(N(Plan!$B$9)>0,N(B16)<=0),Plan!$D$9,0)+IF(AND(N(Plan!$B$10)>0,N(C16)<=0),Plan!$D$10,0)+IF(AND(N(Plan!$B$11)>0,N(D16)<=0),Plan!$D$11,0)+IF(AND(N(Plan!$B$12)>0,N(E16)<=0),Plan!$D$12,0)+IF(AND(N(Plan!$B$13)>0,N(F16)<=0),Plan!$D$13,0)+IF(AND(N(Plan!$B$14)>0,N(G16)<=0),Plan!$D$14,0)+IF(AND(N(Plan!$B$15)>0,N(H16)<=0),Plan!$D$15,0)+IF(AND(N(Plan!$B$16)>0,N(I16)<=0),Plan!$D$16,0)+IF(AND(N(Plan!$B$17)>0,N(J16)<=0),Plan!$D$17,0)+IF(AND(N(Plan!$B$18)>0,N(K16)<=0),Plan!$D$18,0),0)))) | D17: =IF(N(D16)<=0,0,MAX(0,D16*(1+Plan!$C$11/12)-(Plan!$D$11+IF(Plan!$E$11=$L17,Plan!$B$5+IF(AND(N(Plan!$B$9)>0,N(B16)<=0),Plan!$D$9,0)+IF(AND(N(Plan!$B$10)>0,N(C16)<=0),Plan!$D$10,0)+IF(AND(N(Plan!$B$11)>0,N(D16)<=0),Plan!$D$11,0)+IF(AND(N(Plan!$B$12)>0,N(E16)<=0),Plan!$D$12,0)+IF(AND(N(Plan!$B$13)>0,N(F16)<=0),Plan!$D$13,0)+IF(AND(N(Plan!$B$14)>0,N(G16)<=0),Plan!$D$14,0)+IF(AND(N(Plan!$B$15)>0,N(H16)<=0),Plan!$D$15,0)+IF(AND(N(Plan!$B$16)>0,N(I16)<=0),Plan!$D$16,0)+IF(AND(N(Plan!$B$17)>0,N(J16)<=0),Plan!$D$17,0)+IF(AND(N(Plan!$B$18)>0,N(K16)<=0),Plan!$D$18,0),0)))) | E17: =IF(N(E16)<=0,0,MAX(0,E16*(1+Plan!$C$12/12)-(Plan!$D$12+IF(Plan!$E$12=$L17,Plan!$B$5+IF(AND(N(Plan!$B$9)>0,N(B16)<=0),Plan!$D$9,0)+IF(AND(N(Plan!$B$10)>0,N(C16)<=0),Plan!$D$10,0)+IF(AND(N(Plan!$B$11)>0,N(D16)<=0),Plan!$D$11,0)+IF(AND(N(Plan!$B$12)>0,N(E16)<=0),Plan!$D$12,0)+IF(AND(N(Plan!$B$13)>0,N(F16)<=0),Plan!$D$13,0)+IF(AND(N(Plan!$B$14)>0,N(G16)<=0),Plan!$D$14,0)+IF(AND(N(Plan!$B$15)>0,N(H16)<=0),Plan!$D$15,0)+IF(AND(N(Plan!$B$16)>0,N(I16)<=0),Plan!$D$16,0)+IF(AND(N(Plan!$B$17)>0,N(J16)<=0),Plan!$D$17,0)+IF(AND(N(Plan!$B$18)>0,N(K16)<=0),Plan!$D$18,0),0)))) | F17: =IF(N(F16)<=0,0,MAX(0,F16*(1+Plan!$C$13/12)-(Plan!$D$13+IF(Plan!$E$13=$L17,Plan!$B$5+IF(AND(N(Plan!$B$9)>0,N(B16)<=0),Plan!$D$9,0)+IF(AND(N(Plan!$B$10)>0,N(C16)<=0),Plan!$D$10,0)+IF(AND(N(Plan!$B$11)>0,N(D16)<=0),Plan!$D$11,0)+IF(AND(N(Plan!$B$12)>0,N(E16)<=0),Plan!$D$12,0)+IF(AND(N(Plan!$B$13)>0,N(F16)<=0),Plan!$D$13,0)+IF(AND(N(Plan!$B$14)>0,N(G16)<=0),Plan!$D$14,0)+IF(AND(N(Plan!$B$15)>0,N(H16)<=0),Plan!$D$15,0)+IF(AND(N(Plan!$B$16)>0,N(I16)<=0),Plan!$D$16,0)+IF(AND(N(Plan!$B$17)>0,N(J16)<=0),Plan!$D$17,0)+IF(AND(N(Plan!$B$18)>0,N(K16)<=0),Plan!$D$18,0),0)))) | G17: =IF(N(G16)<=0,0,MAX(0,G16*(1+Plan!$C$14/12)-(Plan!$D$14+IF(Plan!$E$14=$L17,Plan!$B$5+IF(AND(N(Plan!$B$9)>0,N(B16)<=0),Plan!$D$9,0)+IF(AND(N(Plan!$B$10)>0,N(C16)<=0),Plan!$D$10,0)+IF(AND(N(Plan!$B$11)>0,N(D16)<=0),Plan!$D$11,0)+IF(AND(N(Plan!$B$12)>0,N(E16)<=0),Plan!$D$12,0)+IF(AND(N(Plan!$B$13)>0,N(F16)<=0),Plan!$D$13,0)+IF(AND(N(Plan!$B$14)>0,N(G16)<=0),Plan!$D$14,0)+IF(AND(N(Plan!$B$15)>0,N(H16)<=0),Plan!$D$15,0)+IF(AND(N(Plan!$B$16)>0,N(I16)<=0),Plan!$D$16,0)+IF(AND(N(Plan!$B$17)>0,N(J16)<=0),Plan!$D$17,0)+IF(AND(N(Plan!$B$18)>0,N(K16)<=0),Plan!$D$18,0),0)))) | H17: =IF(N(H16)<=0,0,MAX(0,H16*(1+Plan!$C$15/12)-(Plan!$D$15+IF(Plan!$E$15=$L17,Plan!$B$5+IF(AND(N(Plan!$B$9)>0,N(B16)<=0),Plan!$D$9,0)+IF(AND(N(Plan!$B$10)>0,N(C16)<=0),Plan!$D$10,0)+IF(AND(N(Plan!$B$11)>0,N(D16)<=0),Plan!$D$11,0)+IF(AND(N(Plan!$B$12)>0,N(E16)<=0),Plan!$D$12,0)+IF(AND(N(Plan!$B$13)>0,N(F16)<=0),Plan!$D$13,0)+IF(AND(N(Plan!$B$14)>0,N(G16)<=0),Plan!$D$14,0)+IF(AND(N(Plan!$B$15)>0,N(H16)<=0),Plan!$D$15,0)+IF(AND(N(Plan!$B$16)>0,N(I16)<=0),Plan!$D$16,0)+IF(AND(N(Plan!$B$17)>0,N(J16)<=0),Plan!$D$17,0)+IF(AND(N(Plan!$B$18)>0,N(K16)<=0),Plan!$D$18,0),0)))) | I17: =IF(N(I16)<=0,0,MAX(0,I16*(1+Plan!$C$16/12)-(Plan!$D$16+IF(Plan!$E$16=$L17,Plan!$B$5+IF(AND(N(Plan!$B$9)>0,N(B16)<=0),Plan!$D$9,0)+IF(AND(N(Plan!$B$10)>0,N(C16)<=0),Plan!$D$10,0)+IF(AND(N(Plan!$B$11)>0,N(D16)<=0),Plan!$D$11,0)+IF(AND(N(Plan!$B$12)>0,N(E16)<=0),Plan!$D$12,0)+IF(AND(N(Plan!$B$13)>0,N(F16)<=0),Plan!$D$13,0)+IF(AND(N(Plan!$B$14)>0,N(G16)<=0),Plan!$D$14,0)+IF(AND(N(Plan!$B$15)>0,N(H16)<=0),Plan!$D$15,0)+IF(AND(N(Plan!$B$16)>0,N(I16)<=0),Plan!$D$16,0)+IF(AND(N(Plan!$B$17)>0,N(J16)<=0),Plan!$D$17,0)+IF(AND(N(Plan!$B$18)>0,N(K16)<=0),Plan!$D$18,0),0)))) | J17: =IF(N(J16)<=0,0,MAX(0,J16*(1+Plan!$C$17/12)-(Plan!$D$17+IF(Plan!$E$17=$L17,Plan!$B$5+IF(AND(N(Plan!$B$9)>0,N(B16)<=0),Plan!$D$9,0)+IF(AND(N(Plan!$B$10)>0,N(C16)<=0),Plan!$D$10,0)+IF(AND(N(Plan!$B$11)>0,N(D16)<=0),Plan!$D$11,0)+IF(AND(N(Plan!$B$12)>0,N(E16)<=0),Plan!$D$12,0)+IF(AND(N(Plan!$B$13)>0,N(F16)<=0),Plan!$D$13,0)+IF(AND(N(Plan!$B$14)>0,N(G16)<=0),Plan!$D$14,0)+IF(AND(N(Plan!$B$15)>0,N(H16)<=0),Plan!$D$15,0)+IF(AND(N(Plan!$B$16)>0,N(I16)<=0),Plan!$D$16,0)+IF(AND(N(Plan!$B$17)>0,N(J16)<=0),Plan!$D$17,0)+IF(AND(N(Plan!$B$18)>0,N(K16)<=0),Plan!$D$18,0),0)))) | K17: =IF(N(K16)<=0,0,MAX(0,K16*(1+Plan!$C$18/12)-(Plan!$D$18+IF(Plan!$E$18=$L17,Plan!$B$5+IF(AND(N(Plan!$B$9)>0,N(B16)<=0),Plan!$D$9,0)+IF(AND(N(Plan!$B$10)>0,N(C16)<=0),Plan!$D$10,0)+IF(AND(N(Plan!$B$11)>0,N(D16)<=0),Plan!$D$11,0)+IF(AND(N(Plan!$B$12)>0,N(E16)<=0),Plan!$D$12,0)+IF(AND(N(Plan!$B$13)>0,N(F16)<=0),Plan!$D$13,0)+IF(AND(N(Plan!$B$14)>0,N(G16)<=0),Plan!$D$14,0)+IF(AND(N(Plan!$B$15)>0,N(H16)<=0),Plan!$D$15,0)+IF(AND(N(Plan!$B$16)>0,N(I16)<=0),Plan!$D$16,0)+IF(AND(N(Plan!$B$17)>0,N(J16)<=0),Plan!$D$17,0)+IF(AND(N(Plan!$B$18)>0,N(K16)<=0),Plan!$D$18,0),0)))) | L17: =MIN(IF(N(B16)>0,Plan!$E$9,999),IF(N(C16)>0,Plan!$E$10,999),IF(N(D16)>0,Plan!$E$11,999),IF(N(E16)>0,Plan!$E$12,999),IF(N(F16)>0,Plan!$E$13,999),IF(N(G16)>0,Plan!$E$14,999),IF(N(H16)>0,Plan!$E$15,999),IF(N(I16)>0,Plan!$E$16,999),IF(N(J16)>0,Plan!$E$17,999),IF(N(K16)>0,Plan!$E$18,999)) | M17: =IF(N(B16)<=0,0,MIN(B16*(1+Plan!$C$9/12),Plan!$D$9+IF(Plan!$E$9=$L17,Plan!$B$5+IF(AND(N(Plan!$B$9)>0,N(B16)<=0),Plan!$D$9,0)+IF(AND(N(Plan!$B$10)>0,N(C16)<=0),Plan!$D$10,0)+IF(AND(N(Plan!$B$11)>0,N(D16)<=0),Plan!$D$11,0)+IF(AND(N(Plan!$B$12)>0,N(E16)<=0),Plan!$D$12,0)+IF(AND(N(Plan!$B$13)>0,N(F16)<=0),Plan!$D$13,0)+IF(AND(N(Plan!$B$14)>0,N(G16)<=0),Plan!$D$14,0)+IF(AND(N(Plan!$B$15)>0,N(H16)<=0),Plan!$D$15,0)+IF(AND(N(Plan!$B$16)>0,N(I16)<=0),Plan!$D$16,0)+IF(AND(N(Plan!$B$17)>0,N(J16)<=0),Plan!$D$17,0)+IF(AND(N(Plan!$B$18)>0,N(K16)<=0),Plan!$D$18,0),0)))+IF(N(C16)<=0,0,MIN(C16*(1+Plan!$C$10/12),Plan!$D$10+IF(Plan!$E$10=$L17,Plan!$B$5+IF(AND(N(Plan!$B$9)>0,N(B16)<=0),Plan!$D$9,0)+IF(AND(N(Plan!$B$10)>0,N(C16)<=0),Plan!$D$10,0)+IF(AND(N(Plan!$B$11)>0,N(D16)<=0),Plan!$D$11,0)+IF(AND(N(Plan!$B$12)>0,N(E16)<=0),Plan!$D$12,0)+IF(AND(N(Plan!$B$13)>0,N(F16)<=0),Plan!$D$13,0)+IF(AND(N(Plan!$B$14)>0,N(G16)<=0),Plan!$D$14,0)+IF(AND(N(Plan!$B$15)>0,N(H16)<=0),Plan!$D$15,0)+IF(AND(N(Plan!$B$16)>0,N(I16)<=0),Plan!$D$16,0)+IF(AND(N(Plan!$B$17)>0,N(J16)<=0),Plan!$D$17,0)+IF(AND(N(Plan!$B$18)>0,N(K16)<=0),Plan!$D$18,0),0)))+IF(N(D16)<=0,0,MIN(D16*(1+Plan!$C$11/12),Plan!$D$11+IF(Plan!$E$11=$L17,Plan!$B$5+IF(AND(N(Plan!$B$9)>0,N(B16)<=0),Plan!$D$9,0)+IF(AND(N(Plan!$B$10)>0,N(C16)<=0),Plan!$D$10,0)+IF(AND(N(Plan!$B$11)>0,N(D16)<=0),Plan!$D$11,0)+IF(AND(N(Plan!$B$12)>0,N(E16)<=0),Plan!$D$12,0)+IF(AND(N(Plan!$B$13)>0,N(F16)<=0),Plan!$D$13,0)+IF(AND(N(Plan!$B$14)>0,N(G16)<=0),Plan!$D$14,0)+IF(AND(N(Plan!$B$15)>0,N(H16)<=0),Plan!$D$15,0)+IF(AND(N(Plan!$B$16)>0,N(I16)<=0),Plan!$D$16,0)+IF(AND(N(Plan!$B$17)>0,N(J16)<=0),Plan!$D$17,0)+IF(AND(N(Plan!$B$18)>0,N(K16)<=0),Plan!$D$18,0),0)))+IF(N(E16)<=0,0,MIN(E16*(1+Plan!$C$12/12),Plan!$D$12+IF(Plan!$E$12=$L17,Plan!$B$5+IF(AND(N(Plan!$B$9)>0,N(B16)<=0),Plan!$D$9,0)+IF(AND(N(Plan!$B$10)>0,N(C16)<=0),Plan!$D$10,0)+IF(AND(N(Plan!$B$11)>0,N(D16)<=0),Plan!$D$11,0)+IF(AND(N(Plan!$B$12)>0,N(E16)<=0),Plan!$D$12,0)+IF(AND(N(Plan!$B$13)>0,N(F16)<=0),Plan!$D$13,0)+IF(AND(N(Plan!$B$14)>0,N(G16)<=0),Plan!$D$14,0)+IF(AND(N(Plan!$B$15)>0,N(H16)<=0),Plan!$D$15,0)+IF(AND(N(Plan!$B$16)>0,N(I16)<=0),Plan!$D$16,0)+IF(AND(N(Plan!$B$17)>0,N(J16)<=0),Plan!$D$17,0)+IF(AND(N(Plan!$B$18)>0,N(K16)<=0),Plan!$D$18,0),0)))+IF(N(F16)<=0,0,MIN(F16*(1+Plan!$C$13/12),Plan!$D$13+IF(Plan!$E$13=$L17,Plan!$B$5+IF(AND(N(Plan!$B$9)>0,N(B16)<=0),Plan!$D$9,0)+IF(AND(N(Plan!$B$10)>0,N(C16)<=0),Plan!$D$10,0)+IF(AND(N(Plan!$B$11)>0,N(D16)<=0),Plan!$D$11,0)+IF(AND(N(Plan!$B$12)>0,N(E16)<=0),Plan!$D$12,0)+IF(AND(N(Plan!$B$13)>0,N(F16)<=0),Plan!$D$13,0)+IF(AND(N(Plan!$B$14)>0,N(G16)<=0),Plan!$D$14,0)+IF(AND(N(Plan!$B$15)>0,N(H16)<=0),Plan!$D$15,0)+IF(AND(N(Plan!$B$16)>0,N(I16)<=0),Plan!$D$16,0)+IF(AND(N(Plan!$B$17)>0,N(J16)<=0),Plan!$D$17,0)+IF(AND(N(Plan!$B$18)>0,N(K16)<=0),Plan!$D$18,0),0)))+IF(N(G16)<=0,0,MIN(G16*(1+Plan!$C$14/12),Plan!$D$14+IF(Plan!$E$14=$L17,Plan!$B$5+IF(AND(N(Plan!$B$9)>0,N(B16)<=0),Plan!$D$9,0)+IF(AND(N(Plan!$B$10)>0,N(C16)<=0),Plan!$D$10,0)+IF(AND(N(Plan!$B$11)>0,N(D16)<=0),Plan!$D$11,0)+IF(AND(N(Plan!$B$12)>0,N(E16)<=0),Plan!$D$12,0)+IF(AND(N(Plan!$B$13)>0,N(F16)<=0),Plan!$D$13,0)+IF(AND(N(Plan!$B$14)>0,N(G16)<=0),Plan!$D$14,0)+IF(AND(N(Plan!$B$15)>0,N(H16)<=0),Plan!$D$15,0)+IF(AND(N(Plan!$B$16)>0,N(I16)<=0),Plan!$D$16,0)+IF(AND(N(Plan!$B$17)>0,N(J16)<=0),Plan!$D$17,0)+IF(AND(N(Plan!$B$18)>0,N(K16)<=0),Plan!$D$18,0),0)))+IF(N(H16)<=0,0,MIN(H16*(1+Plan!$C$15/12),Plan!$D$15+IF(Plan!$E$15=$L17,Plan!$B$5+IF(AND(N(Plan!$B$9)>0,N(B16)<=0),Plan!$D$9,0)+IF(AND(N(Plan!$B$10)>0,N(C16)<=0),Plan!$D$10,0)+IF(AND(N(Plan!$B$11)>0,N(D16)<=0),Plan!$D$11,0)+IF(AND(N(Plan!$B$12)>0,N(E16)<=0),Plan!$D$12,0)+IF(AND(N(Plan!$B$13)>0,N(F16)<=0),Plan!$D$13,0)+IF(AND(N(Plan!$B$14)>0,N(G16)<=0),Plan!$D$14,0)+IF(AND(N(Plan!$B$15)>0,N(H16)<=0),Plan!$D$15,0)+IF(AND(N(Plan!$B$16)>0,N(I16)<=0),Plan!$D$16,0)+IF(AND(N(Plan!$B$17)>0,N(J16)<=0),Plan!$D$17,0)+IF(AND(N(Plan!$B$18)>0,N(K16)<=0),Plan!$D$18,0),0)))+IF(N(I16)<=0,0,MIN(I16*(1+Plan!$C$16/12),Plan!$D$16+IF(Plan!$E$16=$L17,Plan!$B$5+IF(AND(N(Plan!$B$9)>0,N(B16)<=0),Plan!$D$9,0)+IF(AND(N(Plan!$B$10)>0,N(C16)<=0),Plan!$D$10,0)+IF(AND(N(Plan!$B$11)>0,N(D16)<=0),Plan!$D$11,0)+IF(AND(N(Plan!$B$12)>0,N(E16)<=0),Plan!$D$12,0)+IF(AND(N(Plan!$B$13)>0,N(F16)<=0),Plan!$D$13,0)+IF(AND(N(Plan!$B$14)>0,N(G16)<=0),Plan!$D$14,0)+IF(AND(N(Plan!$B$15)>0,N(H16)<=0),Plan!$D$15,0)+IF(AND(N(Plan!$B$16)>0,N(I16)<=0),Plan!$D$16,0)+IF(AND(N(Plan!$B$17)>0,N(J16)<=0),Plan!$D$17,0)+IF(AND(N(Plan!$B$18)>0,N(K16)<=0),Plan!$D$18,0),0)))+IF(N(J16)<=0,0,MIN(J16*(1+Plan!$C$17/12),Plan!$D$17+IF(Plan!$E$17=$L17,Plan!$B$5+IF(AND(N(Plan!$B$9)>0,N(B16)<=0),Plan!$D$9,0)+IF(AND(N(Plan!$B$10)>0,N(C16)<=0),Plan!$D$10,0)+IF(AND(N(Plan!$B$11)>0,N(D16)<=0),Plan!$D$11,0)+IF(AND(N(Plan!$B$12)>0,N(E16)<=0),Plan!$D$12,0)+IF(AND(N(Plan!$B$13)>0,N(F16)<=0),Plan!$D$13,0)+IF(AND(N(Plan!$B$14)>0,N(G16)<=0),Plan!$D$14,0)+IF(AND(N(Plan!$B$15)>0,N(H16)<=0),Plan!$D$15,0)+IF(AND(N(Plan!$B$16)>0,N(I16)<=0),Plan!$D$16,0)+IF(AND(N(Plan!$B$17)>0,N(J16)<=0),Plan!$D$17,0)+IF(AND(N(Plan!$B$18)>0,N(K16)<=0),Plan!$D$18,0),0)))+IF(N(K16)<=0,0,MIN(K16*(1+Plan!$C$18/12),Plan!$D$18+IF(Plan!$E$18=$L17,Plan!$B$5+IF(AND(N(Plan!$B$9)>0,N(B16)<=0),Plan!$D$9,0)+IF(AND(N(Plan!$B$10)>0,N(C16)<=0),Plan!$D$10,0)+IF(AND(N(Plan!$B$11)>0,N(D16)<=0),Plan!$D$11,0)+IF(AND(N(Plan!$B$12)>0,N(E16)<=0),Plan!$D$12,0)+IF(AND(N(Plan!$B$13)>0,N(F16)<=0),Plan!$D$13,0)+IF(AND(N(Plan!$B$14)>0,N(G16)<=0),Plan!$D$14,0)+IF(AND(N(Plan!$B$15)>0,N(H16)<=0),Plan!$D$15,0)+IF(AND(N(Plan!$B$16)>0,N(I16)<=0),Plan!$D$16,0)+IF(AND(N(Plan!$B$17)>0,N(J16)<=0),Plan!$D$17,0)+IF(AND(N(Plan!$B$18)>0,N(K16)<=0),Plan!$D$18,0),0)))
... A244: 240 | B244: =IF(N(B243)<=0,0,MAX(0,B243*(1+Plan!$C$9/12)-(Plan!$D$9+IF(Plan!$E$9=$L244,Plan!$B$5+IF(AND(N(Plan!$B$9)>0,N(B243)<=0),Plan!$D$9,0)+IF(AND(N(Plan!$B$10)>0,N(C243)<=0),Plan!$D$10,0)+IF(AND(N(Plan!$B$11)>0,N(D243)<=0),Plan!$D$11,0)+IF(AND(N(Plan!$B$12)>0,N(E243)<=0),Plan!$D$12,0)+IF(AND(N(Plan!$B$13)>0,N(F243)<=0),Plan!$D$13,0)+IF(AND(N(Plan!$B$14)>0,N(G243)<=0),Plan!$D$14,0)+IF(AND(N(Plan!$B$15)>0,N(H243)<=0),Plan!$D$15,0)+IF(AND(N(Plan!$B$16)>0,N(I243)<=0),Plan!$D$16,0)+IF(AND(N(Plan!$B$17)>0,N(J243)<=0),Plan!$D$17,0)+IF(AND(N(Plan!$B$18)>0,N(K243)<=0),Plan!$D$18,0),0)))) | C244: =IF(N(C243)<=0,0,MAX(0,C243*(1+Plan!$C$10/12)-(Plan!$D$10+IF(Plan!$E$10=$L244,Plan!$B$5+IF(AND(N(Plan!$B$9)>0,N(B243)<=0),Plan!$D$9,0)+IF(AND(N(Plan!$B$10)>0,N(C243)<=0),Plan!$D$10,0)+IF(AND(N(Plan!$B$11)>0,N(D243)<=0),Plan!$D$11,0)+IF(AND(N(Plan!$B$12)>0,N(E243)<=0),Plan!$D$12,0)+IF(AND(N(Plan!$B$13)>0,N(F243)<=0),Plan!$D$13,0)+IF(AND(N(Plan!$B$14)>0,N(G243)<=0),Plan!$D$14,0)+IF(AND(N(Plan!$B$15)>0,N(H243)<=0),Plan!$D$15,0)+IF(AND(N(Plan!$B$16)>0,N(I243)<=0),Plan!$D$16,0)+IF(AND(N(Plan!$B$17)>0,N(J243)<=0),Plan!$D$17,0)+IF(AND(N(Plan!$B$18)>0,N(K243)<=0),Plan!$D$18,0),0)))) | D244: =IF(N(D243)<=0,0,MAX(0,D243*(1+Plan!$C$11/12)-(Plan!$D$11+IF(Plan!$E$11=$L244,Plan!$B$5+IF(AND(N(Plan!$B$9)>0,N(B243)<=0),Plan!$D$9,0)+IF(AND(N(Plan!$B$10)>0,N(C243)<=0),Plan!$D$10,0)+IF(AND(N(Plan!$B$11)>0,N(D243)<=0),Plan!$D$11,0)+IF(AND(N(Plan!$B$12)>0,N(E243)<=0),Plan!$D$12,0)+IF(AND(N(Plan!$B$13)>0,N(F243)<=0),Plan!$D$13,0)+IF(AND(N(Plan!$B$14)>0,N(G243)<=0),Plan!$D$14,0)+IF(AND(N(Plan!$B$15)>0,N(H243)<=0),Plan!$D$15,0)+IF(AND(N(Plan!$B$16)>0,N(I243)<=0),Plan!$D$16,0)+IF(AND(N(Plan!$B$17)>0,N(J243)<=0),Plan!$D$17,0)+IF(AND(N(Plan!$B$18)>0,N(K243)<=0),Plan!$D$18,0),0)))) | E244: =IF(N(E243)<=0,0,MAX(0,E243*(1+Plan!$C$12/12)-(Plan!$D$12+IF(Plan!$E$12=$L244,Plan!$B$5+IF(AND(N(Plan!$B$9)>0,N(B243)<=0),Plan!$D$9,0)+IF(AND(N(Plan!$B$10)>0,N(C243)<=0),Plan!$D$10,0)+IF(AND(N(Plan!$B$11)>0,N(D243)<=0),Plan!$D$11,0)+IF(AND(N(Plan!$B$12)>0,N(E243)<=0),Plan!$D$12,0)+IF(AND(N(Plan!$B$13)>0,N(F243)<=0),Plan!$D$13,0)+IF(AND(N(Plan!$B$14)>0,N(G243)<=0),Plan!$D$14,0)+IF(AND(N(Plan!$B$15)>0,N(H243)<=0),Plan!$D$15,0)+IF(AND(N(Plan!$B$16)>0,N(I243)<=0),Plan!$D$16,0)+IF(AND(N(Plan!$B$17)>0,N(J243)<=0),Plan!$D$17,0)+IF(AND(N(Plan!$B$18)>0,N(K243)<=0),Plan!$D$18,0),0)))) | F244: =IF(N(F243)<=0,0,MAX(0,F243*(1+Plan!$C$13/12)-(Plan!$D$13+IF(Plan!$E$13=$L244,Plan!$B$5+IF(AND(N(Plan!$B$9)>0,N(B243)<=0),Plan!$D$9,0)+IF(AND(N(Plan!$B$10)>0,N(C243)<=0),Plan!$D$10,0)+IF(AND(N(Plan!$B$11)>0,N(D243)<=0),Plan!$D$11,0)+IF(AND(N(Plan!$B$12)>0,N(E243)<=0),Plan!$D$12,0)+IF(AND(N(Plan!$B$13)>0,N(F243)<=0),Plan!$D$13,0)+IF(AND(N(Plan!$B$14)>0,N(G243)<=0),Plan!$D$14,0)+IF(AND(N(Plan!$B$15)>0,N(H243)<=0),Plan!$D$15,0)+IF(AND(N(Plan!$B$16)>0,N(I243)<=0),Plan!$D$16,0)+IF(AND(N(Plan!$B$17)>0,N(J243)<=0),Plan!$D$17,0)+IF(AND(N(Plan!$B$18)>0,N(K243)<=0),Plan!$D$18,0),0)))) | G244: =IF(N(G243)<=0,0,MAX(0,G243*(1+Plan!$C$14/12)-(Plan!$D$14+IF(Plan!$E$14=$L244,Plan!$B$5+IF(AND(N(Plan!$B$9)>0,N(B243)<=0),Plan!$D$9,0)+IF(AND(N(Plan!$B$10)>0,N(C243)<=0),Plan!$D$10,0)+IF(AND(N(Plan!$B$11)>0,N(D243)<=0),Plan!$D$11,0)+IF(AND(N(Plan!$B$12)>0,N(E243)<=0),Plan!$D$12,0)+IF(AND(N(Plan!$B$13)>0,N(F243)<=0),Plan!$D$13,0)+IF(AND(N(Plan!$B$14)>0,N(G243)<=0),Plan!$D$14,0)+IF(AND(N(Plan!$B$15)>0,N(H243)<=0),Plan!$D$15,0)+IF(AND(N(Plan!$B$16)>0,N(I243)<=0),Plan!$D$16,0)+IF(AND(N(Plan!$B$17)>0,N(J243)<=0),Plan!$D$17,0)+IF(AND(N(Plan!$B$18)>0,N(K243)<=0),Plan!$D$18,0),0)))) | H244: =IF(N(H243)<=0,0,MAX(0,H243*(1+Plan!$C$15/12)-(Plan!$D$15+IF(Plan!$E$15=$L244,Plan!$B$5+IF(AND(N(Plan!$B$9)>0,N(B243)<=0),Plan!$D$9,0)+IF(AND(N(Plan!$B$10)>0,N(C243)<=0),Plan!$D$10,0)+IF(AND(N(Plan!$B$11)>0,N(D243)<=0),Plan!$D$11,0)+IF(AND(N(Plan!$B$12)>0,N(E243)<=0),Plan!$D$12,0)+IF(AND(N(Plan!$B$13)>0,N(F243)<=0),Plan!$D$13,0)+IF(AND(N(Plan!$B$14)>0,N(G243)<=0),Plan!$D$14,0)+IF(AND(N(Plan!$B$15)>0,N(H243)<=0),Plan!$D$15,0)+IF(AND(N(Plan!$B$16)>0,N(I243)<=0),Plan!$D$16,0)+IF(AND(N(Plan!$B$17)>0,N(J243)<=0),Plan!$D$17,0)+IF(AND(N(Plan!$B$18)>0,N(K243)<=0),Plan!$D$18,0),0)))) | I244: =IF(N(I243)<=0,0,MAX(0,I243*(1+Plan!$C$16/12)-(Plan!$D$16+IF(Plan!$E$16=$L244,Plan!$B$5+IF(AND(N(Plan!$B$9)>0,N(B243)<=0),Plan!$D$9,0)+IF(AND(N(Plan!$B$10)>0,N(C243)<=0),Plan!$D$10,0)+IF(AND(N(Plan!$B$11)>0,N(D243)<=0),Plan!$D$11,0)+IF(AND(N(Plan!$B$12)>0,N(E243)<=0),Plan!$D$12,0)+IF(AND(N(Plan!$B$13)>0,N(F243)<=0),Plan!$D$13,0)+IF(AND(N(Plan!$B$14)>0,N(G243)<=0),Plan!$D$14,0)+IF(AND(N(Plan!$B$15)>0,N(H243)<=0),Plan!$D$15,0)+IF(AND(N(Plan!$B$16)>0,N(I243)<=0),Plan!$D$16,0)+IF(AND(N(Plan!$B$17)>0,N(J243)<=0),Plan!$D$17,0)+IF(AND(N(Plan!$B$18)>0,N(K243)<=0),Plan!$D$18,0),0)))) | J244: =IF(N(J243)<=0,0,MAX(0,J243*(1+Plan!$C$17/12)-(Plan!$D$17+IF(Plan!$E$17=$L244,Plan!$B$5+IF(AND(N(Plan!$B$9)>0,N(B243)<=0),Plan!$D$9,0)+IF(AND(N(Plan!$B$10)>0,N(C243)<=0),Plan!$D$10,0)+IF(AND(N(Plan!$B$11)>0,N(D243)<=0),Plan!$D$11,0)+IF(AND(N(Plan!$B$12)>0,N(E243)<=0),Plan!$D$12,0)+IF(AND(N(Plan!$B$13)>0,N(F243)<=0),Plan!$D$13,0)+IF(AND(N(Plan!$B$14)>0,N(G243)<=0),Plan!$D$14,0)+IF(AND(N(Plan!$B$15)>0,N(H243)<=0),Plan!$D$15,0)+IF(AND(N(Plan!$B$16)>0,N(I243)<=0),Plan!$D$16,0)+IF(AND(N(Plan!$B$17)>0,N(J243)<=0),Plan!$D$17,0)+IF(AND(N(Plan!$B$18)>0,N(K243)<=0),Plan!$D$18,0),0)))) | K244: =IF(N(K243)<=0,0,MAX(0,K243*(1+Plan!$C$18/12)-(Plan!$D$18+IF(Plan!$E$18=$L244,Plan!$B$5+IF(AND(N(Plan!$B$9)>0,N(B243)<=0),Plan!$D$9,0)+IF(AND(N(Plan!$B$10)>0,N(C243)<=0),Plan!$D$10,0)+IF(AND(N(Plan!$B$11)>0,N(D243)<=0),Plan!$D$11,0)+IF(AND(N(Plan!$B$12)>0,N(E243)<=0),Plan!$D$12,0)+IF(AND(N(Plan!$B$13)>0,N(F243)<=0),Plan!$D$13,0)+IF(AND(N(Plan!$B$14)>0,N(G243)<=0),Plan!$D$14,0)+IF(AND(N(Plan!$B$15)>0,N(H243)<=0),Plan!$D$15,0)+IF(AND(N(Plan!$B$16)>0,N(I243)<=0),Plan!$D$16,0)+IF(AND(N(Plan!$B$17)>0,N(J243)<=0),Plan!$D$17,0)+IF(AND(N(Plan!$B$18)>0,N(K243)<=0),Plan!$D$18,0),0)))) | L244: =MIN(IF(N(B243)>0,Plan!$E$9,999),IF(N(C243)>0,Plan!$E$10,999),IF(N(D243)>0,Plan!$E$11,999),IF(N(E243)>0,Plan!$E$12,999),IF(N(F243)>0,Plan!$E$13,999),IF(N(G243)>0,Plan!$E$14,999),IF(N(H243)>0,Plan!$E$15,999),IF(N(I243)>0,Plan!$E$16,999),IF(N(J243)>0,Plan!$E$17,999),IF(N(K243)>0,Plan!$E$18,999)) | M244: =IF(N(B243)<=0,0,MIN(B243*(1+Plan!$C$9/12),Plan!$D$9+IF(Plan!$E$9=$L244,Plan!$B$5+IF(AND(N(Plan!$B$9)>0,N(B243)<=0),Plan!$D$9,0)+IF(AND(N(Plan!$B$10)>0,N(C243)<=0),Plan!$D$10,0)+IF(AND(N(Plan!$B$11)>0,N(D243)<=0),Plan!$D$11,0)+IF(AND(N(Plan!$B$12)>0,N(E243)<=0),Plan!$D$12,0)+IF(AND(N(Plan!$B$13)>0,N(F243)<=0),Plan!$D$13,0)+IF(AND(N(Plan!$B$14)>0,N(G243)<=0),Plan!$D$14,0)+IF(AND(N(Plan!$B$15)>0,N(H243)<=0),Plan!$D$15,0)+IF(AND(N(Plan!$B$16)>0,N(I243)<=0),Plan!$D$16,0)+IF(AND(N(Plan!$B$17)>0,N(J243)<=0),Plan!$D$17,0)+IF(AND(N(Plan!$B$18)>0,N(K243)<=0),Plan!$D$18,0),0)))+IF(N(C243)<=0,0,MIN(C243*(1+Plan!$C$10/12),Plan!$D$10+IF(Plan!$E$10=$L244,Plan!$B$5+IF(AND(N(Plan!$B$9)>0,N(B243)<=0),Plan!$D$9,0)+IF(AND(N(Plan!$B$10)>0,N(C243)<=0),Plan!$D$10,0)+IF(AND(N(Plan!$B$11)>0,N(D243)<=0),Plan!$D$11,0)+IF(AND(N(Plan!$B$12)>0,N(E243)<=0),Plan!$D$12,0)+IF(AND(N(Plan!$B$13)>0,N(F243)<=0),Plan!$D$13,0)+IF(AND(N(Plan!$B$14)>0,N(G243)<=0),Plan!$D$14,0)+IF(AND(N(Plan!$B$15)>0,N(H243)<=0),Plan!$D$15,0)+IF(AND(N(Plan!$B$16)>0,N(I243)<=0),Plan!$D$16,0)+IF(AND(N(Plan!$B$17)>0,N(J243)<=0),Plan!$D$17,0)+IF(AND(N(Plan!$B$18)>0,N(K243)<=0),Plan!$D$18,0),0)))+IF(N(D243)<=0,0,MIN(D243*(1+Plan!$C$11/12),Plan!$D$11+IF(Plan!$E$11=$L244,Plan!$B$5+IF(AND(N(Plan!$B$9)>0,N(B243)<=0),Plan!$D$9,0)+IF(AND(N(Plan!$B$10)>0,N(C243)<=0),Plan!$D$10,0)+IF(AND(N(Plan!$B$11)>0,N(D243)<=0),Plan!$D$11,0)+IF(AND(N(Plan!$B$12)>0,N(E243)<=0),Plan!$D$12,0)+IF(AND(N(Plan!$B$13)>0,N(F243)<=0),Plan!$D$13,0)+IF(AND(N(Plan!$B$14)>0,N(G243)<=0),Plan!$D$14,0)+IF(AND(N(Plan!$B$15)>0,N(H243)<=0),Plan!$D$15,0)+IF(AND(N(Plan!$B$16)>0,N(I243)<=0),Plan!$D$16,0)+IF(AND(N(Plan!$B$17)>0,N(J243)<=0),Plan!$D$17,0)+IF(AND(N(Plan!$B$18)>0,N(K243)<=0),Plan!$D$18,0),0)))+IF(N(E243)<=0,0,MIN(E243*(1+Plan!$C$12/12),Plan!$D$12+IF(Plan!$E$12=$L244,Plan!$B$5+IF(AND(N(Plan!$B$9)>0,N(B243)<=0),Plan!$D$9,0)+IF(AND(N(Plan!$B$10)>0,N(C243)<=0),Plan!$D$10,0)+IF(AND(N(Plan!$B$11)>0,N(D243)<=0),Plan!$D$11,0)+IF(AND(N(Plan!$B$12)>0,N(E243)<=0),Plan!$D$12,0)+IF(AND(N(Plan!$B$13)>0,N(F243)<=0),Plan!$D$13,0)+IF(AND(N(Plan!$B$14)>0,N(G243)<=0),Plan!$D$14,0)+IF(AND(N(Plan!$B$15)>0,N(H243)<=0),Plan!$D$15,0)+IF(AND(N(Plan!$B$16)>0,N(I243)<=0),Plan!$D$16,0)+IF(AND(N(Plan!$B$17)>0,N(J243)<=0),Plan!$D$17,0)+IF(AND(N(Plan!$B$18)>0,N(K243)<=0),Plan!$D$18,0),0)))+IF(N(F243)<=0,0,MIN(F243*(1+Plan!$C$13/12),Plan!$D$13+IF(Plan!$E$13=$L244,Plan!$B$5+IF(AND(N(Plan!$B$9)>0,N(B243)<=0),Plan!$D$9,0)+IF(AND(N(Plan!$B$10)>0,N(C243)<=0),Plan!$D$10,0)+IF(AND(N(Plan!$B$11)>0,N(D243)<=0),Plan!$D$11,0)+IF(AND(N(Plan!$B$12)>0,N(E243)<=0),Plan!$D$12,0)+IF(AND(N(Plan!$B$13)>0,N(F243)<=0),Plan!$D$13,0)+IF(AND(N(Plan!$B$14)>0,N(G243)<=0),Plan!$D$14,0)+IF(AND(N(Plan!$B$15)>0,N(H243)<=0),Plan!$D$15,0)+IF(AND(N(Plan!$B$16)>0,N(I243)<=0),Plan!$D$16,0)+IF(AND(N(Plan!$B$17)>0,N(J243)<=0),Plan!$D$17,0)+IF(AND(N(Plan!$B$18)>0,N(K243)<=0),Plan!$D$18,0),0)))+IF(N(G243)<=0,0,MIN(G243*(1+Plan!$C$14/12),Plan!$D$14+IF(Plan!$E$14=$L244,Plan!$B$5+IF(AND(N(Plan!$B$9)>0,N(B243)<=0),Plan!$D$9,0)+IF(AND(N(Plan!$B$10)>0,N(C243)<=0),Plan!$D$10,0)+IF(AND(N(Plan!$B$11)>0,N(D243)<=0),Plan!$D$11,0)+IF(AND(N(Plan!$B$12)>0,N(E243)<=0),Plan!$D$12,0)+IF(AND(N(Plan!$B$13)>0,N(F243)<=0),Plan!$D$13,0)+IF(AND(N(Plan!$B$14)>0,N(G243)<=0),Plan!$D$14,0)+IF(AND(N(Plan!$B$15)>0,N(H243)<=0),Plan!$D$15,0)+IF(AND(N(Plan!$B$16)>0,N(I243)<=0),Plan!$D$16,0)+IF(AND(N(Plan!$B$17)>0,N(J243)<=0),Plan!$D$17,0)+IF(AND(N(Plan!$B$18)>0,N(K243)<=0),Plan!$D$18,0),0)))+IF(N(H243)<=0,0,MIN(H243*(1+Plan!$C$15/12),Plan!$D$15+IF(Plan!$E$15=$L244,Plan!$B$5+IF(AND(N(Plan!$B$9)>0,N(B243)<=0),Plan!$D$9,0)+IF(AND(N(Plan!$B$10)>0,N(C243)<=0),Plan!$D$10,0)+IF(AND(N(Plan!$B$11)>0,N(D243)<=0),Plan!$D$11,0)+IF(AND(N(Plan!$B$12)>0,N(E243)<=0),Plan!$D$12,0)+IF(AND(N(Plan!$B$13)>0,N(F243)<=0),Plan!$D$13,0)+IF(AND(N(Plan!$B$14)>0,N(G243)<=0),Plan!$D$14,0)+IF(AND(N(Plan!$B$15)>0,N(H243)<=0),Plan!$D$15,0)+IF(AND(N(Plan!$B$16)>0,N(I243)<=0),Plan!$D$16,0)+IF(AND(N(Plan!$B$17)>0,N(J243)<=0),Plan!$D$17,0)+IF(AND(N(Plan!$B$18)>0,N(K243)<=0),Plan!$D$18,0),0)))+IF(N(I243)<=0,0,MIN(I243*(1+Plan!$C$16/12),Plan!$D$16+IF(Plan!$E$16=$L244,Plan!$B$5+IF(AND(N(Plan!$B$9)>0,N(B243)<=0),Plan!$D$9,0)+IF(AND(N(Plan!$B$10)>0,N(C243)<=0),Plan!$D$10,0)+IF(AND(N(Plan!$B$11)>0,N(D243)<=0),Plan!$D$11,0)+IF(AND(N(Plan!$B$12)>0,N(E243)<=0),Plan!$D$12,0)+IF(AND(N(Plan!$B$13)>0,N(F243)<=0),Plan!$D$13,0)+IF(AND(N(Plan!$B$14)>0,N(G243)<=0),Plan!$D$14,0)+IF(AND(N(Plan!$B$15)>0,N(H243)<=0),Plan!$D$15,0)+IF(AND(N(Plan!$B$16)>0,N(I243)<=0),Plan!$D$16,0)+IF(AND(N(Plan!$B$17)>0,N(J243)<=0),Plan!$D$17,0)+IF(AND(N(Plan!$B$18)>0,N(K243)<=0),Plan!$D$18,0),0)))+IF(N(J243)<=0,0,MIN(J243*(1+Plan!$C$17/12),Plan!$D$17+IF(Plan!$E$17=$L244,Plan!$B$5+IF(AND(N(Plan!$B$9)>0,N(B243)<=0),Plan!$D$9,0)+IF(AND(N(Plan!$B$10)>0,N(C243)<=0),Plan!$D$10,0)+IF(AND(N(Plan!$B$11)>0,N(D243)<=0),Plan!$D$11,0)+IF(AND(N(Plan!$B$12)>0,N(E243)<=0),Plan!$D$12,0)+IF(AND(N(Plan!$B$13)>0,N(F243)<=0),Plan!$D$13,0)+IF(AND(N(Plan!$B$14)>0,N(G243)<=0),Plan!$D$14,0)+IF(AND(N(Plan!$B$15)>0,N(H243)<=0),Plan!$D$15,0)+IF(AND(N(Plan!$B$16)>0,N(I243)<=0),Plan!$D$16,0)+IF(AND(N(Plan!$B$17)>0,N(J243)<=0),Plan!$D$17,0)+IF(AND(N(Plan!$B$18)>0,N(K243)<=0),Plan!$D$18,0),0)))+IF(N(K243)<=0,0,MIN(K243*(1+Plan!$C$18/12),Plan!$D$18+IF(Plan!$E$18=$L244,Plan!$B$5+IF(AND(N(Plan!$B$9)>0,N(B243)<=0),Plan!$D$9,0)+IF(AND(N(Plan!$B$10)>0,N(C243)<=0),Plan!$D$10,0)+IF(AND(N(Plan!$B$11)>0,N(D243)<=0),Plan!$D$11,0)+IF(AND(N(Plan!$B$12)>0,N(E243)<=0),Plan!$D$12,0)+IF(AND(N(Plan!$B$13)>0,N(F243)<=0),Plan!$D$13,0)+IF(AND(N(Plan!$B$14)>0,N(G243)<=0),Plan!$D$14,0)+IF(AND(N(Plan!$B$15)>0,N(H243)<=0),Plan!$D$15,0)+IF(AND(N(Plan!$B$16)>0,N(I243)<=0),Plan!$D$16,0)+IF(AND(N(Plan!$B$17)>0,N(J243)<=0),Plan!$D$17,0)+IF(AND(N(Plan!$B$18)>0,N(K243)<=0),Plan!$D$18,0),0)))
