Workbook

Sheet Start here
A1: Monthly Budget (50/30/20)
A2: Free template · templates.snoutsmith.com
B4: WHAT IT DOES
B5: Plan a month of income and spending, see actual vs planned per category and how close you are to the 50/30/20 split.
B7: HOW TO USE
B8: 1. Type your monthly take-home income on the Budget sheet.
B9: 2. Adjust the planned amount for each category (or keep the examples).
B10: 3. Log spending on the Spending sheet: date, category, amount.
B11: 4. Budget shows actual, left to spend and your needs/wants/savings split.
B13: GOOD TO KNOW
B14: • Categories are tagged Need, Want or Savings – change the tag in column B.
B15: • Delete the sample rows on Spending (rows 5–44) to start fresh.
B17: Tinted cells are yours to type in. Grey numbers are formulas – leave them. Works in Google Sheets (File → Import or open the .xlsx) and Excel, free plans, no add-ons or scripts.

Sheet Budget
A1: Budget
A2: October 2026 – change the month name freely
A4: Monthly income | B4: 4200
A6: Category | B6: Type | C6: Planned | D6: Actual | E6: Left | F6: % used
A7: Rent / mortgage | B7: Need | C7: 1400 | D7: =SUMIFS(Spending!$C$5:$C$500,Spending!$B$5:$B$500,A7) | E7: =C7-D7 | F7: =IF(C7=0,0,D7/C7)
A8: Utilities | B8: Need | C8: 180 | D8: =SUMIFS(Spending!$C$5:$C$500,Spending!$B$5:$B$500,A8) | E8: =C8-D8 | F8: =IF(C8=0,0,D8/C8)
A9: Groceries | B9: Need | C9: 450 | D9: =SUMIFS(Spending!$C$5:$C$500,Spending!$B$5:$B$500,A9) | E9: =C9-D9 | F9: =IF(C9=0,0,D9/C9)
A10: Transport | B10: Need | C10: 220 | D10: =SUMIFS(Spending!$C$5:$C$500,Spending!$B$5:$B$500,A10) | E10: =C10-D10 | F10: =IF(C10=0,0,D10/C10)
A11: Insurance | B11: Need | C11: 160 | D11: =SUMIFS(Spending!$C$5:$C$500,Spending!$B$5:$B$500,A11) | E11: =C11-D11 | F11: =IF(C11=0,0,D11/C11)
A12: Phone & internet | B12: Need | C12: 90 | D12: =SUMIFS(Spending!$C$5:$C$500,Spending!$B$5:$B$500,A12) | E12: =C12-D12 | F12: =IF(C12=0,0,D12/C12)
A13: Dining out | B13: Want | C13: 200 | D13: =SUMIFS(Spending!$C$5:$C$500,Spending!$B$5:$B$500,A13) | E13: =C13-D13 | F13: =IF(C13=0,0,D13/C13)
A14: Entertainment | B14: Want | C14: 120 | D14: =SUMIFS(Spending!$C$5:$C$500,Spending!$B$5:$B$500,A14) | E14: =C14-D14 | F14: =IF(C14=0,0,D14/C14)
A15: Shopping | B15: Want | C15: 150 | D15: =SUMIFS(Spending!$C$5:$C$500,Spending!$B$5:$B$500,A15) | E15: =C15-D15 | F15: =IF(C15=0,0,D15/C15)
A16: Subscriptions | B16: Want | C16: 45 | D16: =SUMIFS(Spending!$C$5:$C$500,Spending!$B$5:$B$500,A16) | E16: =C16-D16 | F16: =IF(C16=0,0,D16/C16)
A17: Travel fund | B17: Want | C17: 150 | D17: =SUMIFS(Spending!$C$5:$C$500,Spending!$B$5:$B$500,A17) | E17: =C17-D17 | F17: =IF(C17=0,0,D17/C17)
A18: Emergency fund | B18: Savings | C18: 400 | D18: =SUMIFS(Spending!$C$5:$C$500,Spending!$B$5:$B$500,A18) | E18: =C18-D18 | F18: =IF(C18=0,0,D18/C18)
... A20: Extra debt payment | B20: Savings | C20: 150 | D20: =SUMIFS(Spending!$C$5:$C$500,Spending!$B$5:$B$500,A20) | E20: =C20-D20 | F20: =IF(C20=0,0,D20/C20)
A21: Total | C21: =SUM(C7:C20) | D21: =SUM(D7:D20) | E21: =SUM(E7:E20)
A23: SPLIT (target 50 / 30 / 20)
A24: Type | B24: Planned | C24: % of income | D24: Target
A25: Need | B25: =SUMIFS($C$7:$C$20,$B$7:$B$20,A25) | C25: =IF($B$4=0,0,B25/$B$4) | D25: 0.5
A26: Want | B26: =SUMIFS($C$7:$C$20,$B$7:$B$20,A26) | C26: =IF($B$4=0,0,B26/$B$4) | D26: 0.3
A27: Savings | B27: =SUMIFS($C$7:$C$20,$B$7:$B$20,A27) | C27: =IF($B$4=0,0,B27/$B$4) | D27: 0.2
A28: Unplanned income | B28: =B4-C21

Sheet Spending
A1: Spending log
A2: One line per purchase
A4: Date | B4: Category | C4: Amount | D4: Note
A5: 46296 | B5: Phone & internet | C5: 18 | D5: sample
A6: 46297 | B6: Dining out | C6: 22.22 | D6: sample
A7: 46298 | B7: Rent / mortgage | C7: 350 | D7: sample
A8: 46299 | B8: Shopping | C8: 37.5 | D8: sample
A9: 46300 | B9: Phone & internet | C9: 11.25 | D9: sample
A10: 46301 | B10: Rent / mortgage | C10: 175 | D10: sample
A11: 46302 | B11: Transport | C11: 55 | D11: sample
A12: 46303 | B12: Utilities | C12: 25.71 | D12: sample
A13: 46304 | B13: Dining out | C13: 50 | D13: sample
A14: 46305 | B14: Transport | C14: 55 | D14: sample
A15: 46306 | B15: Shopping | C15: 21.43 | D15: sample
A16: 46307 | B16: Rent / mortgage | C16: 175 | D16: sample
... A44: 46307 | B44: Shopping | C44: 21.43 | D44: sample
