Workbook

Sheet Start here
A1: Budget Planner 2026
A2: Free template · templates.snoutsmith.com
B4: WHAT IT DOES
B5: Plan and track every month of 2026: log income and spending, see income, expenses, savings and what is left, and watch the year build up on one dashboard.
B7: HOW TO USE
B8: 1. List your categories on Settings (Income, Expense or Savings).
B9: 2. Log each transaction on its month tab: date, category, type, amount.
B10: 3. Open Year to see the whole year and the chart (it fills itself).
B12: GOOD TO KNOW
B13: • Type is picked from the list – Income, Expense or Savings.
B14: • Totals and charts update by themselves.
B15: • Sample data is filled in for January–October so you can see how it works: select the tinted rows on each month and press Delete.
B17: Tinted cells are yours to type in. Grey numbers are formulas – leave them. Works in Google Sheets (File → Import or open the .xlsx) and Excel, free plans, no add-ons or scripts.

Sheet Settings
A1: Settings
A2: Edit these lists – every month tab uses them
A5: Category | B5: Type
A6: Salary | B6: Income
A7: Side income | B7: Income
A8: Rent | B8: Expense
A9: Groceries | B9: Expense
A10: Utilities | B10: Expense
A11: Transport | B11: Expense
A12: Dining out | B12: Expense
A13: Shopping | B13: Expense
A14: Health | B14: Expense
A15: Fun | B15: Expense
A16: Savings | B16: Savings
A17: Debt payment | B17: Savings

Sheet Year
A1: 2026 at a glance
A2: Pulled from the 12 month tabs – nothing to type here
A4: Month | B4: Income | C4: Expenses | D4: Saved | E4: Left
A5: Jan | B5: ='Jan'!A5 | C5: ='Jan'!B5 | D5: ='Jan'!C5 | E5: ='Jan'!D5
A6: Feb | B6: ='Feb'!A5 | C6: ='Feb'!B5 | D6: ='Feb'!C5 | E6: ='Feb'!D5
A7: Mar | B7: ='Mar'!A5 | C7: ='Mar'!B5 | D7: ='Mar'!C5 | E7: ='Mar'!D5
A8: Apr | B8: ='Apr'!A5 | C8: ='Apr'!B5 | D8: ='Apr'!C5 | E8: ='Apr'!D5
A9: May | B9: ='May'!A5 | C9: ='May'!B5 | D9: ='May'!C5 | E9: ='May'!D5
A10: Jun | B10: ='Jun'!A5 | C10: ='Jun'!B5 | D10: ='Jun'!C5 | E10: ='Jun'!D5
A11: Jul | B11: ='Jul'!A5 | C11: ='Jul'!B5 | D11: ='Jul'!C5 | E11: ='Jul'!D5
A12: Aug | B12: ='Aug'!A5 | C12: ='Aug'!B5 | D12: ='Aug'!C5 | E12: ='Aug'!D5
A13: Sep | B13: ='Sep'!A5 | C13: ='Sep'!B5 | D13: ='Sep'!C5 | E13: ='Sep'!D5
A14: Oct | B14: ='Oct'!A5 | C14: ='Oct'!B5 | D14: ='Oct'!C5 | E14: ='Oct'!D5
A15: Nov | B15: ='Nov'!A5 | C15: ='Nov'!B5 | D15: ='Nov'!C5 | E15: ='Nov'!D5
A16: Dec | B16: ='Dec'!A5 | C16: ='Dec'!B5 | D16: ='Dec'!C5 | E16: ='Dec'!D5
A17: Year | B17: =SUM(B5:B16) | C17: =SUM(C5:C16) | D17: =SUM(D5:D16) | E17: =SUM(E5:E16)

Sheet Jan
A1: January 2026
A2: One line per transaction
A4: INCOME | B4: EXPENSES | C4: SAVED | D4: LEFT
A5: =SUMIFS(D8:D67,C8:C67,"Income") | B5: =SUMIFS(D8:D67,C8:C67,"Expense") | C5: =SUMIFS(D8:D67,C8:C67,"Savings") | D5: =SUMIFS(D8:D67,C8:C67,"Income")-SUMIFS(D8:D67,C8:C67,"<>Income")
A7: Date | B7: Category | C7: Type | D7: Amount | E7: Note
A8: 46023 | B8: Salary | C8: Income | D8: 3680.62
A9: 46024 | B9: Side income | C9: Income | D9: 531.35
A10: 46025 | B10: Groceries | C10: Expense | D10: 113.2
A11: 46026 | B11: Fun | C11: Expense | D11: 307.97
A12: 46027 | B12: Fun | C12: Expense | D12: 265.86
A13: 46028 | B13: Transport | C13: Expense | D13: 51.14
A14: 46029 | B14: Rent | C14: Expense | D14: 358.93
A15: 46030 | B15: Health | C15: Expense | D15: 181.62
A16: 46031 | B16: Rent | C16: Expense | D16: 282.9
A17: 46032 | B17: Dining out | C17: Expense | D17: 292.79
A18: 46033 | B18: Transport | C18: Expense | D18: 242.59
A19: 46034 | B19: Groceries | C19: Expense | D19: 362.05
... A23: 46038 | B23: Health | C23: Expense | D23: 294.45

Sheet Feb
A1: February 2026
A2: One line per transaction
A4: INCOME | B4: EXPENSES | C4: SAVED | D4: LEFT
A5: =SUMIFS(D8:D67,C8:C67,"Income") | B5: =SUMIFS(D8:D67,C8:C67,"Expense") | C5: =SUMIFS(D8:D67,C8:C67,"Savings") | D5: =SUMIFS(D8:D67,C8:C67,"Income")-SUMIFS(D8:D67,C8:C67,"<>Income")
A7: Date | B7: Category | C7: Type | D7: Amount | E7: Note
A8: 46054 | B8: Salary | C8: Income | D8: 3916.58
A9: 46055 | B9: Side income | C9: Income | D9: 493.67
A10: 46056 | B10: Fun | C10: Expense | D10: 227.85
A11: 46057 | B11: Shopping | C11: Expense | D11: 103.88
A12: 46058 | B12: Transport | C12: Expense | D12: 307.96
A13: 46059 | B13: Dining out | C13: Expense | D13: 371.71
A14: 46060 | B14: Health | C14: Expense | D14: 337.47
A15: 46061 | B15: Savings | C15: Savings | D15: 370.04
A16: 46062 | B16: Groceries | C16: Expense | D16: 86.57
A17: 46063 | B17: Dining out | C17: Expense | D17: 61.54
A18: 46064 | B18: Shopping | C18: Expense | D18: 359.8
A19: 46065 | B19: Savings | C19: Savings | D19: 375.53
... A23: 46069 | B23: Fun | C23: Expense | D23: 340.79

Sheet Mar
A1: March 2026
A2: One line per transaction
A4: INCOME | B4: EXPENSES | C4: SAVED | D4: LEFT
A5: =SUMIFS(D8:D67,C8:C67,"Income") | B5: =SUMIFS(D8:D67,C8:C67,"Expense") | C5: =SUMIFS(D8:D67,C8:C67,"Savings") | D5: =SUMIFS(D8:D67,C8:C67,"Income")-SUMIFS(D8:D67,C8:C67,"<>Income")
A7: Date | B7: Category | C7: Type | D7: Amount | E7: Note
A8: 46082 | B8: Salary | C8: Income | D8: 3903.17
A9: 46083 | B9: Side income | C9: Income | D9: 415.05
A10: 46084 | B10: Rent | C10: Expense | D10: 199.89
A11: 46085 | B11: Health | C11: Expense | D11: 174.51
A12: 46086 | B12: Utilities | C12: Expense | D12: 156.34
A13: 46087 | B13: Shopping | C13: Expense | D13: 48.29
A14: 46088 | B14: Savings | C14: Savings | D14: 56.55
A15: 46089 | B15: Utilities | C15: Expense | D15: 215.56
A16: 46090 | B16: Health | C16: Expense | D16: 157.65
A17: 46091 | B17: Rent | C17: Expense | D17: 195.69
A18: 46092 | B18: Dining out | C18: Expense | D18: 285.8
A19: 46093 | B19: Debt payment | C19: Savings | D19: 243.38
... A23: 46097 | B23: Savings | C23: Savings | D23: 369.23

Sheet Apr
A1: April 2026
A2: One line per transaction
A4: INCOME | B4: EXPENSES | C4: SAVED | D4: LEFT
A5: =SUMIFS(D8:D67,C8:C67,"Income") | B5: =SUMIFS(D8:D67,C8:C67,"Expense") | C5: =SUMIFS(D8:D67,C8:C67,"Savings") | D5: =SUMIFS(D8:D67,C8:C67,"Income")-SUMIFS(D8:D67,C8:C67,"<>Income")
A7: Date | B7: Category | C7: Type | D7: Amount | E7: Note
A8: 46113 | B8: Salary | C8: Income | D8: 3929
A9: 46114 | B9: Side income | C9: Income | D9: 332
A10: 46115 | B10: Shopping | C10: Expense | D10: 381.7
A11: 46116 | B11: Debt payment | C11: Savings | D11: 151.01
A12: 46117 | B12: Dining out | C12: Expense | D12: 268.8
A13: 46118 | B13: Debt payment | C13: Savings | D13: 383.49
A14: 46119 | B14: Rent | C14: Expense | D14: 162.72
A15: 46120 | B15: Savings | C15: Savings | D15: 326.52
A16: 46121 | B16: Savings | C16: Savings | D16: 314.3
A17: 46122 | B17: Transport | C17: Expense | D17: 179.04
A18: 46123 | B18: Rent | C18: Expense | D18: 200.22
A19: 46124 | B19: Shopping | C19: Expense | D19: 234.45
... A23: 46128 | B23: Rent | C23: Expense | D23: 222.31

Sheet May
A1: May 2026
A2: One line per transaction
A4: INCOME | B4: EXPENSES | C4: SAVED | D4: LEFT
A5: =SUMIFS(D8:D67,C8:C67,"Income") | B5: =SUMIFS(D8:D67,C8:C67,"Expense") | C5: =SUMIFS(D8:D67,C8:C67,"Savings") | D5: =SUMIFS(D8:D67,C8:C67,"Income")-SUMIFS(D8:D67,C8:C67,"<>Income")
A7: Date | B7: Category | C7: Type | D7: Amount | E7: Note
A8: 46143 | B8: Salary | C8: Income | D8: 3974.09
A9: 46144 | B9: Side income | C9: Income | D9: 425.6
A10: 46145 | B10: Fun | C10: Expense | D10: 245.94
A11: 46146 | B11: Transport | C11: Expense | D11: 259.62
A12: 46147 | B12: Savings | C12: Savings | D12: 240.02
A13: 46148 | B13: Groceries | C13: Expense | D13: 322.4
A14: 46149 | B14: Dining out | C14: Expense | D14: 27.5
A15: 46150 | B15: Groceries | C15: Expense | D15: 47.05
A16: 46151 | B16: Rent | C16: Expense | D16: 189.4
A17: 46152 | B17: Dining out | C17: Expense | D17: 111.08
A18: 46153 | B18: Groceries | C18: Expense | D18: 321.96
A19: 46154 | B19: Utilities | C19: Expense | D19: 147.6
... A23: 46158 | B23: Dining out | C23: Expense | D23: 190.06

Sheet Jun
A1: June 2026
A2: One line per transaction
A4: INCOME | B4: EXPENSES | C4: SAVED | D4: LEFT
A5: =SUMIFS(D8:D67,C8:C67,"Income") | B5: =SUMIFS(D8:D67,C8:C67,"Expense") | C5: =SUMIFS(D8:D67,C8:C67,"Savings") | D5: =SUMIFS(D8:D67,C8:C67,"Income")-SUMIFS(D8:D67,C8:C67,"<>Income")
A7: Date | B7: Category | C7: Type | D7: Amount | E7: Note
A8: 46174 | B8: Salary | C8: Income | D8: 3793.2
A9: 46175 | B9: Side income | C9: Income | D9: 363.2
A10: 46176 | B10: Rent | C10: Expense | D10: 135.12
A11: 46177 | B11: Shopping | C11: Expense | D11: 177.05
A12: 46178 | B12: Transport | C12: Expense | D12: 114.49
A13: 46179 | B13: Dining out | C13: Expense | D13: 361.43
A14: 46180 | B14: Savings | C14: Savings | D14: 391.04
A15: 46181 | B15: Debt payment | C15: Savings | D15: 181.19
A16: 46182 | B16: Rent | C16: Expense | D16: 101.77
A17: 46183 | B17: Health | C17: Expense | D17: 71.39
A18: 46184 | B18: Utilities | C18: Expense | D18: 186.58
A19: 46185 | B19: Savings | C19: Savings | D19: 276.1
... A23: 46189 | B23: Health | C23: Expense | D23: 274.84

Sheet Jul
A1: July 2026
A2: One line per transaction
A4: INCOME | B4: EXPENSES | C4: SAVED | D4: LEFT
A5: =SUMIFS(D8:D67,C8:C67,"Income") | B5: =SUMIFS(D8:D67,C8:C67,"Expense") | C5: =SUMIFS(D8:D67,C8:C67,"Savings") | D5: =SUMIFS(D8:D67,C8:C67,"Income")-SUMIFS(D8:D67,C8:C67,"<>Income")
A7: Date | B7: Category | C7: Type | D7: Amount | E7: Note
A8: 46204 | B8: Salary | C8: Income | D8: 4082.03
A9: 46205 | B9: Side income | C9: Income | D9: 446.92
A10: 46206 | B10: Health | C10: Expense | D10: 37.63
A11: 46207 | B11: Dining out | C11: Expense | D11: 63.39
A12: 46208 | B12: Transport | C12: Expense | D12: 352.08
A13: 46209 | B13: Dining out | C13: Expense | D13: 42.23
A14: 46210 | B14: Groceries | C14: Expense | D14: 134.49
A15: 46211 | B15: Dining out | C15: Expense | D15: 301.38
A16: 46212 | B16: Health | C16: Expense | D16: 232.5
A17: 46213 | B17: Utilities | C17: Expense | D17: 18.26
A18: 46214 | B18: Rent | C18: Expense | D18: 242.37
A19: 46215 | B19: Transport | C19: Expense | D19: 385.45
... A23: 46219 | B23: Groceries | C23: Expense | D23: 94.22

Sheet Aug
A1: August 2026
A2: One line per transaction
A4: INCOME | B4: EXPENSES | C4: SAVED | D4: LEFT
A5: =SUMIFS(D8:D67,C8:C67,"Income") | B5: =SUMIFS(D8:D67,C8:C67,"Expense") | C5: =SUMIFS(D8:D67,C8:C67,"Savings") | D5: =SUMIFS(D8:D67,C8:C67,"Income")-SUMIFS(D8:D67,C8:C67,"<>Income")
A7: Date | B7: Category | C7: Type | D7: Amount | E7: Note
A8: 46235 | B8: Salary | C8: Income | D8: 4004.49
A9: 46236 | B9: Side income | C9: Income | D9: 344.83
A10: 46237 | B10: Transport | C10: Expense | D10: 204.56
A11: 46238 | B11: Health | C11: Expense | D11: 128.99
A12: 46239 | B12: Fun | C12: Expense | D12: 21.62
A13: 46240 | B13: Debt payment | C13: Savings | D13: 350.57
A14: 46241 | B14: Dining out | C14: Expense | D14: 21.97
A15: 46242 | B15: Transport | C15: Expense | D15: 345.15
A16: 46243 | B16: Debt payment | C16: Savings | D16: 316.34
A17: 46244 | B17: Shopping | C17: Expense | D17: 180.26
A18: 46245 | B18: Dining out | C18: Expense | D18: 274.67
A19: 46246 | B19: Health | C19: Expense | D19: 373.89
... A23: 46250 | B23: Rent | C23: Expense | D23: 47.6

Sheet Sep
A1: September 2026
A2: One line per transaction
A4: INCOME | B4: EXPENSES | C4: SAVED | D4: LEFT
A5: =SUMIFS(D8:D67,C8:C67,"Income") | B5: =SUMIFS(D8:D67,C8:C67,"Expense") | C5: =SUMIFS(D8:D67,C8:C67,"Savings") | D5: =SUMIFS(D8:D67,C8:C67,"Income")-SUMIFS(D8:D67,C8:C67,"<>Income")
A7: Date | B7: Category | C7: Type | D7: Amount | E7: Note
A8: 46266 | B8: Salary | C8: Income | D8: 3701.82
A9: 46267 | B9: Side income | C9: Income | D9: 559.94
A10: 46268 | B10: Transport | C10: Expense | D10: 118.18
A11: 46269 | B11: Shopping | C11: Expense | D11: 246.08
A12: 46270 | B12: Dining out | C12: Expense | D12: 156.72
A13: 46271 | B13: Shopping | C13: Expense | D13: 58.86
A14: 46272 | B14: Transport | C14: Expense | D14: 348.96
A15: 46273 | B15: Debt payment | C15: Savings | D15: 315.12
A16: 46274 | B16: Fun | C16: Expense | D16: 67.11
A17: 46275 | B17: Savings | C17: Savings | D17: 311.55
A18: 46276 | B18: Shopping | C18: Expense | D18: 30.07
A19: 46277 | B19: Groceries | C19: Expense | D19: 161.39
... A23: 46281 | B23: Health | C23: Expense | D23: 44.51

Sheet Oct
A1: October 2026
A2: One line per transaction
A4: INCOME | B4: EXPENSES | C4: SAVED | D4: LEFT
A5: =SUMIFS(D8:D67,C8:C67,"Income") | B5: =SUMIFS(D8:D67,C8:C67,"Expense") | C5: =SUMIFS(D8:D67,C8:C67,"Savings") | D5: =SUMIFS(D8:D67,C8:C67,"Income")-SUMIFS(D8:D67,C8:C67,"<>Income")
A7: Date | B7: Category | C7: Type | D7: Amount | E7: Note
A8: 46296 | B8: Salary | C8: Income | D8: 3930.16
A9: 46297 | B9: Side income | C9: Income | D9: 404.68
A10: 46298 | B10: Dining out | C10: Expense | D10: 155.48
A11: 46299 | B11: Dining out | C11: Expense | D11: 232.31
A12: 46300 | B12: Groceries | C12: Expense | D12: 191.24
A13: 46301 | B13: Dining out | C13: Expense | D13: 56.48
A14: 46302 | B14: Rent | C14: Expense | D14: 333.69
A15: 46303 | B15: Rent | C15: Expense | D15: 251.27
A16: 46304 | B16: Rent | C16: Expense | D16: 50.3
A17: 46305 | B17: Groceries | C17: Expense | D17: 333.06
A18: 46306 | B18: Rent | C18: Expense | D18: 87.35
A19: 46307 | B19: Debt payment | C19: Savings | D19: 177.09
... A23: 46311 | B23: Health | C23: Expense | D23: 325.5

Sheet Nov
A1: November 2026
A2: One line per transaction
A4: INCOME | B4: EXPENSES | C4: SAVED | D4: LEFT
A5: =SUMIFS(D8:D67,C8:C67,"Income") | B5: =SUMIFS(D8:D67,C8:C67,"Expense") | C5: =SUMIFS(D8:D67,C8:C67,"Savings") | D5: =SUMIFS(D8:D67,C8:C67,"Income")-SUMIFS(D8:D67,C8:C67,"<>Income")
A7: Date | B7: Category | C7: Type | D7: Amount | E7: Note

Sheet Dec
A1: December 2026
A2: One line per transaction
A4: INCOME | B4: EXPENSES | C4: SAVED | D4: LEFT
A5: =SUMIFS(D8:D67,C8:C67,"Income") | B5: =SUMIFS(D8:D67,C8:C67,"Expense") | C5: =SUMIFS(D8:D67,C8:C67,"Savings") | D5: =SUMIFS(D8:D67,C8:C67,"Income")-SUMIFS(D8:D67,C8:C67,"<>Income")
A7: Date | B7: Category | C7: Type | D7: Amount | E7: Note
